Workbook

Sheet Mecânica
C35: Disponível | D35: Pago | E35: %
B36: GERENTE COMERCIAL | C36: 0 | D36: 0 | E36: =IFERROR(D36/C36,) -> 0
B37: GERENTE DE VENDAS | C37: 0 | D37: 0 | E37: =IFERROR(D37/C37,) -> 0
B38: SUPERVISORES/CONSULTORES | C38: =300*2+500*2+750 -> 2350 | D38: 0 | E38: =IFERROR(D38/C38,) -> 0
B39: VENDEDORES | C39: =16*300 -> 4800 | D39: 0 | E39: =IFERROR(D39/C39,) -> 0
B40: MERCHANDISING EXTERNO | C40: 0 | D40: 0 | E40: =IFERROR(D40/C40,) -> 0
B41: MERCHANDISING INTERNO | C41: 0 | D41: 0 | E41: =IFERROR(D41/C41,) -> 0
B42: TOTAL | C42: =SUM(C35:C41) -> 7150 | D42: =SUM(D35:D41) -> 0 | E42: =IFERROR(D42/C42,) -> 0

Sheet Top Contas
C43: Disponível | D43: Pago | E43: %
B44: GERENTE COMERCIAL | C44: 0 | D44: 0 | E44: =IFERROR(D44/C44,) -> 0
B45: GERENTE DE VENDAS | C45: 0 | D45: 0 | E45: =IFERROR(D45/C45,) -> 0
B46: SUPERVISORES/CONSULTORES | C46: 0 | D46: 0 | E46: =IFERROR(D46/C46,) -> 0
B47: VENDEDORES | C47: 33600 | D47: 900 | E47: =IFERROR(D47/C47,) -> 0.026785714
B48: MERCHANDISING EXTERNO | C48: 0 | D48: 0 | E48: =IFERROR(D48/C48,) -> 0
B49: MERCHANDISING INTERNO | C49: 0 | D49: 0 | E49: =IFERROR(D49/C49,) -> 0
B50: TOTAL | C50: =SUM(C43:C49) -> 33600 | D50: =SUM(D43:D49) -> 900 | E50: =IFERROR(D50/C50,) -> 0.026785714

Sheet VENCEDORES
B3: CÓD | C3: ÁREA | D3: VENDEDOR/REPRESENTANTE | E3: TOP CONTAS | F3: % | G3: LOJA PERFEITA | H3: PONTOS
B4: 4054 | C4: MC-ARA D | D4: RAFAEL IZIDIO DE FARIAS | E4: 1039.625 | F4: 1.7304217 | G4: 81.883056 | H4: 300
B5: 3655 | C5: KA-BNU | D5: NATHAN FREITAS FUZINATO | E5: 3134.992 | F5: 1.523884 | G5: 83.07277 | H5: 300
B6: 3919 | C6: MC-TBCR D | D6: GISLAINE BORGES RODRIGUES | E6: 2809.707 | F6: 1.2974361 | G6: 79.834421
B7: 4066 | C7: MC-BNU D | D7: MURIEL DERCIO VOCKES | E7: 402.167 | F7: 1.2549639 | G7: 85.578333 | H7: 300
B8: 771 | C8: MC-FLP D | D8: JOAO JOSE NASCIMENTO | E8: 761.767 | F8: 1.0516404 | G8: 78.904167
B9: 179 | C9: KA-BRQ | D9: PEDRO PAULO ECCEL | E9: 1739.875 | F9: 0.98943851 | G9: 74.015278
B10: 3956 | C10: MC-IMB D | D10: RAFAEL BERNARDO VIEIRA | E10: 405.834 | F10: 0.73533905 | G10: 87.269444
B11: 359 | C11: MC-ITPE D | D11: MARCELO SCHEFFLER | E11: 1177.79 | F11: 0.58524215 | G11: 84.385

Sheet Geral
E3: EQUIPE | F3: REDE | G3: Q1 - JULHO A SETEMBRO | O3: JULHO | S3: AGOSTO | W3: SETEMBRO | AB3: Q2 - OUTUBRO A DEZEMBRO | AJ3: OUTUBRO | AN3: NOVEMBRO | AR3: DEZEMBRO | AW3: Q3 - JANEIRO A MARÇO | BE3: JANEIRO | BI3: FEVEREIRO | BM3: MARÇO | BR3: Q4 - ABRIL A JUNHO | BZ3: ABRIL | CD3: MAIO | CH3: JUNHO | CM3: TOP CONTAS FY26 ANO FISCAL
G4: HIST | H4: META | I4: FAT | J4: BONIF | K4: MÁQ | L4: % META | M4: % HIST | N4: GAP META | O4: HIST | P4: FAT | Q4: BONIF | R4: MÁQ | S4: HIST | T4: FAT | U4: BONIF | V4: MÁQ | W4: HIST | X4: FAT | Y4: BONIF | Z4: MÁQ | AB4: HIST | AC4: META | AD4: FAT | AE4: BONIF | AF4: MÁQ | AG4: % META | AH4: % HIST | AI4: GAP META | AJ4: HIST | AK4: FAT | AL4: BONIF | AM4: MÁQ | AN4: HIST | AO4: FAT | AP4: BONIF | AQ4: MÁQ | AR4: HIST | AS4: FAT | AT4: BONIF | AU4: MÁQ | AW4: HIST | AX4: META | AY4: FAT | AZ4: BONIF | BA4: MÁQ | BB4: % META | BC4: % HIST | BD4: GAP META | BE4: HIST | BF4: FAT | BG4: BONIF | BH4: MÁQ | BI4: HIST | BJ4: FAT | BK4: BONIF | BL4: MÁQ | BM4: HIST | BN4: FAT | BO4: BONIF | BP4: MÁQ | BR4: HIST | BS4: META | BT4: FAT | BU4: BONIF | BV4: MÁQ | BW4: % META | BX4: % HIST | BY4: GAP META | BZ4: HIST | CA4: FAT | CB4: BONIF | CC4: MÁQ | CD4: HIST | CE4: FAT | CF4: BONIF | CG4: MÁQ | CH4: HIST | CI4: FAT | CJ4: BONIF | CK4: MÁQ | CM4: HIST | CN4: META | CO4: FAT | CP4: BONIF | CQ4: MÁQ | CR4: % META | CS4: % HIST | CT4: GAP META
E5: FLP-SUL MC/KA D | F5: =SUMIF($B:$B,$E5,$F:$F) -> 8 | G5: =SUMIF(Rede!$C:$C,Geral!E5,Rede!$G:$G) -> 7355.454 | H5: =SUMIF(Rede!$C:$C,Geral!E5,Rede!$H:$H) -> 5014.67 | I5: =SUMIF(Rede!$C:$C,Geral!E5,Rede!$I:$I) -> 8042.895 | J5: =SUMIF(Rede!$C:$C,Geral!E5,Rede!$J:$J) -> 76.083 | K5: =SUMIF(Rede!$C:$C,Geral!E5,Rede!$K:$K) -> 0 | L5: =IFERROR((I5+K5+J5)/H5,0) -> 1.6190453 | M5: =IFERROR(((I5+K5+J5)/G5-1),0) -> 0.10380379 | N5: =H5-I5-J5-K5 -> -3104.308 | O5: =SUMIF(Rede!$C:$C,Geral!$E5,Rede!$O:$O) -> 672.315 | P5: =SUMIF(Rede!$C:$C,Geral!$E5,Rede!$P:$P) -> 965.562 | Q5: =SUMIF(Rede!$C:$C,Geral!$E5,Rede!$Q:$Q) -> 32.5 | R5: =SUMIF(Rede!$C:$C,Geral!$E5,Rede!$R:$R) -> 0 | S5: =SUMIF(Rede!$C:$C,Geral!$E5,Rede!$S:$S) -> 2531.329 | T5: =SUMIF(Rede!$C:$C,Geral!$E5,Rede!$T:$T) -> 2637.221 | U5: =SUMIF(Rede!$C:$C,Geral!$E5,Rede!$U:$U) -> 22.583 | V5: =SUMIF(Rede!$C:$C,Geral!$E5,Rede!$V:$V) -> 0 | W5: =SUMIF(Rede!$C:$C,Geral!$E5,Rede!$W:$W) -> 4151.81 | X5: =SUMIF(Rede!$C:$C,Geral!$E5,Rede!$X:$X) -> 4440.112 | Y5: =SUMIF(Rede!$C:$C,Geral!$E5,Rede!$Y:$Y) -> 21 | Z5: =SUMIF(Rede!$C:$C,Geral!$E5,Rede!$Z:$Z) -> 0 | AB5: =SUMIF(Rede!C:C,Geral!E5,Rede!$AB:$AB) -> 5155.36 | AC5: =SUMIF(Rede!C:C,Geral!E5,Rede!$AC:$AC) -> 4298.2769 | AD5: =SUMIF(Rede!C:C,Geral!E5,Rede!$AD:$AD) -> 4664.462 | AE5: =SUMIF(Rede!$C:$C,Geral!$E5,Rede!$AE:$AE) -> 121.375 | AF5: =SUMIF(Rede!C:C,Geral!E5,Rede!$AF:$AF) -> 0 | AG5: =(AD5+AF5+AE5)/AC5 -> 1.1134315 | AH5: =IFERROR(((AD5+AF5+AE5)/AB5-1),0) -> -0.071677439 | AI5: =AC5-AD5-AF5-AE5 -> -487.56007 | AJ5: =SUMIF(Rede!$C:$C,Geral!$E5,Rede!$AJ:$AJ) -> 2689.487 | AK5: =SUMIF(Rede!$C:$C,Geral!$E5,Rede!$AK:$AK) -> 1002.691 | AL5: =SUMIF(Rede!$C:$C,Geral!$E5,Rede!$AL:$AL) -> 45.125 | AM5: =SUMIF(Rede!$C:$C,Geral!$E5,Rede!$AM:$AM) -> 0 | AN5: =SUMIF(Rede!$C:$C,Geral!$E5,Rede!$AN:$AN) -> 577.554 | AO5: =SUMIF(Rede!$C:$C,Geral!$E5,Rede!$AO:$AO) -> 1355.487 | AP5: =SUMIF(Rede!$C:$C,Geral!$E5,Rede!$AP:$AP) -> 21.25 | AQ5: =SUMIF(Rede!$C:$C,Geral!$E5,Rede!$AQ:$AQ) -> 0 | AR5: =SUMIF(Rede!$C:$C,Geral!$E5,Rede!$AR:$AR) -> 1888.319 | AS5: =SUMIF(Rede!$C:$C,Geral!$E5,Rede!$AS:$AS) -> 2306.284 | AT5: =SUMIF(Rede!$C:$C,Geral!$E5,Rede!$AT:$AT) -> 55 | AU5: =SUMIF(Rede!$C:$C,Geral!$E5,Rede!$AU:$AU) -> 0 | AW5: =SUMIF(Rede!$C:$C,Geral!E5,Rede!$AW:$AW) -> 2879.008 | AX5: =SUMIF(Rede!$C:$C,Geral!E5,Rede!$AX:$AX) -> 4042.6382 | AY5: =SUMIF(Rede!$C:$C,Geral!E5,Rede!$AY:$AY) -> 4785.059 | AZ5: =SUMIF(Rede!$C:$C,Geral!E5,Rede!$AZ:$AZ) -> 231.874 | BA5: =SUMIF(Rede!$C:$C,Geral!E5,Rede!$BA:$BA) -> 0 | BB5: =(AY5+AZ5+BA5)/AX5 -> 1.2410047 | BC5: =IFERROR(((AY5+AZ5+BA5)/AW5-1),0) -> 0.74259085 | BD5: =AX5-AY5-BA5-AZ5 -> -974.29482 | BE5: =SUMIF(Rede!$C:$C,Geral!E5,Rede!$BE:$BE) -> 978.18 | BF5: =SUMIF(Rede!$C:$C,Geral!E5,Rede!$BF:$BF) -> 1112.809 | BG5: =SUMIF(Rede!$C:$C,Geral!E5,Rede!$BG:$BG) -> 38.833 | BH5: =SUMIF(Rede!$C:$C,Geral!E5,Rede!$BH:$BH) -> 0 | BI5: =SUMIF(Rede!$C:$C,Geral!E5,Rede!$BI:$BI) -> 705.655 | BJ5: =SUMIF(Rede!$C:$C,Geral!E5,Rede!$BJ:$BJ) -> 878.167 | BK5: =SUMIF(Rede!$C:$C,Geral!E5,Rede!$BK:$BK) -> 30.833 | BL5: =SUMIF(Rede!$C:$C,Geral!E5,Rede!$BL:$BL) -> 0 | BM5: =SUMIF(Rede!$C:$C,Geral!E5,Rede!$BM:$BM) -> 1195.173 | BN5: =SUMIF(Rede!$C:$C,Geral!E5,Rede!$BN:$BN) -> 2794.083 | BO5: =SUMIF(Rede!$C:$C,Geral!E5,Rede!$BO:$BO) -> 162.208 | BP5: =SUMIF(Rede!$C:$C,Geral!E5,Rede!$BP:$BP) -> 0 | BR5: =SUMIF(Rede!$C:$C,Geral!E5,Rede!$BR:$BR) -> 1380.273 | BS5: =SUMIF(Rede!$C:$C,Geral!E5,Rede!$BS:$BS) -> 4311 | BT5: =SUMIF(Rede!$C:$C,Geral!E5,Rede!$BT:$BT) -> 2336.748 | BU5: =SUMIF(Rede!$C:$C,Geral!E5,Rede!$BU:$BU) -> 0 | BV5: =SUMIF(Rede!$C:$C,Geral!E5,Rede!$BV:$BV) -> 67.333 | BW5: =(BT5+BU5+BV5)/BS5 -> 0.55766203 | BX5: =IFERROR(((BT5+BU5+BV5)/BR5-1),0) -> 0.74174312 | BY5: =BS5-BT5-BU5-BV5 -> 1906.919 | BZ5: =SUMIF(Rede!$C:$C,Geral!E5,Rede!$BZ:$BZ) -> 181.166 | CA5: =SUMIF(Rede!$C:$C,Geral!E5,Rede!$CA:$CA) -> 425.417 | CB5: =SUMIF(Rede!$C:$C,Geral!E5,Rede!$CB:$CB) -> 24.75 | CC5: =SUMIF(Rede!$C:$C,Geral!E5,Rede!$CC:$CC) -> 0 | CD5: =SUMIF(Rede!$C:$C,Geral!E5,Rede!$CD:$CD) -> 731.418 | CE5: =SUMIF(Rede!$C:$C,Geral!E5,Rede!$CE:$CE) -> 1002.013 | CF5: =SUMIF(Rede!$C:$C,Geral!E5,Rede!$CF:$CF) -> 21.083 | CG5: =SUMIF(Rede!$C:$C,Geral!E5,Rede!$CG:$CG) -> 0 | CH5: =SUMIF(Rede!$C:$C,Geral!E5,Rede!$CH:$CH) -> 467.689 | CI5: =SUMIF(Rede!$C:$C,Geral!E5,Rede!$CI:$CI) -> 909.318 | CJ5: =SUMIF(Rede!$C:$C,Geral!E5,Rede!$CJ:$CJ) -> 21.5 | CK5: =SUMIF(Rede!$C:$C,Geral!E5,Rede!$CK:$CK) -> 0 | CM5: =G5+AB5+AW5+BR5 -> 16770.095 | CN5: =H5+AC5+AX5+BS5 -> 17666.585 | CO5: =I5+AD5+AY5+BT5 -> 19829.164 | CP5: =J5+AE5+AZ5+BU5 -> 429.332 | CQ5: =K5+AF5+BA5+BV5 -> 67.333 | CR5: =(CO5+CP5+CQ5)/CN5 -> 1.1505239 | CS5: =IFERROR(((CO5+CP5+CQ5)/CM5-1),0) -> 0.21202826 | CT5: =CN5-CO5-CQ5-CP5 -> -2659.2439
E6: NORTE MC/KA D | F6: =SUMIF($B:$B,$E6,$F:$F) -> 6 | G6: =SUMIF(Rede!$C:$C,Geral!E6,Rede!$G:$G) -> 6984.345 | H6: =SUMIF(Rede!$C:$C,Geral!E6,Rede!$H:$H) -> 7627.01 | I6: =SUMIF(Rede!$C:$C,Geral!E6,Rede!$I:$I) -> 7415.409 | J6: =SUMIF(Rede!$C:$C,Geral!E6,Rede!$J:$J) -> 49.417 | K6: =SUMIF(Rede!$C:$C,Geral!E6,Rede!$K:$K) -> 0 | L6: =IFERROR((I6+K6+J6)/H6,0) -> 0.97873557 | M6: =IFERROR(((I6+K6+J6)/G6-1),0) -> 0.068793996 | N6: =H6-I6-J6-K6 -> 162.184 | O6: =SUMIF(Rede!$C:$C,Geral!$E6,Rede!$O:$O) -> 1183.824 | P6: =SUMIF(Rede!$C:$C,Geral!$E6,Rede!$P:$P) -> 976.417 | Q6: =SUMIF(Rede!$C:$C,Geral!$E6,Rede!$Q:$Q) -> 21.5 | R6: =SUMIF(Rede!$C:$C,Geral!$E6,Rede!$R:$R) -> 0 | S6: =SUMIF(Rede!$C:$C,Geral!$E6,Rede!$S:$S) -> 2362.854 | T6: =SUMIF(Rede!$C:$C,Geral!$E6,Rede!$T:$T) -> 2796.75 | U6: =SUMIF(Rede!$C:$C,Geral!$E6,Rede!$U:$U) -> 23.417 | V6: =SUMIF(Rede!$C:$C,Geral!$E6,Rede!$V:$V) -> 0 | W6: =SUMIF(Rede!$C:$C,Geral!$E6,Rede!$W:$W) -> 3437.667 | X6: =SUMIF(Rede!$C:$C,Geral!$E6,Rede!$X:$X) -> 3642.242 | Y6: =SUMIF(Rede!$C:$C,Geral!$E6,Rede!$Y:$Y) -> 4.5 | Z6: =SUMIF(Rede!$C:$C,Geral!$E6,Rede!$Z:$Z) -> 0 | AB6: =SUMIF(Rede!C:C,Geral!E6,Rede!$AB:$AB) -> 9176.73 | AC6: =SUMIF(Rede!C:C,Geral!E6,Rede!$AC:$AC) -> 6537.4414 | AD6: =SUMIF(Rede!C:C,Geral!E6,Rede!$AD:$AD) -> 4787.376 | AE6: =SUMIF(Rede!$C:$C,Geral!$E6,Rede!$AE:$AE) -> 42.583 | AF6: =SUMIF(Rede!C:C,Geral!E6,Rede!$AF:$AF) -> 0 | AG6: =(AD6+AF6+AE6)/AC6 -> 0.73881489 | AH6: =IFERROR(((AD6+AF6+AE6)/AB6-1),0) -> -0.47367319 | AI6: =AC6-AD6-AF6-AE6 -> 1707.4824 | AJ6: =SUMIF(Rede!$C:$C,Geral!$E6,Rede!$AJ:$AJ) -> 3747.229 | AK6: =SUMIF(Rede!$C:$C,Geral!$E6,Rede!$AK:$AK) -> 1864.833 | AL6: =SUMIF(Rede!$C:$C,Geral!$E6,Rede!$AL:$AL) -> 0 | AM6: =SUMIF(Rede!$C:$C,Geral!$E6,Rede!$AM:$AM) -> 0 | AN6: =SUMIF(Rede!$C:$C,Geral!$E6,Rede!$AN:$AN) -> 3037.917 | AO6: =SUMIF(Rede!$C:$C,Geral!$E6,Rede!$AO:$AO) -> 1235.876 | AP6: =SUMIF(Rede!$C:$C,Geral!$E6,Rede!$AP:$AP) -> 11.583 | AQ6: =SUMIF(Rede!$C:$C,Geral!$E6,Rede!$AQ:$AQ) -> 0 | AR6: =SUMIF(Rede!$C:$C,Geral!$E6,Rede!$AR:$AR) -> 2391.584 | AS6: =SUMIF(Rede!$C:$C,Geral!$E6,Rede!$AS:$AS) -> 1686.667 | AT6: =SUMIF(Rede!$C:$C,Geral!$E6,Rede!$AT:$AT) -> 31 | AU6: =SUMIF(Rede!$C:$C,Geral!$E6,Rede!$AU:$AU) -> 0 | AW6: =SUMIF(Rede!$C:$C,Geral!E6,Rede!$AW:$AW) -> 5615.021 | AX6: =SUMIF(Rede!$C:$C,Geral!E6,Rede!$AX:$AX) -> 6148.629 | AY6: =SUMIF(Rede!$C:$C,Geral!E6,Rede!$AY:$AY) -> 6309.574 | AZ6: =SUMIF(Rede!$C:$C,Geral!E6,Rede!$AZ:$AZ) -> 145.25 | BA6: =SUMIF(Rede!$C:$C,Geral!E6,Rede!$BA:$BA) -> 0 | BB6: =(AY6+AZ6+BA6)/AX6 -> 1.0497989 | BC6: =IFERROR(((AY6+AZ6+BA6)/AW6-1),0) -> 0.14956364 | BD6: =AX6-AY6-BA6-AZ6 -> -306.19503 | BE6: =SUMIF(Rede!$C:$C,Geral!E6,Rede!$BE:$BE) -> 1086.667 | BF6: =SUMIF(Rede!$C:$C,Geral!E6,Rede!$BF:$BF) -> 1425.708 | BG6: =SUMIF(Rede!$C:$C,Geral!E6,Rede!$BG:$BG) -> 21.75 | BH6: =SUMIF(Rede!$C:$C,Geral!E6,Rede!$BH:$BH) -> 0 | BI6: =SUMIF(Rede!$C:$C,Geral!E6,Rede!$BI:$BI) -> 1754.396 | BJ6: =SUMIF(Rede!$C:$C,Geral!E6,Rede!$BJ:$BJ) -> 2214.325 | BK6: =SUMIF(Rede!$C:$C,Geral!E6,Rede!$BK:$BK) -> 39.5 | BL6: =SUMIF(Rede!$C:$C,Geral!E6,Rede!$BL:$BL) -> 0 | BM6: =SUMIF(Rede!$C:$C,Geral!E6,Rede!$BM:$BM) -> 2773.958 | BN6: =SUMIF(Rede!$C:$C,Geral!E6,Rede!$BN:$BN) -> 2669.541 | BO6: =SUMIF(Rede!$C:$C,Geral!E6,Rede!$BO:$BO) -> 84 | BP6: =SUMIF(Rede!$C:$C,Geral!E6,Rede!$BP:$BP) -> 0 | BR6: =SUMIF(Rede!$C:$C,Geral!E6,Rede!$BR:$BR) -> 3588.429 | BS6: =SUMIF(Rede!$C:$C,Geral!E6,Rede!$BS:$BS) -> 6546 | BT6: =SUMIF(Rede!$C:$C,Geral!E6,Rede!$BT:$BT) -> 3378.96 | BU6: =SUMIF(Rede!$C:$C,Geral!E6,Rede!$BU:$BU) -> 225 | BV6: =SUMIF(Rede!$C:$C,Geral!E6,Rede!$BV:$BV) -> 132.5 | BW6: =(BT6+BU6+BV6)/BS6 -> 0.57080049 | BX6: =IFERROR(((BT6+BU6+BV6)/BR6-1),0) -> 0.041252314 | BY6: =BS6-BT6-BU6-BV6 -> 2809.54 | BZ6: =SUMIF(Rede!$C:$C,Geral!E6,Rede!$BZ:$BZ) -> 899.887 | CA6: =SUMIF(Rede!$C:$C,Geral!E6,Rede!$CA:$CA) -> 802.604 | CB6: =SUMIF(Rede!$C:$C,Geral!E6,Rede!$CB:$CB) -> 34.125 | CC6: =SUMIF(Rede!$C:$C,Geral!E6,Rede!$CC:$CC) -> 0 | CD6: =SUMIF(Rede!$C:$C,Geral!E6,Rede!$CD:$CD) -> 1268.625 | CE6: =SUMIF(Rede!$C:$C,Geral!E6,Rede!$CE:$CE) -> 1878.918 | CF6: =SUMIF(Rede!$C:$C,Geral!E6,Rede!$CF:$CF) -> 26.584 | CG6: =SUMIF(Rede!$C:$C,Geral!E6,Rede!$CG:$CG) -> 0 | CH6: =SUMIF(Rede!$C:$C,Geral!E6,Rede!$CH:$CH) -> 1419.917 | CI6: =SUMIF(Rede!$C:$C,Geral!E6,Rede!$CI:$CI) -> 697.438 | CJ6: =SUMIF(Rede!$C:$C,Geral!E6,Rede!$CJ:$CJ) -> 71.791 | CK6: =SUMIF(Rede!$C:$C,Geral!E6,Rede!$CK:$CK) -> 225 | CM6: =G6+AB6+AW6+BR6 -> 25364.525 | CN6: =H6+AC6+AX6+BS6 -> 26859.08 | CO6: =I6+AD6+AY6+BT6 -> 21891.319 | CP6: =J6+AE6+AZ6+BU6 -> 462.25 | CQ6: =K6+AF6+BA6+BV6 -> 132.5 | CR6: =(CO6+CP6+CQ6)/CN6 -> 0.83718686 | CS6: =IFERROR(((CO6+CP6+CQ6)/CM6-1),0) -> -0.11348354 | CT6: =CN6-CO6-CQ6-CP6 -> 4373.0113
F7: =SUM(F5:F6) -> 14 | G7: =SUM(G5:G6) -> 14339.799 | H7: =SUM(H5:H6) -> 12641.68 | I7: =SUM(I5:I6) -> 15458.304 | J7: =SUM(J5:J6) -> 125.5 | K7: =SUM(K5:K6) -> 0 | L7: =IFERROR((I7+K7+J7)/H7,0) -> 1.232732 | M7: =IFERROR(((I7+K7+J7)/G7-1),0) -> 0.086751913 | N7: =H7-I7-J7-K7 -> -2942.124 | O7: =SUM(O5:O6) -> 1856.139 | P7: =SUM(P5:P6) -> 1941.979 | Q7: =SUM(Q5:Q6) -> 54 | R7: =SUM(R5:R6) -> 0 | S7: =SUM(S5:S6) -> 4894.183 | T7: =SUM(T5:T6) -> 5433.971 | U7: =SUM(U5:U6) -> 46 | V7: =SUM(V5:V6) -> 0 | ... Z7: =SUM(Z5:Z6) -> 0 | AB7: =SUM(AB5:AB6) -> 14332.09 | AC7: =SUM(AC5:AC6) -> 10835.718 | AD7: =SUM(AD5:AD6) -> 9451.838 | AE7: =SUM(AE5:AE6) -> 163.958 | AF7: =SUM(AF5:AF6) -> 0 | AG7: =(AD7+AF7+AE7)/AC7 -> 0.88741657 | AH7: =IFERROR(((AD7+AF7+AE7)/AB7-1),0) -> -0.32907231 | AI7: =AC7-AD7-AF7-AE7 -> 1219.9223 | AJ7: =SUM(AJ5:AJ6) -> 6436.716 | AK7: =SUM(AK5:AK6) -> 2867.524 | AL7: =SUM(AL5:AL6) -> 45.125 | AM7: =SUM(AM5:AM6) -> 0 | AN7: =SUM(AN5:AN6) -> 3615.471 | AO7: =SUM(AO5:AO6) -> 2591.363 | AP7: =SUM(AP5:AP6) -> 32.833 | AQ7: =SUM(AQ5:AQ6) -> 0 | ... AU7: =SUM(AU5:AU6) -> 0 | AW7: =SUM(AW5:AW6) -> 8494.029 | AX7: =SUM(AX5:AX6) -> 10191.267 | AY7: =SUM(AY5:AY6) -> 11094.633 | AZ7: =SUM(AZ5:AZ6) -> 377.124 | BA7: =SUM(BA5:BA6) -> 0 | BB7: =(AY7+AZ7+BA7)/AX7 -> 1.1256458 | BC7: =IFERROR(((AY7+AZ7+BA7)/AW7-1),0) -> 0.3505672 | BD7: =AX7-AY7-BA7-AZ7 -> -1280.4899 | BE7: =SUM(BE5:BE6) -> 2064.847 | BF7: =SUM(BF5:BF6) -> 2538.517 | BG7: =SUM(BG5:BG6) -> 60.583 | BH7: =SUM(BH5:BH6) -> 0 | BI7: =SUM(BI5:BI6) -> 2460.051 | BJ7: =SUM(BJ5:BJ6) -> 3092.492 | BK7: =SUM(BK5:BK6) -> 70.333 | BL7: =SUM(BL5:BL6) -> 0 | ... BP7: =SUM(BP5:BP6) -> 0 | BR7: =SUM(BR5:BR6) -> 4968.702 | BS7: =SUM(BS5:BS6) -> 10857 | BT7: =SUM(BT5:BT6) -> 5715.708 | BU7: =SUM(BU5:BU6) -> 225 | BV7: =SUM(BV5:BV6) -> 199.833 | BW7: =(BT7+BU7+BV7)/BS7 -> 0.56558359 | BX7: =IFERROR(((BT7+BU7+BV7)/BR7-1),0) -> 0.23584409 | BY7: =BS7-BT7-BU7-BV7 -> 4716.459 | BZ7: =SUM(BZ5:BZ6) -> 1081.053 | CA7: =SUM(CA5:CA6) -> 1228.021 | CB7: =SUM(CB5:CB6) -> 58.875 | CC7: =SUM(CC5:CC6) -> 0 | CD7: =SUM(CD5:CD6) -> 2000.043 | CE7: =SUM(CE5:CE6) -> 2880.931 | CF7: =SUM(CF5:CF6) -> 47.667 | CG7: =SUM(CG5:CG6) -> 0 | ... CK7: =SUM(CK5:CK6) -> 225 | CM7: =SUM(CM5:CM6) -> 42134.62 | CN7: =SUM(CN5:CN6) -> 44525.665 | CO7: =SUM(CO5:CO6) -> 41720.483 | CP7: =SUM(CP5:CP6) -> 891.582 | CQ7: =SUM(CQ5:CQ6) -> 199.833 | CR7: =(CO7+CP7+CQ7)/CN7 -> 0.96151057 | CS7: =IFERROR(((CO7+CP7+CQ7)/CM7-1),0) -> 0.016074145 | CT7: =CN7-CO7-CQ7-CP7 -> 1713.7674
E8: ATUALIZADO:
E9: 46197
B10: JOHNSON - TOP CONTAS FY26 | F10: REDE | G10: Q1 - JULHO A SETEMBRO | O10: JULHO | S10: AGOSTO | W10: SETEMBRO | AB10: Q2 - OUTUBRO A DEZEMBRO | AJ10: OUTUBRO | AN10: NOVEMBRO | AR10: DEZEMBRO | AW10: Q3 - JANEIRO A MARÇO | BE10: JANEIRO | BI10: FEVEREIRO | BM10: MARÇO | BR10: Q4 - ABRIL A JUNHO | BZ10: ABRIL | CD10: MAIO | CH10: JUNHO | CM10: TOP CONTAS FY26 ANO FISCAL
B11: EQUIPE | C11: CÓD | D11: ÁREA | E11: VENDEDOR/REPRESENTANTE | G11: HIST | H11: META | I11: FAT | J11: BONIF | K11: MÁQ | L11: % META | M11: % HIST | N11: GAP META | O11: HIST | P11: FAT | Q11: BONIF | R11: MÁQ | S11: HIST | T11: FAT | U11: BONIF | V11: MÁQ | W11: HIST | X11: FAT | Y11: BONIF | Z11: MÁQ | AB11: HIST | AC11: META | AD11: FAT | AE11: BONIF | AF11: MÁQ | AG11: % META | AH11: % HIST | AI11: GAP META | AJ11: HIST | AK11: FAT | AL11: BONIF | AM11: MÁQ | AN11: HIST | AO11: FAT | AP11: BONIF | AQ11: MÁQ | AR11: HIST | AS11: FAT | AT11: BONIF | AU11: MÁQ | AW11: HIST | AX11: META | AY11: FAT | AZ11: BONIF | BA11: MÁQ | BB11: % META | BC11: % HIST | BD11: GAP META | BE11: HIST | BF11: FAT | BG11: BONIF | BH11: MÁQ | BI11: HIST | BJ11: FAT | BK11: BONIF | BL11: MÁQ | BM11: HIST | BN11: FAT | BO11: BONIF | BP11: MÁQ | BR11: HIST | BS11: META | BT11: FAT | BU11: BONIF | BV11: MÁQ | BW11: % META | BX11: % HIST | BY11: GAP META | BZ11: HIST | CA11: FAT | CB11: BONIF | CC11: MÁQ | CD11: HIST | CE11: FAT | CF11: BONIF | CG11: MÁQ | CH11: HIST | CI11: FAT | CJ11: BONIF | CK11: MÁQ | CM11: HIST | CN11: META | CO11: FAT | CP11: BONIF | CQ11: MÁQ | CR11: % META | CS11: % HIST | CT11: GAP META
B12: FLP-SUL MC/KA D | C12: 771 | D12: MC-FLP D | E12: JOAO JOSE NASCIMENTO | F12: =COUNTIF(Rede!$D:$D,Geral!$C12) -> 1 | G12: =SUMIF(Rede!$D:$D,Geral!C12,Rede!$G:$G) -> 1650.944 | H12: =SUMIF(Rede!$D:$D,Geral!C12,Rede!$H:$H) -> 898.53 | I12: =SUMIF(Rede!$D:$D,Geral!C12,Rede!$I:$I) -> 690.575 | J12: =SUMIF(Rede!$D:$D,Geral!$C12,Rede!$J:$J) -> 0 | K12: =SUMIF(Rede!$D:$D,Geral!C12,Rede!$K:$K) -> 0 | L12: =IFERROR((I12+K12+J12)/H12,0) -> 0.76856087 | M12: =IFERROR(((I12+K12+J12)/G12-1),0) -> -0.58170901 | N12: =H12-I12-J12-K12 -> 207.955 | O12: =SUMIF(Rede!$D:$D,Geral!$C12,Rede!$O:$O) -> 270.844 | P12: =SUMIF(Rede!$D:$D,Geral!$C12,Rede!$P:$P) -> 10.708 | Q12: =SUMIF(Rede!$D:$D,Geral!$C12,Rede!$Q:$Q) -> 0 | R12: =SUMIF(Rede!$D:$D,Geral!$C12,Rede!$R:$R) -> 0 | S12: =SUMIF(Rede!$D:$D,Geral!$C12,Rede!$S:$S) -> 854.558 | T12: =SUMIF(Rede!$D:$D,Geral!$C12,Rede!$T:$T) -> 803.7 | U12: =SUMIF(Rede!$D:$D,Geral!$C12,Rede!$U:$U) -> 0 | V12: =SUMIF(Rede!$D:$D,Geral!$C12,Rede!$V:$V) -> 0 | W12: =SUMIF(Rede!$D:$D,Geral!$C12,Rede!$W:$W) -> 525.542 | X12: =SUMIF(Rede!$D:$D,Geral!$C12,Rede!$X:$X) -> -123.833 | Y12: =SUMIF(Rede!$D:$D,Geral!$C12,Rede!$Y:$Y) -> 0 | Z12: =SUMIF(Rede!$D:$D,Geral!$C12,Rede!$Z:$Z) -> 0 | AB12: =SUMIF(Rede!D:D,Geral!C12,Rede!$AB:$AB) -> 1068.366 | AC12: =SUMIF(Rede!D:D,Geral!C12,Rede!$AC:$AC) -> 770.16614 | AD12: =SUMIF(Rede!D:D,Geral!C12,Rede!$AD:$AD) -> 557.392 | AE12: =SUMIF(Rede!$D:$D,Geral!$C12,Rede!$AE:$AE) -> 0 | AF12: =SUMIF(Rede!D:D,Geral!C12,Rede!$AF:$AF) -> 0 | AG12: =(AD12+AF12+AE12)/AC12 -> 0.72372955 | AH12: =IFERROR(((AD12+AF12+AE12)/AB12-1),0) -> -0.47827617 | AI12: =AC12-AD12-AF12-AE12 -> 212.77414 | AJ12: =SUMIF(Rede!$D:$D,Geral!$C12,Rede!$AJ:$AJ) -> 814.133 | AK12: =SUMIF(Rede!$D:$D,Geral!$C12,Rede!$AK:$AK) -> 230.108 | AL12: =SUMIF(Rede!$D:$D,Geral!$C12,Rede!$AL:$AL) -> 0 | AM12: =SUMIF(Rede!$D:$D,Geral!$C12,Rede!$AM:$AM) -> 0 | AN12: =SUMIF(Rede!$D:$D,Geral!$C12,Rede!$AN:$AN) -> 111.858 | AO12: =SUMIF(Rede!$D:$D,Geral!$C12,Rede!$AO:$AO) -> 158.5 | AP12: =SUMIF(Rede!$D:$D,Geral!$C12,Rede!$AP:$AP) -> 0 | AQ12: =SUMIF(Rede!$D:$D,Geral!$C12,Rede!$AQ:$AQ) -> 0 | AR12: =SUMIF(Rede!$D:$D,Geral!$C12,Rede!$AR:$AR) -> 142.375 | AS12: =SUMIF(Rede!$D:$D,Geral!$C12,Rede!$AS:$AS) -> 168.784 | AT12: =SUMIF(Rede!$D:$D,Geral!$C12,Rede!$AT:$AT) -> 0 | AU12: =SUMIF(Rede!$D:$D,Geral!$C12,Rede!$AU:$AU) -> 0 | AW12: =SUMIF(Rede!$D:$D,Geral!C12,Rede!$AW:$AW) -> 455.592 | AX12: =SUMIF(Rede!$D:$D,Geral!C12,Rede!$AX:$AX) -> 724.36074 | AY12: =SUMIF(Rede!$D:$D,Geral!C12,Rede!$AY:$AY) -> 761.767 | AZ12: =SUMIF(Rede!$D:$D,Geral!C12,Rede!$AZ:$AZ) -> 0 | BA12: =SUMIF(Rede!$D:$D,Geral!C12,Rede!$BA:$BA) -> 0 | BB12: =(AY12+AZ12+BA12)/AX12 -> 1.0516404 | BC12: =IFERROR(((AY12+AZ12+BA12)/AW12-1),0) -> 0.6720377 | BD12: =AX12-AY12-BA12-AZ12 -> -37.40626 | BE12: =SUMIF(Rede!$D:$D,Geral!C12,Rede!$BE:$BE) -> 286.55 | BF12: =SUMIF(Rede!$D:$D,Geral!C12,Rede!$BF:$BF) -> 102.017 | BG12: =SUMIF(Rede!$D:$D,Geral!C12,Rede!$BG:$BG) -> 0 | BH12: =SUMIF(Rede!D:D,Geral!C12,Rede!$BH:$BH) -> 0 | BI12: =SUMIF(Rede!$D:$D,Geral!C12,Rede!$BI:$BI) -> 82.959 | BJ12: =SUMIF(Rede!$D:$D,Geral!C12,Rede!$BJ:$BJ) -> 68.25 | BK12: =SUMIF(Rede!$D:$D,Geral!C12,Rede!$BK:$BK) -> 0 | BL12: =SUMIF(Rede!$D:$D,Geral!C12,Rede!$BL:$BL) -> 0 | BM12: =SUMIF(Rede!$D:$D,Geral!C12,Rede!$BM:$BM) -> 86.083 | BN12: =SUMIF(Rede!$D:$D,Geral!C12,Rede!$BN:$BN) -> 591.5 | BO12: =SUMIF(Rede!$D:$D,Geral!C12,Rede!$BO:$BO) -> 0 | BP12: =SUMIF(Rede!$D:$D,Geral!C12,Rede!$BP:$BP) -> 0 | BR12: =SUMIF(Rede!$D:$D,Geral!C12,Rede!$BR:$BR) -> 151.605 | BS12: =SUMIF(Rede!$D:$D,Geral!C12,Rede!$BS:$BS) -> 771 | BT12: =SUMIF(Rede!$D:$D,Geral!C12,Rede!$BT:$BT) -> 79.889 | BU12: =SUMIF(Rede!$D:$D,Geral!C12,Rede!$BU:$BU) -> 0 | BV12: =SUMIF(Rede!$D:$D,Geral!C12,Rede!$BV:$BV) -> 0 | BW12: =(BT12+BU12+BV12)/BS12 -> 0.10361738 | BX12: =IFERROR(((BT12+BU12+BV12)/BR12-1),0) -> -0.47304508 | BY12: =BS12-BT12-BU12-BV12 -> 691.111 | BZ12: =SUMIF(Rede!$D:$D,Geral!C12,Rede!$BZ:$BZ) -> 24.083 | CA12: =SUMIF(Rede!$D:$D,Geral!C12,Rede!$CA:$CA) -> -121 | CB12: =SUMIF(Rede!$D:$D,Geral!C12,Rede!$CB:$CB) -> 0 | CC12: =SUMIF(Rede!$D:$D,Geral!C12,Rede!$CC:$CC) -> 0 | CD12: =SUMIF(Rede!$D:$D,Geral!C12,Rede!$CD:$CD) -> 59.867 | CE12: =SUMIF(Rede!$D:$D,Geral!C12,Rede!$CE:$CE) -> 111.25 | CF12: =SUMIF(Rede!$D:$D,Geral!C12,Rede!$CF:$CF) -> 0 | CG12: =SUMIF(Rede!$D:$D,Geral!C12,Rede!$CG:$CG) -> 0 | CH12: =SUMIF(Rede!$D:$D,Geral!C12,Rede!$CH:$CH) -> 67.655 | CI12: =SUMIF(Rede!$D:$D,Geral!C12,Rede!$CI:$CI) -> 89.639 | CJ12: =SUMIF(Rede!$D:$D,Geral!C12,Rede!$CJ:$CJ) -> 0 | CK12: =SUMIF(Rede!$D:$D,Geral!C12,Rede!$CK:$CK) -> 0 | CM12: =G12+AB12+AW12+BR12 -> 3326.507 | CN12: =H12+AC12+AX12+BS12 -> 3164.0569 | CO12: =I12+AD12+AY12+BT12 -> 2089.623 | CP12: =J12+AE12+AZ12+BU12 -> 0 | CQ12: =K12+AF12+BA12+BV12 -> 0 | CR12: =(CO12+CP12+CQ12)/CN12 -> 0.66042523 | CS12: =IFERROR(((CO12+CP12+CQ12)/CM12-1),0) -> -0.37182666 | CT12: =CN12-CO12-CQ12-CP12 -> 1074.4339
B13: FLP-SUL MC/KA D | C13: 3919 | D13: MC-TBCR D | E13: GISLAINE BORGES RODRIGUES | F13: =COUNTIF(Rede!$D:$D,Geral!$C13) -> 4 | G13: =SUMIF(Rede!$D:$D,Geral!C13,Rede!$G:$G) -> 3551.218 | H13: =SUMIF(Rede!$D:$D,Geral!C13,Rede!$H:$H) -> 2686.29 | I13: =SUMIF(Rede!$D:$D,Geral!C13,Rede!$I:$I) -> 5346.376 | J13: =SUMIF(Rede!$D:$D,Geral!$C13,Rede!$J:$J) -> 75.083 | K13: =SUMIF(Rede!$D:$D,Geral!C13,Rede!$K:$K) -> 0 | L13: =IFERROR((I13+K13+J13)/H13,0) -> 2.0181957 | M13: =IFERROR(((I13+K13+J13)/G13-1),0) -> 0.52664776 | N13: =H13-I13-J13-K13 -> -2735.169 | O13: =SUMIF(Rede!$D:$D,Geral!$C13,Rede!$O:$O) -> 214.888 | P13: =SUMIF(Rede!$D:$D,Geral!$C13,Rede!$P:$P) -> 750.521 | Q13: =SUMIF(Rede!$D:$D,Geral!$C13,Rede!$Q:$Q) -> 31.5 | R13: =SUMIF(Rede!$D:$D,Geral!$C13,Rede!$R:$R) -> 0 | S13: =SUMIF(Rede!$D:$D,Geral!$C13,Rede!$S:$S) -> 307.271 | T13: =SUMIF(Rede!$D:$D,Geral!$C13,Rede!$T:$T) -> 1621.521 | U13: =SUMIF(Rede!$D:$D,Geral!$C13,Rede!$U:$U) -> 22.583 | V13: =SUMIF(Rede!$D:$D,Geral!$C13,Rede!$V:$V) -> 0 | W13: =SUMIF(Rede!$D:$D,Geral!$C13,Rede!$W:$W) -> 3029.059 | X13: =SUMIF(Rede!$D:$D,Geral!$C13,Rede!$X:$X) -> 2974.334 | Y13: =SUMIF(Rede!$D:$D,Geral!$C13,Rede!$Y:$Y) -> 21 | Z13: =SUMIF(Rede!$D:$D,Geral!$C13,Rede!$Z:$Z) -> 0 | AB13: =SUMIF(Rede!D:D,Geral!C13,Rede!$AB:$AB) -> 3310.571 | AC13: =SUMIF(Rede!D:D,Geral!C13,Rede!$AC:$AC) -> 2302.5261 | AD13: =SUMIF(Rede!D:D,Geral!C13,Rede!$AD:$AD) -> 3064.618 | AE13: =SUMIF(Rede!$D:$D,Geral!$C13,Rede!$AE:$AE) -> 90.375 | AF13: =SUMIF(Rede!D:D,Geral!C13,Rede!$AF:$AF) -> 0 | AG13: =(AD13+AF13+AE13)/AC13 -> 1.3702311 | AH13: =IFERROR(((AD13+AF13+AE13)/AB13-1),0) -> -0.04699431 | AI13: =AC13-AD13-AF13-AE13 -> -852.46689 | AJ13: =SUMIF(Rede!$D:$D,Geral!$C13,Rede!$AJ:$AJ) -> 1575.708 | AK13: =SUMIF(Rede!$D:$D,Geral!$C13,Rede!$AK:$AK) -> 631.833 | AL13: =SUMIF(Rede!$D:$D,Geral!$C13,Rede!$AL:$AL) -> 41.625 | AM13: =SUMIF(Rede!$D:$D,Geral!$C13,Rede!$AM:$AM) -> 0 | AN13: =SUMIF(Rede!$D:$D,Geral!$C13,Rede!$AN:$AN) -> 313.613 | AO13: =SUMIF(Rede!$D:$D,Geral!$C13,Rede!$AO:$AO) -> 1032.952 | AP13: =SUMIF(Rede!$D:$D,Geral!$C13,Rede!$AP:$AP) -> 18 | AQ13: =SUMIF(Rede!$D:$D,Geral!$C13,Rede!$AQ:$AQ) -> 0 | AR13: =SUMIF(Rede!$D:$D,Geral!$C13,Rede!$AR:$AR) -> 1421.25 | AS13: =SUMIF(Rede!$D:$D,Geral!$C13,Rede!$AS:$AS) -> 1399.833 | AT13: =SUMIF(Rede!$D:$D,Geral!$C13,Rede!$AT:$AT) -> 30.75 | AU13: =SUMIF(Rede!$D:$D,Geral!$C13,Rede!$AU:$AU) -> 0 | AW13: =SUMIF(Rede!$D:$D,Geral!C13,Rede!$AW:$AW) -> 1272.979 | AX13: =SUMIF(Rede!$D:$D,Geral!C13,Rede!$AX:$AX) -> 2165.5841 | AY13: =SUMIF(Rede!$D:$D,Geral!C13,Rede!$AY:$AY) -> 2641.541 | AZ13: =SUMIF(Rede!$D:$D,Geral!C13,Rede!$AZ:$AZ) -> 168.166 | BA13: =SUMIF(Rede!$D:$D,Geral!C13,Rede!$BA:$BA) -> 0 | BB13: =(AY13+AZ13+BA13)/AX13 -> 1.2974361 | BC13: =IFERROR(((AY13+AZ13+BA13)/AW13-1),0) -> 1.2071904 | BD13: =AX13-AY13-BA13-AZ13 -> -644.12295 | BE13: =SUMIF(Rede!D:D,Geral!C13,Rede!$BE:$BE) -> 210.538 | BF13: =SUMIF(Rede!D:D,Geral!C13,Rede!$BF:$BF) -> 664.625 | BG13: =SUMIF(Rede!D:D,Geral!C13,Rede!$BG:$BG) -> 33.833 | BH13: =SUMIF(Rede!D:D,Geral!C13,Rede!$BH:$BH) -> 0 | BI13: =SUMIF(Rede!$D:$D,Geral!C13,Rede!$BI:$BI) -> 351.755 | BJ13: =SUMIF(Rede!$D:$D,Geral!C13,Rede!$BJ:$BJ) -> 666.583 | BK13: =SUMIF(Rede!$D:$D,Geral!C13,Rede!$BK:$BK) -> 30.833 | BL13: =SUMIF(Rede!$D:$D,Geral!C13,Rede!$BL:$BL) -> 0 | BM13: =SUMIF(Rede!$D:$D,Geral!C13,Rede!$BM:$BM) -> 710.686 | BN13: =SUMIF(Rede!$D:$D,Geral!C13,Rede!$BN:$BN) -> 1310.333 | BO13: =SUMIF(Rede!$D:$D,Geral!C13,Rede!$BO:$BO) -> 103.5 | BP13: =SUMIF(Rede!$D:$D,Geral!C13,Rede!$BP:$BP) -> 0 | BR13: =SUMIF(Rede!$D:$D,Geral!C13,Rede!$BR:$BR) -> 640.002 | BS13: =SUMIF(Rede!$D:$D,Geral!C13,Rede!$BS:$BS) -> 2310 | BT13: =SUMIF(Rede!$D:$D,Geral!C13,Rede!$BT:$BT) -> 1492.776 | BU13: =SUMIF(Rede!$D:$D,Geral!C13,Rede!$BU:$BU) -> 0 | BV13: =SUMIF(Rede!$D:$D,Geral!C13,Rede!$BV:$BV) -> 62.583 | BW13: =(BT13+BU13+BV13)/BS13 -> 0.67331558 | BX13: =IFERROR(((BT13+BU13+BV13)/BR13-1),0) -> 1.4302408 | BY13: =BS13-BT13-BU13-BV13 -> 754.641 | BZ13: =SUMIF(Rede!$D:$D,Geral!C13,Rede!$BZ:$BZ) -> 28.959 | CA13: =SUMIF(Rede!$D:$D,Geral!C13,Rede!$CA:$CA) -> 405.501 | CB13: =SUMIF(Rede!$D:$D,Geral!C13,Rede!$CB:$CB) -> 24.75 | CC13: =SUMIF(Rede!$D:$D,Geral!C13,Rede!$CC:$CC) -> 0 | CD13: =SUMIF(Rede!$D:$D,Geral!C13,Rede!$CD:$CD) -> 474.217 | CE13: =SUMIF(Rede!$D:$D,Geral!C13,Rede!$CE:$CE) -> 635.596 | CF13: =SUMIF(Rede!$D:$D,Geral!C13,Rede!$CF:$CF) -> 21.083 | CG13: =SUMIF(Rede!$D:$D,Geral!C13,Rede!$CG:$CG) -> 0 | CH13: =SUMIF(Rede!$D:$D,Geral!C13,Rede!$CH:$CH) -> 136.826 | CI13: =SUMIF(Rede!$D:$D,Geral!C13,Rede!$CI:$CI) -> 451.679 | CJ13: =SUMIF(Rede!$D:$D,Geral!C13,Rede!$CJ:$CJ) -> 16.75 | CK13: =SUMIF(Rede!$D:$D,Geral!C13,Rede!$CK:$CK) -> 0 | CM13: =G13+AB13+AW13+BR13 -> 8774.77 | CN13: =H13+AC13+AX13+BS13 -> 9464.4002 | CO13: =I13+AD13+AY13+BT13 -> 12545.311 | CP13: =J13+AE13+AZ13+BU13 -> 333.624 | CQ13: =K13+AF13+BA13+BV13 -> 62.583 | CR13: =(CO13+CP13+CQ13)/CN13 -> 1.3673891 | CS13: =IFERROR(((CO13+CP13+CQ13)/CM13-1),0) -> 0.47485552 | CT13: =CN13-CO13-CQ13-CP13 -> -3477.1178
B14: FLP-SUL MC/KA D | C14: 3956 | D14: MC-IMB D | E14: RAFAEL BERNARDO VIEIRA | F14: =COUNTIF(Rede!$D:$D,Geral!$C14) -> 1 | G14: =SUMIF(Rede!$D:$D,Geral!C14,Rede!$G:$G) -> 902.167 | H14: =SUMIF(Rede!$D:$D,Geral!C14,Rede!$H:$H) -> 684.6 | I14: =SUMIF(Rede!$D:$D,Geral!C14,Rede!$I:$I) -> 1216.569 | J14: =SUMIF(Rede!$D:$D,Geral!$C14,Rede!$J:$J) -> 0 | K14: =SUMIF(Rede!$D:$D,Geral!C14,Rede!$K:$K) -> 0 | L14: =IFERROR((I14+K14+J14)/H14,0) -> 1.7770508 | M14: =IFERROR(((I14+K14+J14)/G14-1),0) -> 0.34849645 | N14: =H14-I14-J14-K14 -> -531.969 | O14: =SUMIF(Rede!$D:$D,Geral!$C14,Rede!$O:$O) -> 44.625 | P14: =SUMIF(Rede!$D:$D,Geral!$C14,Rede!$P:$P) -> 70.833 | Q14: =SUMIF(Rede!$D:$D,Geral!$C14,Rede!$Q:$Q) -> 0 | R14: =SUMIF(Rede!$D:$D,Geral!$C14,Rede!$R:$R) -> 0 | S14: =SUMIF(Rede!$D:$D,Geral!$C14,Rede!$S:$S) -> 854.875 | T14: =SUMIF(Rede!$D:$D,Geral!$C14,Rede!$T:$T) -> 10.5 | U14: =SUMIF(Rede!$D:$D,Geral!$C14,Rede!$U:$U) -> 0 | V14: =SUMIF(Rede!$D:$D,Geral!$C14,Rede!$V:$V) -> 0 | W14: =SUMIF(Rede!$D:$D,Geral!$C14,Rede!$W:$W) -> 2.667 | X14: =SUMIF(Rede!$D:$D,Geral!$C14,Rede!$X:$X) -> 1135.236 | Y14: =SUMIF(Rede!$D:$D,Geral!$C14,Rede!$Y:$Y) -> 0 | Z14: =SUMIF(Rede!$D:$D,Geral!$C14,Rede!$Z:$Z) -> 0 | AB14: =SUMIF(Rede!D:D,Geral!C14,Rede!$AB:$AB) -> 468.896 | AC14: =SUMIF(Rede!D:D,Geral!C14,Rede!$AC:$AC) -> 586.80029 | AD14: =SUMIF(Rede!D:D,Geral!C14,Rede!$AD:$AD) -> 259.119 | AE14: =SUMIF(Rede!$D:$D,Geral!$C14,Rede!$AE:$AE) -> 3.5 | AF14: =SUMIF(Rede!D:D,Geral!C14,Rede!$AF:$AF) -> 0 | AG14: =(AD14+AF14+AE14)/AC14 -> 0.44754409 | AH14: =IFERROR(((AD14+AF14+AE14)/AB14-1),0) -> -0.43992058 | AI14: =AC14-AD14-AF14-AE14 -> 324.18129 | AJ14: =SUMIF(Rede!$D:$D,Geral!$C14,Rede!$AJ:$AJ) -> 259.313 | AK14: =SUMIF(Rede!$D:$D,Geral!$C14,Rede!$AK:$AK) -> 22.167 | AL14: =SUMIF(Rede!$D:$D,Geral!$C14,Rede!$AL:$AL) -> 3.5 | AM14: =SUMIF(Rede!$D:$D,Geral!$C14,Rede!$AM:$AM) -> 0 | AN14: =SUMIF(Rede!$D:$D,Geral!$C14,Rede!$AN:$AN) -> 15 | AO14: =SUMIF(Rede!$D:$D,Geral!$C14,Rede!$AO:$AO) -> 42.285 | AP14: =SUMIF(Rede!$D:$D,Geral!$C14,Rede!$AP:$AP) -> 0 | AQ14: =SUMIF(Rede!$D:$D,Geral!$C14,Rede!$AQ:$AQ) -> 0 | AR14: =SUMIF(Rede!$D:$D,Geral!$C14,Rede!$AR:$AR) -> 194.583 | AS14: =SUMIF(Rede!$D:$D,Geral!$C14,Rede!$AS:$AS) -> 194.667 | AT14: =SUMIF(Rede!$D:$D,Geral!$C14,Rede!$AT:$AT) -> 0 | AU14: =SUMIF(Rede!$D:$D,Geral!$C14,Rede!$AU:$AU) -> 0 | AW14: =SUMIF(Rede!$D:$D,Geral!C14,Rede!$AW:$AW) -> 660.291 | AX14: =SUMIF(Rede!$D:$D,Geral!C14,Rede!$AX:$AX) -> 551.90051 | AY14: =SUMIF(Rede!$D:$D,Geral!C14,Rede!$AY:$AY) -> 399.251 | AZ14: =SUMIF(Rede!$D:$D,Geral!C14,Rede!$AZ:$AZ) -> 6.583 | BA14: =SUMIF(Rede!$D:$D,Geral!C14,Rede!$BA:$BA) -> 0 | BB14: =(AY14+AZ14+BA14)/AX14 -> 0.73533905 | BC14: =IFERROR(((AY14+AZ14+BA14)/AW14-1),0) -> -0.385371 | BD14: =AX14-AY14-BA14-AZ14 -> 146.06651 | BE14: =SUMIF(Rede!D:D,Geral!C14,Rede!$BE:$BE) -> 281.667 | BF14: =SUMIF(Rede!D:D,Geral!C14,Rede!$BF:$BF) -> 183.667 | BG14: =SUMIF(Rede!D:D,Geral!C14,Rede!$BG:$BG) -> 5 | BH14: =SUMIF(Rede!D:D,Geral!C14,Rede!$BH:$BH) -> 0 | BI14: =SUMIF(Rede!$D:$D,Geral!C14,Rede!$BI:$BI) -> 202.666 | BJ14: =SUMIF(Rede!$D:$D,Geral!C14,Rede!$BJ:$BJ) -> 37.334 | BK14: =SUMIF(Rede!$D:$D,Geral!C14,Rede!$BK:$BK) -> 0 | BL14: =SUMIF(Rede!$D:$D,Geral!C14,Rede!$BL:$BL) -> 0 | BM14: =SUMIF(Rede!$D:$D,Geral!C14,Rede!$BM:$BM) -> 175.958 | BN14: =SUMIF(Rede!$D:$D,Geral!C14,Rede!$BN:$BN) -> 178.25 | BO14: =SUMIF(Rede!$D:$D,Geral!C14,Rede!$BO:$BO) -> 1.583 | BP14: =SUMIF(Rede!$D:$D,Geral!C14,Rede!$BP:$BP) -> 0 | BR14: =SUMIF(Rede!$D:$D,Geral!C14,Rede!$BR:$BR) -> 181.833 | BS14: =SUMIF(Rede!$D:$D,Geral!C14,Rede!$BS:$BS) -> 588 | BT14: =SUMIF(Rede!$D:$D,Geral!C14,Rede!$BT:$BT) -> 202.083 | BU14: =SUMIF(Rede!$D:$D,Geral!C14,Rede!$BU:$BU) -> 0 | BV14: =SUMIF(Rede!$D:$D,Geral!C14,Rede!$BV:$BV) -> 4.75 | BW14: =(BT14+BU14+BV14)/BS14 -> 0.3517568 | BX14: =IFERROR(((BT14+BU14+BV14)/BR14-1),0) -> 0.13748879 | BY14: =BS14-BT14-BU14-BV14 -> 381.167 | BZ14: =SUMIF(Rede!$D:$D,Geral!C14,Rede!$BZ:$BZ) -> 50.791 | CA14: =SUMIF(Rede!$D:$D,Geral!C14,Rede!$CA:$CA) -> 102.458 | CB14: =SUMIF(Rede!$D:$D,Geral!C14,Rede!$CB:$CB) -> 0 | CC14: =SUMIF(Rede!$D:$D,Geral!C14,Rede!$CC:$CC) -> 0 | CD14: =SUMIF(Rede!$D:$D,Geral!C14,Rede!$CD:$CD) -> 73.334 | CE14: =SUMIF(Rede!$D:$D,Geral!C14,Rede!$CE:$CE) -> 50.167 | CF14: =SUMIF(Rede!$D:$D,Geral!C14,Rede!$CF:$CF) -> 0 | CG14: =SUMIF(Rede!$D:$D,Geral!C14,Rede!$CG:$CG) -> 0 | CH14: =SUMIF(Rede!$D:$D,Geral!C14,Rede!$CH:$CH) -> 57.708 | CI14: =SUMIF(Rede!$D:$D,Geral!C14,Rede!$CI:$CI) -> 49.458 | CJ14: =SUMIF(Rede!$D:$D,Geral!C14,Rede!$CJ:$CJ) -> 4.75 | CK14: =SUMIF(Rede!$D:$D,Geral!C14,Rede!$CK:$CK) -> 0 | CM14: =G14+AB14+AW14+BR14 -> 2213.187 | CN14: =H14+AC14+AX14+BS14 -> 2411.3008 | CO14: =I14+AD14+AY14+BT14 -> 2077.022 | CP14: =J14+AE14+AZ14+BU14 -> 10.083 | CQ14: =K14+AF14+BA14+BV14 -> 4.75 | CR14: =(CO14+CP14+CQ14)/CN14 -> 0.86752138 | CS14: =IFERROR(((CO14+CP14+CQ14)/CM14-1),0) -> -0.054822299 | CT14: =CN14-CO14-CQ14-CP14 -> 319.4458
B15: FLP-SUL MC/KA D | C15: 4054 | D15: MC-ARA D | E15: RAFAEL IZIDIO DE FARIAS | F15: =COUNTIF(Rede!$D:$D,Geral!$C15) -> 2 | G15: =SUMIF(Rede!$D:$D,Geral!C15,Rede!$G:$G) -> 1251.125 | H15: =SUMIF(Rede!$D:$D,Geral!C15,Rede!$H:$H) -> 745.25 | I15: =SUMIF(Rede!$D:$D,Geral!C15,Rede!$I:$I) -> 789.375 | J15: =SUMIF(Rede!$D:$D,Geral!$C15,Rede!$J:$J) -> 1 | K15: =SUMIF(Rede!$D:$D,Geral!C15,Rede!$K:$K) -> 0 | L15: =IFERROR((I15+K15+J15)/H15,0) -> 1.0605502 | M15: =IFERROR(((I15+K15+J15)/G15-1),0) -> -0.36826856 | N15: =H15-I15-J15-K15 -> -45.125 | O15: =SUMIF(Rede!$D:$D,Geral!$C15,Rede!$O:$O) -> 141.958 | P15: =SUMIF(Rede!$D:$D,Geral!$C15,Rede!$P:$P) -> 133.5 | Q15: =SUMIF(Rede!$D:$D,Geral!$C15,Rede!$Q:$Q) -> 1 | R15: =SUMIF(Rede!$D:$D,Geral!$C15,Rede!$R:$R) -> 0 | S15: =SUMIF(Rede!$D:$D,Geral!$C15,Rede!$S:$S) -> 514.625 | T15: =SUMIF(Rede!$D:$D,Geral!$C15,Rede!$T:$T) -> 201.5 | U15: =SUMIF(Rede!$D:$D,Geral!$C15,Rede!$U:$U) -> 0 | V15: =SUMIF(Rede!$D:$D,Geral!$C15,Rede!$V:$V) -> 0 | W15: =SUMIF(Rede!$D:$D,Geral!$C15,Rede!$W:$W) -> 594.542 | X15: =SUMIF(Rede!$D:$D,Geral!$C15,Rede!$X:$X) -> 454.375 | Y15: =SUMIF(Rede!$D:$D,Geral!$C15,Rede!$Y:$Y) -> 0 | Z15: =SUMIF(Rede!$D:$D,Geral!$C15,Rede!$Z:$Z) -> 0 | AB15: =SUMIF(Rede!D:D,Geral!C15,Rede!$AB:$AB) -> 307.527 | AC15: =SUMIF(Rede!D:D,Geral!C15,Rede!$AC:$AC) -> 638.78438 | AD15: =SUMIF(Rede!D:D,Geral!C15,Rede!$AD:$AD) -> 783.333 | AE15: =SUMIF(Rede!$D:$D,Geral!$C15,Rede!$AE:$AE) -> 27.5 | AF15: =SUMIF(Rede!D:D,Geral!C15,Rede!$AF:$AF) -> 0 | AG15: =(AD15+AF15+AE15)/AC15 -> 1.2693375 | AH15: =IFERROR(((AD15+AF15+AE15)/AB15-1),0) -> 1.6366238 | AI15: =AC15-AD15-AF15-AE15 -> -172.04862 | AJ15: =SUMIF(Rede!$D:$D,Geral!$C15,Rede!$AJ:$AJ) -> 40.333 | AK15: =SUMIF(Rede!$D:$D,Geral!$C15,Rede!$AK:$AK) -> 118.583 | AL15: =SUMIF(Rede!$D:$D,Geral!$C15,Rede!$AL:$AL) -> 0 | AM15: =SUMIF(Rede!$D:$D,Geral!$C15,Rede!$AM:$AM) -> 0 | AN15: =SUMIF(Rede!$D:$D,Geral!$C15,Rede!$AN:$AN) -> 137.083 | AO15: =SUMIF(Rede!$D:$D,Geral!$C15,Rede!$AO:$AO) -> 121.75 | AP15: =SUMIF(Rede!$D:$D,Geral!$C15,Rede!$AP:$AP) -> 3.25 | AQ15: =SUMIF(Rede!$D:$D,Geral!$C15,Rede!$AQ:$AQ) -> 0 | AR15: =SUMIF(Rede!$D:$D,Geral!$C15,Rede!$AR:$AR) -> 130.111 | AS15: =SUMIF(Rede!$D:$D,Geral!$C15,Rede!$AS:$AS) -> 543 | AT15: =SUMIF(Rede!$D:$D,Geral!$C15,Rede!$AT:$AT) -> 24.25 | AU15: =SUMIF(Rede!$D:$D,Geral!$C15,Rede!$AU:$AU) -> 0 | AW15: =SUMIF(Rede!$D:$D,Geral!C15,Rede!$AW:$AW) -> 490.146 | AX15: =SUMIF(Rede!$D:$D,Geral!C15,Rede!$AX:$AX) -> 600.79287 | AY15: =SUMIF(Rede!$D:$D,Geral!C15,Rede!$AY:$AY) -> 982.5 | AZ15: =SUMIF(Rede!$D:$D,Geral!C15,Rede!$AZ:$AZ) -> 57.125 | BA15: =SUMIF(Rede!$D:$D,Geral!C15,Rede!$BA:$BA) -> 0 | BB15: =(AY15+AZ15+BA15)/AX15 -> 1.7304217 | BC15: =IFERROR(((AY15+AZ15+BA15)/AW15-1),0) -> 1.1210517 | BD15: =AX15-AY15-BA15-AZ15 -> -438.83213 | BE15: =SUMIF(Rede!D:D,Geral!C15,Rede!$BE:$BE) -> 199.425 | BF15: =SUMIF(Rede!D:D,Geral!C15,Rede!$BF:$BF) -> 162.5 | BG15: =SUMIF(Rede!D:D,Geral!C15,Rede!$BG:$BG) -> 0 | BH15: =SUMIF(Rede!D:D,Geral!C15,Rede!$BH:$BH) -> 0 | BI15: =SUMIF(Rede!$D:$D,Geral!C15,Rede!$BI:$BI) -> 68.275 | BJ15: =SUMIF(Rede!$D:$D,Geral!C15,Rede!$BJ:$BJ) -> 106 | BK15: =SUMIF(Rede!$D:$D,Geral!C15,Rede!$BK:$BK) -> 0 | BL15: =SUMIF(Rede!$D:$D,Geral!C15,Rede!$BL:$BL) -> 0 | BM15: =SUMIF(Rede!$D:$D,Geral!C15,Rede!$BM:$BM) -> 222.446 | BN15: =SUMIF(Rede!$D:$D,Geral!C15,Rede!$BN:$BN) -> 714 | BO15: =SUMIF(Rede!$D:$D,Geral!C15,Rede!$BO:$BO) -> 57.125 | BP15: =SUMIF(Rede!$D:$D,Geral!C15,Rede!$BP:$BP) -> 0 | BR15: =SUMIF(Rede!$D:$D,Geral!C15,Rede!$BR:$BR) -> 406.833 | BS15: =SUMIF(Rede!$D:$D,Geral!C15,Rede!$BS:$BS) -> 642 | BT15: =SUMIF(Rede!$D:$D,Geral!C15,Rede!$BT:$BT) -> 562 | BU15: =SUMIF(Rede!$D:$D,Geral!C15,Rede!$BU:$BU) -> 0 | BV15: =SUMIF(Rede!$D:$D,Geral!C15,Rede!$BV:$BV) -> 0 | BW15: =(BT15+BU15+BV15)/BS15 -> 0.87538941 | BX15: =IFERROR(((BT15+BU15+BV15)/BR15-1),0) -> 0.3814022 | BY15: =BS15-BT15-BU15-BV15 -> 80 | BZ15: =SUMIF(Rede!$D:$D,Geral!C15,Rede!$BZ:$BZ) -> 77.333 | CA15: =SUMIF(Rede!$D:$D,Geral!C15,Rede!$CA:$CA) -> 38.458 | CB15: =SUMIF(Rede!$D:$D,Geral!C15,Rede!$CB:$CB) -> 0 | CC15: =SUMIF(Rede!$D:$D,Geral!C15,Rede!$CC:$CC) -> 0 | CD15: =SUMIF(Rede!$D:$D,Geral!C15,Rede!$CD:$CD) -> 124 | CE15: =SUMIF(Rede!$D:$D,Geral!C15,Rede!$CE:$CE) -> 205 | CF15: =SUMIF(Rede!$D:$D,Geral!C15,Rede!$CF:$CF) -> 0 | CG15: =SUMIF(Rede!$D:$D,Geral!C15,Rede!$CG:$CG) -> 0 | CH15: =SUMIF(Rede!$D:$D,Geral!C15,Rede!$CH:$CH) -> 205.5 | CI15: =SUMIF(Rede!$D:$D,Geral!C15,Rede!$CI:$CI) -> 318.542 | CJ15: =SUMIF(Rede!$D:$D,Geral!C15,Rede!$CJ:$CJ) -> 0 | CK15: =SUMIF(Rede!$D:$D,Geral!C15,Rede!$CK:$CK) -> 0 | CM15: =G15+AB15+AW15+BR15 -> 2455.631 | CN15: =H15+AC15+AX15+BS15 -> 2626.8273 | CO15: =I15+AD15+AY15+BT15 -> 3117.208 | CP15: =J15+AE15+AZ15+BU15 -> 85.625 | CQ15: =K15+AF15+BA15+BV15 -> 0 | CR15: =(CO15+CP15+CQ15)/CN15 -> 1.2192781 | CS15: =IFERROR(((CO15+CP15+CQ15)/CM15-1),0) -> 0.30428106 | CT15: =CN15-CO15-CQ15-CP15 -> -576.00574
B16: NORTE MC/KA D | C16: 179 | D16: KA-BRQ | E16: PEDRO PAULO ECCEL | F16: =COUNTIF(Rede!$D:$D,Geral!$C16) -> 1 | G16: =SUMIF(Rede!$D:$D,Geral!C16,Rede!$G:$G) -> 1707.958 | H16: =SUMIF(Rede!$D:$D,Geral!C16,Rede!$H:$H) -> 2181.26 | I16: =SUMIF(Rede!$D:$D,Geral!C16,Rede!$I:$I) -> 1828 | J16: =SUMIF(Rede!$D:$D,Geral!$C16,Rede!$J:$J) -> 15 | K16: =SUMIF(Rede!$D:$D,Geral!C16,Rede!$K:$K) -> 0 | L16: =IFERROR((I16+K16+J16)/H16,0) -> 0.84492449 | M16: =IFERROR(((I16+K16+J16)/G16-1),0) -> 0.079066347 | N16: =H16-I16-J16-K16 -> 338.26 | O16: =SUMIF(Rede!$D:$D,Geral!$C16,Rede!$O:$O) -> 504 | P16: =SUMIF(Rede!$D:$D,Geral!$C16,Rede!$P:$P) -> 109 | Q16: =SUMIF(Rede!$D:$D,Geral!$C16,Rede!$Q:$Q) -> 0 | R16: =SUMIF(Rede!$D:$D,Geral!$C16,Rede!$R:$R) -> 0 | S16: =SUMIF(Rede!$D:$D,Geral!$C16,Rede!$S:$S) -> 204.958 | T16: =SUMIF(Rede!$D:$D,Geral!$C16,Rede!$T:$T) -> 1458 | U16: =SUMIF(Rede!$D:$D,Geral!$C16,Rede!$U:$U) -> 15 | V16: =SUMIF(Rede!$D:$D,Geral!$C16,Rede!$V:$V) -> 0 | W16: =SUMIF(Rede!$D:$D,Geral!$C16,Rede!$W:$W) -> 999 | X16: =SUMIF(Rede!$D:$D,Geral!$C16,Rede!$X:$X) -> 261 | Y16: =SUMIF(Rede!$D:$D,Geral!$C16,Rede!$Y:$Y) -> 0 | Z16: =SUMIF(Rede!$D:$D,Geral!$C16,Rede!$Z:$Z) -> 0 | AB16: =SUMIF(Rede!D:D,Geral!C16,Rede!$AB:$AB) -> 2156 | AC16: =SUMIF(Rede!D:D,Geral!C16,Rede!$AC:$AC) -> 1869.6433 | AD16: =SUMIF(Rede!D:D,Geral!C16,Rede!$AD:$AD) -> 1741.75 | AE16: =SUMIF(Rede!$D:$D,Geral!$C16,Rede!$AE:$AE) -> 3 | AF16: =SUMIF(Rede!D:D,Geral!C16,Rede!$AF:$AF) -> 0 | AG16: =(AD16+AF16+AE16)/AC16 -> 0.9331994 | AH16: =IFERROR(((AD16+AF16+AE16)/AB16-1),0) -> -0.19074675 | AI16: =AC16-AD16-AF16-AE16 -> 124.8933 | AJ16: =SUMIF(Rede!$D:$D,Geral!$C16,Rede!$AJ:$AJ) -> 624 | AK16: =SUMIF(Rede!$D:$D,Geral!$C16,Rede!$AK:$AK) -> 548.75 | AL16: =SUMIF(Rede!$D:$D,Geral!$C16,Rede!$AL:$AL) -> 0 | AM16: =SUMIF(Rede!$D:$D,Geral!$C16,Rede!$AM:$AM) -> 0 | AN16: =SUMIF(Rede!$D:$D,Geral!$C16,Rede!$AN:$AN) -> 945 | AO16: =SUMIF(Rede!$D:$D,Geral!$C16,Rede!$AO:$AO) -> 578 | AP16: =SUMIF(Rede!$D:$D,Geral!$C16,Rede!$AP:$AP) -> 3 | AQ16: =SUMIF(Rede!$D:$D,Geral!$C16,Rede!$AQ:$AQ) -> 0 | AR16: =SUMIF(Rede!$D:$D,Geral!$C16,Rede!$AR:$AR) -> 587 | AS16: =SUMIF(Rede!$D:$D,Geral!$C16,Rede!$AS:$AS) -> 615 | AT16: =SUMIF(Rede!$D:$D,Geral!$C16,Rede!$AT:$AT) -> 0 | AU16: =SUMIF(Rede!$D:$D,Geral!$C16,Rede!$AU:$AU) -> 0 | AW16: =SUMIF(Rede!$D:$D,Geral!C16,Rede!$AW:$AW) -> 2145.417 | AX16: =SUMIF(Rede!$D:$D,Geral!C16,Rede!$AX:$AX) -> 1758.4468 | AY16: =SUMIF(Rede!$D:$D,Geral!C16,Rede!$AY:$AY) -> 1714.875 | AZ16: =SUMIF(Rede!$D:$D,Geral!C16,Rede!$AZ:$AZ) -> 25 | BA16: =SUMIF(Rede!$D:$D,Geral!C16,Rede!$BA:$BA) -> 0 | BB16: =(AY16+AZ16+BA16)/AX16 -> 0.98943851 | BC16: =IFERROR(((AY16+AZ16+BA16)/AW16-1),0) -> -0.18902712 | BD16: =AX16-AY16-BA16-AZ16 -> 18.571814 | BE16: =SUMIF(Rede!D:D,Geral!C16,Rede!$BE:$BE) -> 517 | BF16: =SUMIF(Rede!D:D,Geral!C16,Rede!$BF:$BF) -> 235.917 | BG16: =SUMIF(Rede!D:D,Geral!C16,Rede!$BG:$BG) -> 0 | BH16: =SUMIF(Rede!D:D,Geral!C16,Rede!$BH:$BH) -> 0 | BI16: =SUMIF(Rede!$D:$D,Geral!C16,Rede!$BI:$BI) -> 408 | BJ16: =SUMIF(Rede!$D:$D,Geral!C16,Rede!$BJ:$BJ) -> 790.958 | BK16: =SUMIF(Rede!$D:$D,Geral!C16,Rede!$BK:$BK) -> 12 | BL16: =SUMIF(Rede!$D:$D,Geral!C16,Rede!$BL:$BL) -> 0 | BM16: =SUMIF(Rede!$D:$D,Geral!C16,Rede!$BM:$BM) -> 1220.417 | BN16: =SUMIF(Rede!$D:$D,Geral!C16,Rede!$BN:$BN) -> 688 | BO16: =SUMIF(Rede!$D:$D,Geral!C16,Rede!$BO:$BO) -> 13 | BP16: =SUMIF(Rede!$D:$D,Geral!C16,Rede!$BP:$BP) -> 0 | BR16: =SUMIF(Rede!$D:$D,Geral!C16,Rede!$BR:$BR) -> 1078.25 | BS16: =SUMIF(Rede!$D:$D,Geral!C16,Rede!$BS:$BS) -> 1872 | BT16: =SUMIF(Rede!$D:$D,Geral!C16,Rede!$BT:$BT) -> 1087 | BU16: =SUMIF(Rede!$D:$D,Geral!C16,Rede!$BU:$BU) -> 59 | BV16: =SUMIF(Rede!$D:$D,Geral!C16,Rede!$BV:$BV) -> 18 | BW16: =(BT16+BU16+BV16)/BS16 -> 0.62179487 | BX16: =IFERROR(((BT16+BU16+BV16)/BR16-1),0) -> 0.079527011 | BY16: =BS16-BT16-BU16-BV16 -> 708 | BZ16: =SUMIF(Rede!$D:$D,Geral!C16,Rede!$BZ:$BZ) -> 179.25 | CA16: =SUMIF(Rede!$D:$D,Geral!C16,Rede!$CA:$CA) -> 365 | CB16: =SUMIF(Rede!$D:$D,Geral!C16,Rede!$CB:$CB) -> 3 | CC16: =SUMIF(Rede!$D:$D,Geral!C16,Rede!$CC:$CC) -> 0 | CD16: =SUMIF(Rede!$D:$D,Geral!C16,Rede!$CD:$CD) -> 490 | CE16: =SUMIF(Rede!$D:$D,Geral!C16,Rede!$CE:$CE) -> 518 | CF16: =SUMIF(Rede!$D:$D,Geral!C16,Rede!$CF:$CF) -> 15 | CG16: =SUMIF(Rede!$D:$D,Geral!C16,Rede!$CG:$CG) -> 0 | CH16: =SUMIF(Rede!$D:$D,Geral!C16,Rede!$CH:$CH) -> 409 | CI16: =SUMIF(Rede!$D:$D,Geral!C16,Rede!$CI:$CI) -> 204 | CJ16: =SUMIF(Rede!$D:$D,Geral!C16,Rede!$CJ:$CJ) -> 0 | CK16: =SUMIF(Rede!$D:$D,Geral!C16,Rede!$CK:$CK) -> 59 | CM16: =G16+AB16+AW16+BR16 -> 7087.625 | CN16: =H16+AC16+AX16+BS16 -> 7681.3501 | CO16: =I16+AD16+AY16+BT16 -> 6371.625 | CP16: =J16+AE16+AZ16+BU16 -> 102 | CQ16: =K16+AF16+BA16+BV16 -> 18 | CR16: =(CO16+CP16+CQ16)/CN16 -> 0.8451151 | CS16: =IFERROR(((CO16+CP16+CQ16)/CM16-1),0) -> -0.084090228 | CT16: =CN16-CO16-CQ16-CP16 -> 1189.7251
B17: NORTE MC/KA D | C17: 359 | D17: MC-ITPE D | E17: MARCELO SCHEFFLER | F17: =COUNTIF(Rede!$D:$D,Geral!$C17) -> 3 | G17: =SUMIF(Rede!$D:$D,Geral!C17,Rede!$G:$G) -> 3532.387 | H17: =SUMIF(Rede!$D:$D,Geral!C17,Rede!$H:$H) -> 2496.36 | I17: =SUMIF(Rede!$D:$D,Geral!C17,Rede!$I:$I) -> 2599.292 | J17: =SUMIF(Rede!$D:$D,Geral!$C17,Rede!$J:$J) -> 21.25 | K17: =SUMIF(Rede!$D:$D,Geral!C17,Rede!$K:$K) -> 0 | L17: =IFERROR((I17+K17+J17)/H17,0) -> 1.0497452 | M17: =IFERROR(((I17+K17+J17)/G17-1),0) -> -0.25813848 | N17: =H17-I17-J17-K17 -> -124.182 | O17: =SUMIF(Rede!$D:$D,Geral!$C17,Rede!$O:$O) -> 167.241 | P17: =SUMIF(Rede!$D:$D,Geral!$C17,Rede!$P:$P) -> 96.042 | Q17: =SUMIF(Rede!$D:$D,Geral!$C17,Rede!$Q:$Q) -> 11.75 | R17: =SUMIF(Rede!$D:$D,Geral!$C17,Rede!$R:$R) -> 0 | S17: =SUMIF(Rede!$D:$D,Geral!$C17,Rede!$S:$S) -> 1846.146 | T17: =SUMIF(Rede!$D:$D,Geral!$C17,Rede!$T:$T) -> 906.5 | U17: =SUMIF(Rede!$D:$D,Geral!$C17,Rede!$U:$U) -> 5 | V17: =SUMIF(Rede!$D:$D,Geral!$C17,Rede!$V:$V) -> 0 | W17: =SUMIF(Rede!$D:$D,Geral!$C17,Rede!$W:$W) -> 1519 | X17: =SUMIF(Rede!$D:$D,Geral!$C17,Rede!$X:$X) -> 1596.75 | Y17: =SUMIF(Rede!$D:$D,Geral!$C17,Rede!$Y:$Y) -> 4.5 | Z17: =SUMIF(Rede!$D:$D,Geral!$C17,Rede!$Z:$Z) -> 0 | AB17: =SUMIF(Rede!D:D,Geral!C17,Rede!$AB:$AB) -> 1915.563 | AC17: =SUMIF(Rede!D:D,Geral!C17,Rede!$AC:$AC) -> 2139.7439 | AD17: =SUMIF(Rede!D:D,Geral!C17,Rede!$AD:$AD) -> 788.877 | AE17: =SUMIF(Rede!$D:$D,Geral!$C17,Rede!$AE:$AE) -> 27.333 | AF17: =SUMIF(Rede!D:D,Geral!C17,Rede!$AF:$AF) -> 0 | AG17: =(AD17+AF17+AE17)/AC17 -> 0.3814522 | AH17: =IFERROR(((AD17+AF17+AE17)/AB17-1),0) -> -0.57390595 | AI17: =AC17-AD17-AF17-AE17 -> 1323.5339 | AJ17: =SUMIF(Rede!$D:$D,Geral!$C17,Rede!$AJ:$AJ) -> 651.146 | AK17: =SUMIF(Rede!$D:$D,Geral!$C17,Rede!$AK:$AK) -> 131.167 | AL17: =SUMIF(Rede!$D:$D,Geral!$C17,Rede!$AL:$AL) -> 0 | AM17: =SUMIF(Rede!$D:$D,Geral!$C17,Rede!$AM:$AM) -> 0 | AN17: =SUMIF(Rede!$D:$D,Geral!$C17,Rede!$AN:$AN) -> 546.5 | AO17: =SUMIF(Rede!$D:$D,Geral!$C17,Rede!$AO:$AO) -> 273.876 | AP17: =SUMIF(Rede!$D:$D,Geral!$C17,Rede!$AP:$AP) -> 7.333 | AQ17: =SUMIF(Rede!$D:$D,Geral!$C17,Rede!$AQ:$AQ) -> 0 | AR17: =SUMIF(Rede!$D:$D,Geral!$C17,Rede!$AR:$AR) -> 717.917 | AS17: =SUMIF(Rede!$D:$D,Geral!$C17,Rede!$AS:$AS) -> 383.834 | AT17: =SUMIF(Rede!$D:$D,Geral!$C17,Rede!$AT:$AT) -> 20 | AU17: =SUMIF(Rede!$D:$D,Geral!$C17,Rede!$AU:$AU) -> 0 | AW17: =SUMIF(Rede!$D:$D,Geral!C17,Rede!$AW:$AW) -> 1699.604 | AX17: =SUMIF(Rede!$D:$D,Geral!C17,Rede!$AX:$AX) -> 2012.4832 | AY17: =SUMIF(Rede!$D:$D,Geral!C17,Rede!$AY:$AY) -> 1096.79 | AZ17: =SUMIF(Rede!$D:$D,Geral!C17,Rede!$AZ:$AZ) -> 81 | BA17: =SUMIF(Rede!$D:$D,Geral!C17,Rede!$BA:$BA) -> 0 | BB17: =(AY17+AZ17+BA17)/AX17 -> 0.58524215 | BC17: =IFERROR(((AY17+AZ17+BA17)/AW17-1),0) -> -0.30702093 | BD17: =AX17-AY17-BA17-AZ17 -> 834.69322 | BE17: =SUMIF(Rede!D:D,Geral!C17,Rede!$BE:$BE) -> 192.167 | BF17: =SUMIF(Rede!D:D,Geral!C17,Rede!$BF:$BF) -> 251.624 | BG17: =SUMIF(Rede!D:D,Geral!C17,Rede!$BG:$BG) -> 9 | BH17: =SUMIF(Rede!D:D,Geral!C17,Rede!$BH:$BH) -> 0 | BI17: =SUMIF(Rede!$D:$D,Geral!C17,Rede!$BI:$BI) -> 320.479 | BJ17: =SUMIF(Rede!$D:$D,Geral!C17,Rede!$BJ:$BJ) -> 192.958 | BK17: =SUMIF(Rede!$D:$D,Geral!C17,Rede!$BK:$BK) -> 25 | BL17: =SUMIF(Rede!$D:$D,Geral!C17,Rede!$BL:$BL) -> 0 | BM17: =SUMIF(Rede!$D:$D,Geral!C17,Rede!$BM:$BM) -> 1186.958 | BN17: =SUMIF(Rede!$D:$D,Geral!C17,Rede!$BN:$BN) -> 652.208 | BO17: =SUMIF(Rede!$D:$D,Geral!C17,Rede!$BO:$BO) -> 47 | BP17: =SUMIF(Rede!$D:$D,Geral!C17,Rede!$BP:$BP) -> 0 | BR17: =SUMIF(Rede!$D:$D,Geral!C17,Rede!$BR:$BR) -> 1171.812 | BS17: =SUMIF(Rede!$D:$D,Geral!C17,Rede!$BS:$BS) -> 2142 | BT17: =SUMIF(Rede!$D:$D,Geral!C17,Rede!$BT:$BT) -> 902.793 | BU17: =SUMIF(Rede!$D:$D,Geral!C17,Rede!$BU:$BU) -> 121 | BV17: =SUMIF(Rede!$D:$D,Geral!C17,Rede!$BV:$BV) -> 94.542 | BW17: =(BT17+BU17+BV17)/BS17 -> 0.52209851 | BX17: =IFERROR(((BT17+BU17+BV17)/BR17-1),0) -> -0.04563616 | BY17: =BS17-BT17-BU17-BV17 -> 1023.665 | BZ17: =SUMIF(Rede!$D:$D,Geral!C17,Rede!$BZ:$BZ) -> 332.062 | CA17: =SUMIF(Rede!$D:$D,Geral!C17,Rede!$CA:$CA) -> 284.937 | CB17: =SUMIF(Rede!$D:$D,Geral!C17,Rede!$CB:$CB) -> 30.292 | CC17: =SUMIF(Rede!$D:$D,Geral!C17,Rede!$CC:$CC) -> 0 | CD17: =SUMIF(Rede!$D:$D,Geral!C17,Rede!$CD:$CD) -> 121.75 | CE17: =SUMIF(Rede!$D:$D,Geral!C17,Rede!$CE:$CE) -> 223.751 | CF17: =SUMIF(Rede!$D:$D,Geral!C17,Rede!$CF:$CF) -> 8.417 | CG17: =SUMIF(Rede!$D:$D,Geral!C17,Rede!$CG:$CG) -> 0 | CH17: =SUMIF(Rede!$D:$D,Geral!C17,Rede!$CH:$CH) -> 718 | CI17: =SUMIF(Rede!$D:$D,Geral!C17,Rede!$CI:$CI) -> 394.105 | CJ17: =SUMIF(Rede!$D:$D,Geral!C17,Rede!$CJ:$CJ) -> 55.833 | CK17: =SUMIF(Rede!$D:$D,Geral!C17,Rede!$CK:$CK) -> 121 | CM17: =G17+AB17+AW17+BR17 -> 8319.366 | CN17: =H17+AC17+AX17+BS17 -> 8790.5871 | CO17: =I17+AD17+AY17+BT17 -> 5387.752 | CP17: =J17+AE17+AZ17+BU17 -> 250.583 | CQ17: =K17+AF17+BA17+BV17 -> 94.542 | CR17: =(CO17+CP17+CQ17)/CN17 -> 0.65216088 | CS17: =IFERROR(((CO17+CP17+CQ17)/CM17-1),0) -> -0.31089977 | CT17: =CN17-CO17-CQ17-CP17 -> 3057.7101
B18: NORTE MC/KA D | C18: 4066 | D18: MC-BNU D | E18: MURIEL DERCIO VOCKES | F18: =COUNTIF(Rede!$D:$D,Geral!$C18) -> 1 | G18: =SUMIF(Rede!$D:$D,Geral!C18,Rede!$G:$G) -> 651.25 | H18: =SUMIF(Rede!$D:$D,Geral!C18,Rede!$H:$H) -> 397.51 | I18: =SUMIF(Rede!$D:$D,Geral!C18,Rede!$I:$I) -> 396.458 | J18: =SUMIF(Rede!$D:$D,Geral!$C18,Rede!$J:$J) -> 12.75 | K18: =SUMIF(Rede!$D:$D,Geral!C18,Rede!$K:$K) -> 0 | L18: =IFERROR((I18+K18+J18)/H18,0) -> 1.0294282 | M18: =IFERROR(((I18+K18+J18)/G18-1),0) -> -0.37165758 | N18: =H18-I18-J18-K18 -> -11.698 | O18: =SUMIF(Rede!$D:$D,Geral!$C18,Rede!$O:$O) -> 75.833 | P18: =SUMIF(Rede!$D:$D,Geral!$C18,Rede!$P:$P) -> 145.375 | Q18: =SUMIF(Rede!$D:$D,Geral!$C18,Rede!$Q:$Q) -> 9.75 | R18: =SUMIF(Rede!$D:$D,Geral!$C18,Rede!$R:$R) -> 0 | S18: =SUMIF(Rede!$D:$D,Geral!$C18,Rede!$S:$S) -> 72.75 | T18: =SUMIF(Rede!$D:$D,Geral!$C18,Rede!$T:$T) -> 259.583 | U18: =SUMIF(Rede!$D:$D,Geral!$C18,Rede!$U:$U) -> 3 | V18: =SUMIF(Rede!$D:$D,Geral!$C18,Rede!$V:$V) -> 0 | W18: =SUMIF(Rede!$D:$D,Geral!$C18,Rede!$W:$W) -> 502.667 | X18: =SUMIF(Rede!$D:$D,Geral!$C18,Rede!$X:$X) -> -8.5 | Y18: =SUMIF(Rede!$D:$D,Geral!$C18,Rede!$Y:$Y) -> 0 | Z18: =SUMIF(Rede!$D:$D,Geral!$C18,Rede!$Z:$Z) -> 0 | AB18: =SUMIF(Rede!D:D,Geral!C18,Rede!$AB:$AB) -> 179 | AC18: =SUMIF(Rede!D:D,Geral!C18,Rede!$AC:$AC) -> 340.72555 | AD18: =SUMIF(Rede!D:D,Geral!C18,Rede!$AD:$AD) -> 113.916 | AE18: =SUMIF(Rede!$D:$D,Geral!$C18,Rede!$AE:$AE) -> 1.25 | AF18: =SUMIF(Rede!D:D,Geral!C18,Rede!$AF:$AF) -> 0 | AG18: =(AD18+AF18+AE18)/AC18 -> 0.33800224 | AH18: =IFERROR(((AD18+AF18+AE18)/AB18-1),0) -> -0.35661453 | AI18: =AC18-AD18-AF18-AE18 -> 225.55955 | AJ18: =SUMIF(Rede!$D:$D,Geral!$C18,Rede!$AJ:$AJ) -> 78.5 | AK18: =SUMIF(Rede!$D:$D,Geral!$C18,Rede!$AK:$AK) -> 25.083 | AL18: =SUMIF(Rede!$D:$D,Geral!$C18,Rede!$AL:$AL) -> 0 | AM18: =SUMIF(Rede!$D:$D,Geral!$C18,Rede!$AM:$AM) -> 0 | AN18: =SUMIF(Rede!$D:$D,Geral!$C18,Rede!$AN:$AN) -> 58.5 | AO18: =SUMIF(Rede!$D:$D,Geral!$C18,Rede!$AO:$AO) -> 65 | AP18: =SUMIF(Rede!$D:$D,Geral!$C18,Rede!$AP:$AP) -> 1.25 | AQ18: =SUMIF(Rede!$D:$D,Geral!$C18,Rede!$AQ:$AQ) -> 0 | AR18: =SUMIF(Rede!$D:$D,Geral!$C18,Rede!$AR:$AR) -> 42 | AS18: =SUMIF(Rede!$D:$D,Geral!$C18,Rede!$AS:$AS) -> 23.833 | AT18: =SUMIF(Rede!$D:$D,Geral!$C18,Rede!$AT:$AT) -> 0 | AU18: =SUMIF(Rede!$D:$D,Geral!$C18,Rede!$AU:$AU) -> 0 | AW18: =SUMIF(Rede!$D:$D,Geral!C18,Rede!$AW:$AW) -> 358.75 | AX18: =SUMIF(Rede!$D:$D,Geral!C18,Rede!$AX:$AX) -> 320.461 | AY18: =SUMIF(Rede!$D:$D,Geral!C18,Rede!$AY:$AY) -> 373.917 | AZ18: =SUMIF(Rede!$D:$D,Geral!C18,Rede!$AZ:$AZ) -> 28.25 | BA18: =SUMIF(Rede!$D:$D,Geral!C18,Rede!$BA:$BA) -> 0 | BB18: =(AY18+AZ18+BA18)/AX18 -> 1.2549639 | BC18: =IFERROR(((AY18+AZ18+BA18)/AW18-1),0) -> 0.121023 | BD18: =AX18-AY18-BA18-AZ18 -> -81.705999 | BE18: =SUMIF(Rede!D:D,Geral!C18,Rede!$BE:$BE) -> 38.5 | BF18: =SUMIF(Rede!D:D,Geral!C18,Rede!$BF:$BF) -> 65.167 | BG18: =SUMIF(Rede!D:D,Geral!C18,Rede!$BG:$BG) -> 1.75 | BH18: =SUMIF(Rede!D:D,Geral!C18,Rede!$BH:$BH) -> 0 | BI18: =SUMIF(Rede!$D:$D,Geral!C18,Rede!$BI:$BI) -> 152.25 | BJ18: =SUMIF(Rede!$D:$D,Geral!C18,Rede!$BJ:$BJ) -> 113.417 | BK18: =SUMIF(Rede!$D:$D,Geral!C18,Rede!$BK:$BK) -> 2.5 | BL18: =SUMIF(Rede!$D:$D,Geral!C18,Rede!$BL:$BL) -> 0 | BM18: =SUMIF(Rede!$D:$D,Geral!C18,Rede!$BM:$BM) -> 168 | BN18: =SUMIF(Rede!$D:$D,Geral!C18,Rede!$BN:$BN) -> 195.333 | BO18: =SUMIF(Rede!$D:$D,Geral!C18,Rede!$BO:$BO) -> 24 | BP18: =SUMIF(Rede!$D:$D,Geral!C18,Rede!$BP:$BP) -> 0 | BR18: =SUMIF(Rede!$D:$D,Geral!C18,Rede!$BR:$BR) -> 121.125 | BS18: =SUMIF(Rede!$D:$D,Geral!C18,Rede!$BS:$BS) -> 342 | BT18: =SUMIF(Rede!$D:$D,Geral!C18,Rede!$BT:$BT) -> 160.667 | BU18: =SUMIF(Rede!$D:$D,Geral!C18,Rede!$BU:$BU) -> 45 | BV18: =SUMIF(Rede!$D:$D,Geral!C18,Rede!$BV:$BV) -> 19.958 | BW18: =(BT18+BU18+BV18)/BS18 -> 0.65972222 | BX18: =IFERROR(((BT18+BU18+BV18)/BR18-1),0) -> 0.8627451 | BY18: =BS18-BT18-BU18-BV18 -> 116.375 | BZ18: =SUMIF(Rede!$D:$D,Geral!C18,Rede!$BZ:$BZ) -> 62.25 | CA18: =SUMIF(Rede!$D:$D,Geral!C18,Rede!$CA:$CA) -> 26.667 | CB18: =SUMIF(Rede!$D:$D,Geral!C18,Rede!$CB:$CB) -> 0.833 | CC18: =SUMIF(Rede!$D:$D,Geral!C18,Rede!$CC:$CC) -> 0 | CD18: =SUMIF(Rede!$D:$D,Geral!C18,Rede!$CD:$CD) -> 50.875 | CE18: =SUMIF(Rede!$D:$D,Geral!C18,Rede!$CE:$CE) -> 30.667 | CF18: =SUMIF(Rede!$D:$D,Geral!C18,Rede!$CF:$CF) -> 3.167 | CG18: =SUMIF(Rede!$D:$D,Geral!C18,Rede!$CG:$CG) -> 0 | CH18: =SUMIF(Rede!$D:$D,Geral!C18,Rede!$CH:$CH) -> 8 | CI18: =SUMIF(Rede!$D:$D,Geral!C18,Rede!$CI:$CI) -> 103.333 | CJ18: =SUMIF(Rede!$D:$D,Geral!C18,Rede!$CJ:$CJ) -> 15.958 | CK18: =SUMIF(Rede!$D:$D,Geral!C18,Rede!$CK:$CK) -> 45 | CM18: =G18+AB18+AW18+BR18 -> 1310.125 | CN18: =H18+AC18+AX18+BS18 -> 1400.6966 | CO18: =I18+AD18+AY18+BT18 -> 1044.958 | CP18: =J18+AE18+AZ18+BU18 -> 87.25 | CQ18: =K18+AF18+BA18+BV18 -> 19.958 | CR18: =(CO18+CP18+CQ18)/CN18 -> 0.82256646 | CS18: =IFERROR(((CO18+CP18+CQ18)/CM18-1),0) -> -0.12056788 | CT18: =CN18-CO18-CQ18-CP18 -> 248.53055
B19: NORTE MC/KA D | C19: 3655 | D19: KA-BNU | E19: NATHAN FREITAS FUZINATO | F19: =COUNTIF(Rede!$D:$D,Geral!$C19) -> 1 | G19: =SUMIF(Rede!$D:$D,Geral!C19,Rede!$G:$G) -> 1092.75 | H19: =SUMIF(Rede!$D:$D,Geral!C19,Rede!$H:$H) -> 2551.88 | I19: =SUMIF(Rede!$D:$D,Geral!C19,Rede!$I:$I) -> 2591.659 | J19: =SUMIF(Rede!$D:$D,Geral!$C19,Rede!$J:$J) -> 0.417 | K19: =SUMIF(Rede!$D:$D,Geral!C19,Rede!$K:$K) -> 0 | L19: =IFERROR((I19+K19+J19)/H19,0) -> 1.0157515 | M19: =IFERROR(((I19+K19+J19)/G19-1),0) -> 1.3720668 | N19: =H19-I19-J19-K19 -> -40.196 | O19: =SUMIF(Rede!$D:$D,Geral!$C19,Rede!$O:$O) -> 436.75 | P19: =SUMIF(Rede!$D:$D,Geral!$C19,Rede!$P:$P) -> 626 | Q19: =SUMIF(Rede!$D:$D,Geral!$C19,Rede!$Q:$Q) -> 0 | R19: =SUMIF(Rede!$D:$D,Geral!$C19,Rede!$R:$R) -> 0 | S19: =SUMIF(Rede!$D:$D,Geral!$C19,Rede!$S:$S) -> 239 | T19: =SUMIF(Rede!$D:$D,Geral!$C19,Rede!$T:$T) -> 172.667 | U19: =SUMIF(Rede!$D:$D,Geral!$C19,Rede!$U:$U) -> 0.417 | V19: =SUMIF(Rede!$D:$D,Geral!$C19,Rede!$V:$V) -> 0 | W19: =SUMIF(Rede!$D:$D,Geral!$C19,Rede!$W:$W) -> 417 | X19: =SUMIF(Rede!$D:$D,Geral!$C19,Rede!$X:$X) -> 1792.992 | Y19: =SUMIF(Rede!$D:$D,Geral!$C19,Rede!$Y:$Y) -> 0 | Z19: =SUMIF(Rede!$D:$D,Geral!$C19,Rede!$Z:$Z) -> 0 | AB19: =SUMIF(Rede!D:D,Geral!C19,Rede!$AB:$AB) -> 4926.167 | AC19: =SUMIF(Rede!D:D,Geral!C19,Rede!$AC:$AC) -> 2187.3287 | AD19: =SUMIF(Rede!D:D,Geral!C19,Rede!$AD:$AD) -> 2142.833 | AE19: =SUMIF(Rede!$D:$D,Geral!$C19,Rede!$AE:$AE) -> 11 | AF19: =SUMIF(Rede!D:D,Geral!C19,Rede!$AF:$AF) -> 0 | AG19: =(AD19+AF19+AE19)/AC19 -> 0.9846865 | AH19: =IFERROR(((AD19+AF19+AE19)/AB19-1),0) -> -0.5627771 | AI19: =AC19-AD19-AF19-AE19 -> 33.495656 | AJ19: =SUMIF(Rede!$D:$D,Geral!$C19,Rede!$AJ:$AJ) -> 2393.583 | AK19: =SUMIF(Rede!$D:$D,Geral!$C19,Rede!$AK:$AK) -> 1159.833 | AL19: =SUMIF(Rede!$D:$D,Geral!$C19,Rede!$AL:$AL) -> 0 | AM19: =SUMIF(Rede!$D:$D,Geral!$C19,Rede!$AM:$AM) -> 0 | AN19: =SUMIF(Rede!$D:$D,Geral!$C19,Rede!$AN:$AN) -> 1487.917 | AO19: =SUMIF(Rede!$D:$D,Geral!$C19,Rede!$AO:$AO) -> 319 | AP19: =SUMIF(Rede!$D:$D,Geral!$C19,Rede!$AP:$AP) -> 0 | AQ19: =SUMIF(Rede!$D:$D,Geral!$C19,Rede!$AQ:$AQ) -> 0 | AR19: =SUMIF(Rede!$D:$D,Geral!$C19,Rede!$AR:$AR) -> 1044.667 | AS19: =SUMIF(Rede!$D:$D,Geral!$C19,Rede!$AS:$AS) -> 664 | AT19: =SUMIF(Rede!$D:$D,Geral!$C19,Rede!$AT:$AT) -> 11 | AU19: =SUMIF(Rede!$D:$D,Geral!$C19,Rede!$AU:$AU) -> 0 | AW19: =SUMIF(Rede!$D:$D,Geral!C19,Rede!$AW:$AW) -> 1411.25 | AX19: =SUMIF(Rede!$D:$D,Geral!C19,Rede!$AX:$AX) -> 2057.2379 | AY19: =SUMIF(Rede!$D:$D,Geral!C19,Rede!$AY:$AY) -> 3123.992 | AZ19: =SUMIF(Rede!$D:$D,Geral!C19,Rede!$AZ:$AZ) -> 11 | BA19: =SUMIF(Rede!$D:$D,Geral!C19,Rede!$BA:$BA) -> 0 | BB19: =(AY19+AZ19+BA19)/AX19 -> 1.523884 | BC19: =IFERROR(((AY19+AZ19+BA19)/AW19-1),0) -> 1.2214292 | BD19: =AX19-AY19-BA19-AZ19 -> -1077.7541 | BE19: =SUMIF(Rede!D:D,Geral!C19,Rede!$BE:$BE) -> 339 | BF19: =SUMIF(Rede!D:D,Geral!C19,Rede!$BF:$BF) -> 873 | BG19: =SUMIF(Rede!D:D,Geral!C19,Rede!$BG:$BG) -> 11 | BH19: =SUMIF(Rede!D:D,Geral!C19,Rede!$BH:$BH) -> 0 | BI19: =SUMIF(Rede!$D:$D,Geral!C19,Rede!$BI:$BI) -> 873.667 | BJ19: =SUMIF(Rede!$D:$D,Geral!C19,Rede!$BJ:$BJ) -> 1116.992 | BK19: =SUMIF(Rede!$D:$D,Geral!C19,Rede!$BK:$BK) -> 0 | BL19: =SUMIF(Rede!$D:$D,Geral!C19,Rede!$BL:$BL) -> 0 | BM19: =SUMIF(Rede!$D:$D,Geral!C19,Rede!$BM:$BM) -> 198.583 | BN19: =SUMIF(Rede!$D:$D,Geral!C19,Rede!$BN:$BN) -> 1134 | BO19: =SUMIF(Rede!$D:$D,Geral!C19,Rede!$BO:$BO) -> 0 | BP19: =SUMIF(Rede!$D:$D,Geral!C19,Rede!$BP:$BP) -> 0 | BR19: =SUMIF(Rede!$D:$D,Geral!C19,Rede!$BR:$BR) -> 1217.242 | BS19: =SUMIF(Rede!$D:$D,Geral!C19,Rede!$BS:$BS) -> 2190 | BT19: =SUMIF(Rede!$D:$D,Geral!C19,Rede!$BT:$BT) -> 1228.5 | BU19: =SUMIF(Rede!$D:$D,Geral!C19,Rede!$BU:$BU) -> 0 | BV19: =SUMIF(Rede!$D:$D,Geral!C19,Rede!$BV:$BV) -> 0 | BW19: =(BT19+BU19+BV19)/BS19 -> 0.5609589 | BX19: =IFERROR(((BT19+BU19+BV19)/BR19-1),0) -> 0.0092487772 | BY19: =BS19-BT19-BU19-BV19 -> 961.5 | BZ19: =SUMIF(Rede!$D:$D,Geral!C19,Rede!$BZ:$BZ) -> 326.325 | CA19: =SUMIF(Rede!$D:$D,Geral!C19,Rede!$CA:$CA) -> 126 | CB19: =SUMIF(Rede!$D:$D,Geral!C19,Rede!$CB:$CB) -> 0 | CC19: =SUMIF(Rede!$D:$D,Geral!C19,Rede!$CC:$CC) -> 0 | CD19: =SUMIF(Rede!$D:$D,Geral!C19,Rede!$CD:$CD) -> 606 | CE19: =SUMIF(Rede!$D:$D,Geral!C19,Rede!$CE:$CE) -> 1106.5 | CF19: =SUMIF(Rede!$D:$D,Geral!C19,Rede!$CF:$CF) -> 0 | CG19: =SUMIF(Rede!$D:$D,Geral!C19,Rede!$CG:$CG) -> 0 | CH19: =SUMIF(Rede!$D:$D,Geral!C19,Rede!$CH:$CH) -> 284.917 | CI19: =SUMIF(Rede!$D:$D,Geral!C19,Rede!$CI:$CI) -> -4 | CJ19: =SUMIF(Rede!$D:$D,Geral!C19,Rede!$CJ:$CJ) -> 0 | CK19: =SUMIF(Rede!$D:$D,Geral!C19,Rede!$CK:$CK) -> 0 | CM19: =G19+AB19+AW19+BR19 -> 8647.409 | CN19: =H19+AC19+AX19+BS19 -> 8986.4466 | CO19: =I19+AD19+AY19+BT19 -> 9086.984 | CP19: =J19+AE19+AZ19+BU19 -> 22.417 | CQ19: =K19+AF19+BA19+BV19 -> 0 | CR19: =(CO19+CP19+CQ19)/CN19 -> 1.0136822 | CS19: =IFERROR(((CO19+CP19+CQ19)/CM19-1),0) -> 0.053425483 | CT19: =CN19-CO19-CQ19-CP19 -> -122.95441
B20: TT | F20: =SUM(F12:F19) -> 14 | G20: =SUBTOTAL(9,G12:G19) -> 14339.799 | H20: =SUBTOTAL(9,H12:H19) -> 12641.68 | I20: =SUBTOTAL(9,I12:I19) -> 15458.304 | J20: =SUBTOTAL(9,J12:J19) -> 125.5 | K20: =SUBTOTAL(9,K12:K19) -> 0 | L20: =IFERROR((I20+K20+J20)/H20,0) -> 1.232732 | M20: =IFERROR(((I20+K20+J20)/G20-1),0) -> 0.086751913 | N20: =H20-I20-J20-K20 -> -2942.124 | O20: =SUM(O12:O19) -> 1856.139 | P20: =SUM(P12:P19) -> 1941.979 | Q20: =SUM(Q12:Q19) -> 54 | R20: =SUM(R12:R19) -> 0 | S20: =SUM(S12:S19) -> 4894.183 | T20: =SUM(T12:T19) -> 5433.971 | U20: =SUM(U12:U19) -> 46 | V20: =SUM(V12:V19) -> 0 | ... Z20: =SUM(Z12:Z19) -> 0 | AB20: =SUBTOTAL(9,AB12:AB19) -> 14332.09 | AC20: =SUBTOTAL(9,AC12:AC19) -> 10835.718 | AD20: =SUBTOTAL(9,AD12:AD19) -> 9451.838 | AE20: =SUBTOTAL(9,AE12:AE19) -> 163.958 | AF20: =SUBTOTAL(9,AF12:AF19) -> 0 | AG20: =(AD20+AF20+AE20)/AC20 -> 0.88741657 | AH20: =IFERROR(((AD20+AF20+AE20)/AB20-1),0) -> -0.32907231 | AI20: =AC20-AD20-AF20-AE20 -> 1219.9223 | AJ20: =SUM(AJ12:AJ19) -> 6436.716 | AK20: =SUM(AK12:AK19) -> 2867.524 | AL20: =SUM(AL12:AL19) -> 45.125 | AM20: =SUM(AM12:AM19) -> 0 | AN20: =SUM(AN12:AN19) -> 3615.471 | AO20: =SUM(AO12:AO19) -> 2591.363 | AP20: =SUM(AP12:AP19) -> 32.833 | AQ20: =SUM(AQ12:AQ19) -> 0 | ... AU20: =SUM(AU12:AU19) -> 0 | AW20: =SUBTOTAL(9,AW12:AW19) -> 8494.029 | AX20: =SUBTOTAL(9,AX12:AX19) -> 10191.267 | AY20: =SUBTOTAL(9,AY12:AY19) -> 11094.633 | AZ20: =SUBTOTAL(9,AZ12:AZ19) -> 377.124 | BA20: =SUBTOTAL(9,BA12:BA19) -> 0 | BB20: =(AY20+AZ20+BA20)/AX20 -> 1.1256458 | BC20: =IFERROR(((AY20+AZ20+BA20)/AW20-1),0) -> 0.3505672 | BD20: =AX20-AY20-BA20-AZ20 -> -1280.4899 | BE20: =SUM(BE12:BE19) -> 2064.847 | BF20: =SUM(BF12:BF19) -> 2538.517 | BG20: =SUM(BG12:BG19) -> 60.583 | BH20: =SUM(BH12:BH19) -> 0 | BI20: =SUM(BI12:BI19) -> 2460.051 | BJ20: =SUM(BJ12:BJ19) -> 3092.492 | BK20: =SUM(BK12:BK19) -> 70.333 | BL20: =SUM(BL12:BL19) -> 0 | ... BP20: =SUM(BP12:BP19) -> 0 | BR20: =SUBTOTAL(9,BR12:BR19) -> 4968.702 | BS20: =SUBTOTAL(9,BS12:BS19) -> 10857 | BT20: =SUBTOTAL(9,BT12:BT19) -> 5715.708 | BU20: =SUBTOTAL(9,BU12:BU19) -> 225 | BV20: =SUBTOTAL(9,BV12:BV19) -> 199.833 | BW20: =(BT20+BU20+BV20)/BS20 -> 0.56558359 | BX20: =IFERROR(((BT20+BU20+BV20)/BR20-1),0) -> 0.23584409 | BY20: =BS20-BT20-BU20-BV20 -> 4716.459 | BZ20: =SUM(BZ12:BZ19) -> 1081.053 | CA20: =SUM(CA12:CA19) -> 1228.021 | CB20: =SUM(CB12:CB19) -> 58.875 | CC20: =SUM(CC12:CC19) -> 0 | CD20: =SUM(CD12:CD19) -> 2000.043 | CE20: =SUM(CE12:CE19) -> 2880.931 | CF20: =SUM(CF12:CF19) -> 47.667 | CG20: =SUM(CG12:CG19) -> 0 | ... CK20: =SUM(CK12:CK19) -> 225 | CM20: =SUBTOTAL(9,CM12:CM19) -> 42134.62 | CN20: =SUBTOTAL(9,CN12:CN19) -> 44525.665 | CO20: =SUBTOTAL(9,CO12:CO19) -> 41720.483 | CP20: =SUBTOTAL(9,CP12:CP19) -> 891.582 | CQ20: =SUBTOTAL(9,CQ12:CQ19) -> 199.833 | CR20: =(CO20+CP20+CQ20)/CN20 -> 0.96151057 | CS20: =IFERROR(((CO20+CP20+CQ20)/CM20-1),0) -> 0.016074145 | CT20: =CN20-CO20-CQ20-CP20 -> 1713.7674

Sheet Rede
G7: =SUBTOTAL(9,G10:G23) -> 14339.799 | H7: =SUBTOTAL(9,H10:H23) -> 12641.68 | I7: =SUBTOTAL(9,I10:I23) -> 15458.304 | J7: =SUBTOTAL(9,J10:J23) -> 125.5 | K7: =SUBTOTAL(9,K10:K23) -> 0 | L7: =IFERROR(((I7+K7+J7)/H7),0) -> 1.232732 | M7: =IFERROR(((I7+J7+K7)/G7-1),0) -> 0.086751913 | N7: =H7-I7-J7-K7 -> -2942.124 | O7: =SUBTOTAL(9,O10:O23) -> 1856.139 | P7: =SUBTOTAL(9,P10:P23) -> 1941.979 | Q7: =SUBTOTAL(9,Q10:Q23) -> 54 | R7: =SUBTOTAL(9,R10:R23) -> 0 | S7: =SUBTOTAL(9,S10:S23) -> 4894.183 | T7: =SUBTOTAL(9,T10:T23) -> 5433.971 | U7: =SUBTOTAL(9,U10:U23) -> 46 | V7: =SUBTOTAL(9,V10:V23) -> 0 | ... Z7: =SUBTOTAL(9,Z10:Z23) -> 0 | AB7: =SUBTOTAL(9,AB10:AB23) -> 14332.09 | AC7: =SUBTOTAL(9,AC10:AC23) -> 10835.718 | AD7: =SUBTOTAL(9,AD10:AD23) -> 9451.838 | AE7: =SUBTOTAL(9,AE10:AE23) -> 163.958 | AF7: =SUBTOTAL(9,AF10:AF23) -> 0 | AG7: =IFERROR(((AD7+AF7+AE7)/AC7),0) -> 0.88741657 | AH7: =IFERROR(((AD7+AE7+AF7)/AB7-1),0) -> -0.32907231 | AI7: =AC7-AD7-AE7-AF7 -> 1219.9223 | AJ7: =SUBTOTAL(9,AJ10:AJ23) -> 6436.716 | AK7: =SUBTOTAL(9,AK10:AK23) -> 2867.524 | AL7: =SUBTOTAL(9,AL10:AL23) -> 45.125 | AM7: =SUBTOTAL(9,AM10:AM23) -> 0 | AN7: =SUBTOTAL(9,AN10:AN23) -> 3615.471 | AO7: =SUBTOTAL(9,AO10:AO23) -> 2591.363 | AP7: =SUBTOTAL(9,AP10:AP23) -> 32.833 | AQ7: =SUBTOTAL(9,AQ10:AQ23) -> 0 | ... AU7: =SUBTOTAL(9,AU10:AU23) -> 0 | AW7: =SUBTOTAL(9,AW10:AW23) -> 8494.029 | AX7: =SUBTOTAL(9,AX10:AX23) -> 10191.267 | AY7: =SUBTOTAL(9,AY10:AY23) -> 11094.633 | AZ7: =SUBTOTAL(9,AZ10:AZ23) -> 377.124 | BA7: =SUBTOTAL(9,BA10:BA23) -> 0 | BB7: =IFERROR(((AY7+BA7+AZ7)/AX7),0) -> 1.1256458 | BC7: =IFERROR(((AY7+AZ7+BA7)/AW7-1),0) -> 0.3505672 | BD7: =AX7-AY7-AZ7-BA7 -> -1280.4899 | BE7: =SUBTOTAL(9,BE10:BE23) -> 2064.847 | BF7: =SUBTOTAL(9,BF10:BF23) -> 2538.517 | BG7: =SUBTOTAL(9,BG10:BG23) -> 60.583 | BH7: =SUBTOTAL(9,BH10:BH23) -> 0 | BI7: =SUBTOTAL(9,BI10:BI23) -> 2460.051 | BJ7: =SUBTOTAL(9,BJ10:BJ23) -> 3092.492 | BK7: =SUBTOTAL(9,BK10:BK23) -> 70.333 | BL7: =SUBTOTAL(9,BL10:BL23) -> 0 | ... BP7: =SUBTOTAL(9,BP10:BP23) -> 0 | BR7: =SUBTOTAL(9,BR10:BR23) -> 4968.702 | BS7: =SUBTOTAL(9,BS10:BS23) -> 10857 | BT7: =SUBTOTAL(9,BT10:BT23) -> 5715.708 | BU7: =SUBTOTAL(9,BU10:BU23) -> 225 | BV7: =SUBTOTAL(9,BV10:BV23) -> 199.833 | BW7: =IFERROR(((BT7+BV7+BU7)/BS7),0) -> 0.56558359 | BX7: =IFERROR(((BT7+BU7+BV7)/BR7-1),0) -> 0.23584409 | BY7: =BS7-BT7-BU7-BV7 -> 4716.459 | BZ7: =SUBTOTAL(9,BZ10:BZ23) -> 1081.053 | CA7: =SUBTOTAL(9,CA10:CA23) -> 1228.021 | CB7: =SUBTOTAL(9,CB10:CB23) -> 58.875 | CC7: =SUBTOTAL(9,CC10:CC23) -> 0 | CD7: =SUBTOTAL(9,CD10:CD23) -> 2000.043 | CE7: =SUBTOTAL(9,CE10:CE23) -> 2880.931 | CF7: =SUBTOTAL(9,CF10:CF23) -> 47.667 | CG7: =SUBTOTAL(9,CG10:CG23) -> 0 | ... CK7: =SUBTOTAL(9,CK10:CK23) -> 225 | CM7: =SUBTOTAL(9,CM10:CM23) -> 42134.62 | CN7: =SUBTOTAL(9,CN10:CN23) -> 44525.665 | CO7: =SUBTOTAL(9,CO10:CO23) -> 41720.483 | CP7: =SUBTOTAL(9,CP10:CP23) -> 891.582 | CQ7: =SUBTOTAL(9,CQ10:CQ23) -> 199.833 | CR7: =IFERROR(((CO7+CQ7+CP7)/CN7),0) -> 0.96151057 | CS7: =IFERROR(((CO7+CP7+CQ7)/CM7-1),0) -> 0.016074145 | CT7: =CN7-CO7-CP7-CQ7 -> 1713.7674
G8: Q1 - JULHO A SETEMBRO | O8: JULHO | S8: AGOSTO | W8: SETEMBRO | AB8: Q2 - OUTUBRO A DEZEMBRO | AJ8: OUTUBRO | AN8: NOVEMBRO | AR8: DEZEMBRO | AW8: Q3 - JANEIRO A MARÇO | BE8: JANEIRO | BI8: FEVEREIRO | BM8: MARÇO | BR8: Q4 - ABRIL A JUNHO | BZ8: ABRIL | CD8: MAIO | CH8: JUNHO | CM8: TOP CONTAS FY26 ANO FISCAL
C9: EQUIPE | D9: CÓD | E9: ÁREA | F9: REDE | G9: HIST | H9: META | I9: FAT | J9: BONIF | K9: MÁQ | L9: % META | M9: % HIST | N9: GAP META | O9: HIST | P9: FAT | Q9: BONIF | R9: MÁQ | S9: HIST | T9: FAT | U9: BONIF | V9: MÁQ | W9: HIST | X9: FAT | Y9: BONIF | Z9: MÁQ | AB9: HIST | AC9: META | AD9: FAT | AE9: BONIF | AF9: MÁQ | AG9: % META | AH9: % HIST | AI9: GAP META | AJ9: HIST | AK9: FAT | AL9: BONIF | AM9: MÁQ | AN9: HIST | AO9: FAT | AP9: BONIF | AQ9: MÁQ | AR9: HIST | AS9: FAT | AT9: BONIF | AU9: MÁQ | AW9: HIST | AX9: META | AY9: FAT | AZ9: BONIF | BA9: MÁQ | BB9: % META | BC9: % HIST | BD9: GAP META | BE9: HIST | BF9: FAT | BG9: BONIF | BH9: MÁQ | BI9: HIST | BJ9: FAT | BK9: BONIF | BL9: MÁQ | BM9: HIST | BN9: FAT | BO9: BONIF | BP9: MÁQ | BR9: HIST | BS9: META | BT9: FAT | BU9: BONIF | BV9: MÁQ | BW9: % META | BX9: % HIST | BY9: GAP META | BZ9: HIST | CA9: FAT | CB9: BONIF | CC9: MÁQ | CD9: HIST | CE9: FAT | CF9: BONIF | CG9: MÁQ | CH9: HIST | CI9: FAT | CJ9: BONIF | CK9: MÁQ | CM9: HIST | CN9: META | CO9: FAT | CP9: BONIF | CQ9: MÁQ | CR9: % META | CS9: % HIST | CT9: GAP META
C10: FLP-SUL MC/KA D | D10: 771 | E10: MC-FLP D | F10: REDE HIPER SELECT | G10: =O10+S10+W10 -> 1650.944 | H10: =_xlfn.XLOOKUP($F10,Metas!$B:$B,Metas!Q:Q,0,0,1) -> 898.53 | I10: =P10+T10+X10 -> 690.575 | J10: =Q10+U10+Y10 -> 0 | K10: =R10+V10+Z10 -> 0 | L10: =IFERROR(((I10+K10+J10)/H10),0) -> 0.76856087 | M10: =IFERROR(((I10+J10+K10)/G10-1),0) -> -0.58170901 | N10: =H10-I10-J10-K10 -> 207.955 | O10: =SUMIF(Cliente!$H:$H,Rede!F10,Cliente!$N:$N) -> 270.844 | P10: =SUMIF(Cliente!$H:$H,Rede!$F10,Cliente!$O:$O) -> 10.708 | Q10: =SUMIF(Cliente!$H:$H,Rede!$F10,Cliente!$P:$P) -> 0 | R10: =SUMIF(Cliente!$H:$H,Rede!$F10,Cliente!$Q:$Q) -> 0 | S10: =SUMIF(Cliente!$H:$H,Rede!$F10,Cliente!$R:$R) -> 854.558 | T10: =SUMIF(Cliente!$H:$H,Rede!$F10,Cliente!$S:$S) -> 803.7 | U10: =SUMIF(Cliente!$H:$H,Rede!$F10,Cliente!$T:$T) -> 0 | V10: =SUMIF(Cliente!$H:$H,Rede!$F10,Cliente!$U:$U) -> 0 | W10: =SUMIF(Cliente!$H:$H,Rede!$F10,Cliente!$V:$V) -> 525.542 | X10: =SUMIF(Cliente!$H:$H,Rede!$F10,Cliente!$W:$W) -> -123.833 | Y10: =SUMIF(Cliente!$H:$H,Rede!$F10,Cliente!$X:$X) -> 0 | Z10: =SUMIF(Cliente!$H:$H,Rede!$F10,Cliente!$Y:$Y) -> 0 | AB10: =AJ10+AN10+AR10 -> 1068.366 | AC10: =_xlfn.XLOOKUP(F10,Metas!B:B,Metas!R:R,0,0,1) -> 770.16614 | AD10: =AK10+AO10+AS10 -> 557.392 | AE10: =AL10+AP10+AT10 -> 0 | AF10: =AM10+AQ10+AU10 -> 0 | AG10: =IFERROR(((AD10+AE10+AF10)/AC10),0) -> 0.72372955 | AH10: =IFERROR(((AD10+AE10+AF10)/AB10-1),0) -> -0.47827617 | AI10: =AC10-AD10-AE10-AF10 -> 212.77414 | AJ10: =SUMIF(Cliente!$H:$H,Rede!$F10,Cliente!$AE:$AE) -> 814.133 | AK10: =SUMIF(Cliente!$H:$H,Rede!$F10,Cliente!$AF:$AF) -> 230.108 | AL10: =SUMIF(Cliente!$H:$H,Rede!$F10,Cliente!$AG:$AG) -> 0 | AM10: =SUMIF(Cliente!$H:$H,Rede!$F10,Cliente!$AH:$AH) -> 0 | AN10: =SUMIF(Cliente!$H:$H,Rede!$F10,Cliente!$AI:$AI) -> 111.858 | AO10: =SUMIF(Cliente!$H:$H,Rede!$F10,Cliente!$AJ:$AJ) -> 158.5 | AP10: =SUMIF(Cliente!$H:$H,Rede!$F10,Cliente!$AK:$AK) -> 0 | AQ10: =SUMIF(Cliente!$H:$H,Rede!$F10,Cliente!$AL:$AL) -> 0 | AR10: =SUMIF(Cliente!$H:$H,Rede!$F10,Cliente!$AM:$AM) -> 142.375 | AS10: =SUMIF(Cliente!$H:$H,Rede!$F10,Cliente!$AN:$AN) -> 168.784 | AT10: =SUMIF(Cliente!$H:$H,Rede!$F10,Cliente!$AO:$AO) -> 0 | AU10: =SUMIF(Cliente!$H:$H,Rede!$F10,Cliente!$AP:$AP) -> 0 | AW10: =BE10+BI10+BM10 -> 455.592 | AX10: =_xlfn.XLOOKUP(Rede!F10,Metas!B:B,Metas!S:S,0,0,1) -> 724.36074 | AY10: =BF10+BJ10+BN10 -> 761.767 | AZ10: =BG10+BK10+BO10 -> 0 | BA10: =BH10+BL10+BP10 -> 0 | BB10: =IFERROR(((AY10+AZ10+BA10)/AX10),0) -> 1.0516404 | BC10: =IFERROR(((AY10+AZ10+BA10)/AW10-1),0) -> 0.6720377 | BD10: =AX10-AY10-AZ10-BA10 -> -37.40626 | BE10: =SUMIF(Cliente!$H:$H,Rede!F10,Cliente!$AV:$AV) -> 286.55 | BF10: =SUMIF(Cliente!$H:$H,Rede!F10,Cliente!$AW:$AW) -> 102.017 | BG10: =SUMIF(Cliente!$H:$H,Rede!$F10,Cliente!$AX:$AX) -> 0 | BH10: =SUMIF(Cliente!$H:$H,Rede!$F10,Cliente!$AY:$AY) -> 0 | BI10: =SUMIF(Cliente!$H:$H,Rede!F10,Cliente!$AZ:$AZ) -> 82.959 | BJ10: =SUMIF(Cliente!$H:$H,Rede!F10,Cliente!$BA:$BA) -> 68.25 | BK10: =SUMIF(Cliente!$H:$H,Rede!$F10,Cliente!$BB:$BB) -> 0 | BL10: =SUMIF(Cliente!$H:$H,Rede!$F10,Cliente!$BC:$BC) -> 0 | BM10: =SUMIF(Cliente!$H:$H,Rede!F10,Cliente!$BD:$BD) -> 86.083 | BN10: =SUMIF(Cliente!$H:$H,Rede!F10,Cliente!$BE:$BE) -> 591.5 | BO10: =SUMIF(Cliente!$H:$H,Rede!$F10,Cliente!$BF:$BF) -> 0 | BP10: =SUMIF(Cliente!$H:$H,Rede!$F10,Cliente!$BG:$BG) -> 0 | BR10: =BZ10+CD10+CH10 -> 151.605 | BS10: =_xlfn.XLOOKUP(Rede!F10,Metas!B:B,Metas!T:T,0,0,1) -> 771 | BT10: =CA10+CE10+CI10 -> 79.889 | BU10: =CB10+CF10+CJ10 -> 0 | BV10: =CC10+CG10+CK10 -> 0 | BW10: =IFERROR(((BT10+BV10+BU10)/BS10),0) -> 0.10361738 | BX10: =IFERROR(((BT10+BU10+BV10)/BR10-1),0) -> -0.47304508 | BY10: =BS10-BT10-BU10-BV10 -> 691.111 | BZ10: =SUMIF(Cliente!$H:$H,Rede!F10,Cliente!$BM:$BM) -> 24.083 | CA10: =SUMIF(Cliente!$H:$H,Rede!F10,Cliente!$BN:$BN) -> -121 | CB10: =SUMIF(Cliente!$H:$H,Rede!$F10,Cliente!$BO:$BO) -> 0 | CC10: =SUMIF(Cliente!$H:$H,Rede!$F10,Cliente!$BP:$BP) -> 0 | CD10: =SUMIF(Cliente!$H:$H,Rede!F10,Cliente!$BQ:$BQ) -> 59.867 | CE10: =SUMIF(Cliente!$H:$H,Rede!F10,Cliente!$BR:$BR) -> 111.25 | CF10: =SUMIF(Cliente!$H:$H,Rede!$F10,Cliente!$BS:$BS) -> 0 | CG10: =SUMIF(Cliente!$H:$H,Rede!$F10,Cliente!$BT:$BT) -> 0 | CH10: =SUMIF(Cliente!$H:$H,Rede!$F10,Cliente!$BU:$BU) -> 67.655 | CI10: =SUMIF(Cliente!$H:$H,Rede!$F10,Cliente!$BV:$BV) -> 89.639 | CJ10: =SUMIF(Cliente!$H:$H,Rede!$F10,Cliente!$BW:$BW) -> 0 | CK10: =SUMIF(Cliente!$H:$H,Rede!$F10,Cliente!$BX:$BX) -> 0 | CM10: =G10+AB10+AW10+BR10 -> 3326.507 | CN10: =H10+AC10+AX10+BS10 -> 3164.0569 | CO10: =I10+AD10+AY10+BT10 -> 2089.623 | CP10: =J10+AE10+AZ10+BU10 -> 0 | CQ10: =K10+AF10+BA10+BV10 -> 0 | CR10: =IFERROR(((CO10+CQ10+CP10)/CN10),0) -> 0.66042523 | CS10: =IFERROR(((CO10+CP10+CQ10)/CM10-1),0) -> -0.37182666 | CT10: =CN10-CO10-CP10-CQ10 -> 1074.4339
C11: FLP-SUL MC/KA D | D11: 3919 | E11: MC-TBCR D | F11: REDE SM ROSSO | G11: =O11+S11+W11 -> 82.917 | H11: =_xlfn.XLOOKUP($F11,Metas!$B:$B,Metas!Q:Q,0,0,1) -> 574.64 | I11: =P11+T11+X11 -> 1734.916 | J11: =Q11+U11+Y11 -> 18.333 | K11: =R11+V11+Z11 -> 0 | L11: =IFERROR(((I11+K11+J11)/H11),0) -> 3.0510389 | M11: =IFERROR(((I11+J11+K11)/G11-1),0) -> 20.144627 | N11: =H11-I11-J11-K11 -> -1178.609 | O11: =SUMIF(Cliente!$H:$H,Rede!F11,Cliente!$N:$N) -> -1 | P11: =SUMIF(Cliente!$H:$H,Rede!$F11,Cliente!$O:$O) -> 173 | Q11: =SUMIF(Cliente!$H:$H,Rede!$F11,Cliente!$P:$P) -> 14.75 | R11: =SUMIF(Cliente!$H:$H,Rede!$F11,Cliente!$Q:$Q) -> 0 | S11: =SUMIF(Cliente!$H:$H,Rede!$F11,Cliente!$R:$R) -> 84 | T11: =SUMIF(Cliente!$H:$H,Rede!$F11,Cliente!$S:$S) -> 788.333 | U11: =SUMIF(Cliente!$H:$H,Rede!$F11,Cliente!$T:$T) -> 2.583 | V11: =SUMIF(Cliente!$H:$H,Rede!$F11,Cliente!$U:$U) -> 0 | W11: =SUMIF(Cliente!$H:$H,Rede!$F11,Cliente!$V:$V) -> -0.083 | X11: =SUMIF(Cliente!$H:$H,Rede!$F11,Cliente!$W:$W) -> 773.583 | Y11: =SUMIF(Cliente!$H:$H,Rede!$F11,Cliente!$X:$X) -> 1 | Z11: =SUMIF(Cliente!$H:$H,Rede!$F11,Cliente!$Y:$Y) -> 0 | AB11: =AJ11+AN11+AR11 -> 1206.354 | AC11: =_xlfn.XLOOKUP(F11,Metas!B:B,Metas!R:R,0,0,1) -> 492.54739 | AD11: =AK11+AO11+AS11 -> 525.938 | AE11: =AL11+AP11+AT11 -> 24.625 | AF11: =AM11+AQ11+AU11 -> 0 | AG11: =IFERROR(((AD11+AE11+AF11)/AC11),0) -> 1.1177869 | AH11: =IFERROR(((AD11+AE11+AF11)/AB11-1),0) -> -0.54361406 | AI11: =AC11-AD11-AE11-AF11 -> -58.015608 | AJ11: =SUMIF(Cliente!$H:$H,Rede!$F11,Cliente!$AE:$AE) -> 1136.604 | AK11: =SUMIF(Cliente!$H:$H,Rede!$F11,Cliente!$AF:$AF) -> 245.75 | AL11: =SUMIF(Cliente!$H:$H,Rede!$F11,Cliente!$AG:$AG) -> 9.625 | AM11: =SUMIF(Cliente!$H:$H,Rede!$F11,Cliente!$AH:$AH) -> 0 | AN11: =SUMIF(Cliente!$H:$H,Rede!$F11,Cliente!$AI:$AI) -> 60.75 | AO11: =SUMIF(Cliente!$H:$H,Rede!$F11,Cliente!$AJ:$AJ) -> 194.188 | AP11: =SUMIF(Cliente!$H:$H,Rede!$F11,Cliente!$AK:$AK) -> 13 | AQ11: =SUMIF(Cliente!$H:$H,Rede!$F11,Cliente!$AL:$AL) -> 0 | AR11: =SUMIF(Cliente!$H:$H,Rede!$F11,Cliente!$AM:$AM) -> 9 | AS11: =SUMIF(Cliente!$H:$H,Rede!$F11,Cliente!$AN:$AN) -> 86 | AT11: =SUMIF(Cliente!$H:$H,Rede!$F11,Cliente!$AO:$AO) -> 2 | AU11: =SUMIF(Cliente!$H:$H,Rede!$F11,Cliente!$AP:$AP) -> 0 | AW11: =BE11+BI11+BM11 -> 393.542 | AX11: =_xlfn.XLOOKUP(Rede!F11,Metas!B:B,Metas!S:S,0,0,1) -> 463.25328 | AY11: =BF11+BJ11+BN11 -> 938 | AZ11: =BG11+BK11+BO11 -> 85.083 | BA11: =BH11+BL11+BP11 -> 0 | BB11: =IFERROR(((AY11+AZ11+BA11)/AX11),0) -> 2.2084744 | BC11: =IFERROR(((AY11+AZ11+BA11)/AW11-1),0) -> 1.5996793 | BD11: =AX11-AY11-AZ11-BA11 -> -559.82972 | BE11: =SUMIF(Cliente!$H:$H,Rede!F11,Cliente!$AV:$AV) -> 211 | BF11: =SUMIF(Cliente!$H:$H,Rede!F11,Cliente!$AW:$AW) -> 355 | BG11: =SUMIF(Cliente!$H:$H,Rede!$F11,Cliente!$AX:$AX) -> 24.583 | BH11: =SUMIF(Cliente!$H:$H,Rede!$F11,Cliente!$AY:$AY) -> 0 | BI11: =SUMIF(Cliente!$H:$H,Rede!F11,Cliente!$AZ:$AZ) -> -2.083 | BJ11: =SUMIF(Cliente!$H:$H,Rede!F11,Cliente!$BA:$BA) -> 307 | BK11: =SUMIF(Cliente!$H:$H,Rede!$F11,Cliente!$BB:$BB) -> 19.25 | BL11: =SUMIF(Cliente!$H:$H,Rede!$F11,Cliente!$BC:$BC) -> 0 | BM11: =SUMIF(Cliente!$H:$H,Rede!F11,Cliente!$BD:$BD) -> 184.625 | BN11: =SUMIF(Cliente!$H:$H,Rede!F11,Cliente!$BE:$BE) -> 276 | BO11: =SUMIF(Cliente!$H:$H,Rede!$F11,Cliente!$BF:$BF) -> 41.25 | BP11: =SUMIF(Cliente!$H:$H,Rede!$F11,Cliente!$BG:$BG) -> 0 | BR11: =BZ11+CD11+CH11 -> 186.917 | BS11: =_xlfn.XLOOKUP(Rede!F11,Metas!B:B,Metas!T:T,0,0,1) -> 495 | BT11: =CA11+CE11+CI11 -> 181 | BU11: =CC11+CG11+CK11 -> 0 | BV11: =CB11+CF11+CJ11 -> 23 | BW11: =IFERROR(((BT11+BV11+BU11)/BS11),0) -> 0.41212121 | BX11: =IFERROR(((BT11+BU11+BV11)/BR11-1),0) -> 0.091393506 | BY11: =BS11-BT11-BU11-BV11 -> 291 | BZ11: =SUMIF(Cliente!$H:$H,Rede!F11,Cliente!$BM:$BM) -> 0 | CA11: =SUMIF(Cliente!$H:$H,Rede!F11,Cliente!$BN:$BN) -> 140 | CB11: =SUMIF(Cliente!$H:$H,Rede!$F11,Cliente!$BO:$BO) -> 16 | CC11: =SUMIF(Cliente!$H:$H,Rede!$F11,Cliente!$BP:$BP) -> 0 | CD11: =SUMIF(Cliente!$H:$H,Rede!F11,Cliente!$BQ:$BQ) -> 102.917 | CE11: =SUMIF(Cliente!$H:$H,Rede!F11,Cliente!$BR:$BR) -> 41 | CF11: =SUMIF(Cliente!$H:$H,Rede!$F11,Cliente!$BS:$BS) -> 0 | CG11: =SUMIF(Cliente!$H:$H,Rede!$F11,Cliente!$BT:$BT) -> 0 | CH11: =SUMIF(Cliente!$H:$H,Rede!$F11,Cliente!$BU:$BU) -> 84 | CI11: =SUMIF(Cliente!$H:$H,Rede!$F11,Cliente!$BV:$BV) -> 0 | CJ11: =SUMIF(Cliente!$H:$H,Rede!$F11,Cliente!$BW:$BW) -> 7 | CK11: =SUMIF(Cliente!$H:$H,Rede!$F11,Cliente!$BX:$BX) -> 0 | CM11: =G11+AB11+AW11+BR11 -> 1869.73 | CN11: =H11+AC11+AX11+BS11 -> 2025.4407 | CO11: =I11+AD11+AY11+BT11 -> 3379.854 | CP11: =J11+AE11+AZ11+BU11 -> 128.041 | CQ11: =K11+AF11+BA11+BV11 -> 23 | CR11: =IFERROR(((CO11+CQ11+CP11)/CN11),0) -> 1.7432725 | CS11: =IFERROR(((CO11+CP11+CQ11)/CM11-1),0) -> 0.88845181 | CT11: =CN11-CO11-CP11-CQ11 -> -1505.4543
C12: FLP-SUL MC/KA D | D12: 3919 | E12: MC-TBCR D | F12: REDE MANENTI | G12: =O12+S12+W12 -> 1796.008 | H12: =_xlfn.XLOOKUP($F12,Metas!$B:$B,Metas!Q:Q,0,0,1) -> 949.44 | I12: =P12+T12+X12 -> 1664.188 | J12: =Q12+U12+Y12 -> 27 | K12: =R12+V12+Z12 -> 0 | L12: =IFERROR(((I12+K12+J12)/H12),0) -> 1.7812479 | M12: =IFERROR(((I12+J12+K12)/G12-1),0) -> -0.058362769 | N12: =H12-I12-J12-K12 -> -741.748 | O12: =SUMIF(Cliente!$H:$H,Rede!F12,Cliente!$N:$N) -> 97.179 | P12: =SUMIF(Cliente!$H:$H,Rede!$F12,Cliente!$O:$O) -> 263.875 | Q12: =SUMIF(Cliente!$H:$H,Rede!$F12,Cliente!$P:$P) -> 3 | R12: =SUMIF(Cliente!$H:$H,Rede!$F12,Cliente!$Q:$Q) -> 0 | S12: =SUMIF(Cliente!$H:$H,Rede!$F12,Cliente!$R:$R) -> 80.521 | T12: =SUMIF(Cliente!$H:$H,Rede!$F12,Cliente!$S:$S) -> 85.146 | U12: =SUMIF(Cliente!$H:$H,Rede!$F12,Cliente!$T:$T) -> 7 | V12: =SUMIF(Cliente!$H:$H,Rede!$F12,Cliente!$U:$U) -> 0 | W12: =SUMIF(Cliente!$H:$H,Rede!$F12,Cliente!$V:$V) -> 1618.308 | X12: =SUMIF(Cliente!$H:$H,Rede!$F12,Cliente!$W:$W) -> 1315.167 | Y12: =SUMIF(Cliente!$H:$H,Rede!$F12,Cliente!$X:$X) -> 17 | Z12: =SUMIF(Cliente!$H:$H,Rede!$F12,Cliente!$Y:$Y) -> 0 | AB12: =AJ12+AN12+AR12 -> 1017.884 | AC12: =_xlfn.XLOOKUP(F12,Metas!B:B,Metas!R:R,0,0,1) -> 813.80506 | AD12: =AK12+AO12+AS12 -> 1064.055 | AE12: =AL12+AP12+AT12 -> 43 | AF12: =AM12+AQ12+AU12 -> 0 | AG12: =IFERROR(((AD12+AE12+AF12)/AC12),0) -> 1.3603442 | AH12: =IFERROR(((AD12+AE12+AF12)/AB12-1),0) -> 0.087604285 | AI12: =AC12-AD12-AE12-AF12 -> -293.24994 | AJ12: =SUMIF(Cliente!$H:$H,Rede!$F12,Cliente!$AE:$AE) -> 219.521 | AK12: =SUMIF(Cliente!$H:$H,Rede!$F12,Cliente!$AF:$AF) -> 74.083 | AL12: =SUMIF(Cliente!$H:$H,Rede!$F12,Cliente!$AG:$AG) -> 31 | AM12: =SUMIF(Cliente!$H:$H,Rede!$F12,Cliente!$AH:$AH) -> 0 | AN12: =SUMIF(Cliente!$H:$H,Rede!$F12,Cliente!$AI:$AI) -> 125.863 | AO12: =SUMIF(Cliente!$H:$H,Rede!$F12,Cliente!$AJ:$AJ) -> 397.764 | AP12: =SUMIF(Cliente!$H:$H,Rede!$F12,Cliente!$AK:$AK) -> 2 | AQ12: =SUMIF(Cliente!$H:$H,Rede!$F12,Cliente!$AL:$AL) -> 0 | AR12: =SUMIF(Cliente!$H:$H,Rede!$F12,Cliente!$AM:$AM) -> 672.5 | AS12: =SUMIF(Cliente!$H:$H,Rede!$F12,Cliente!$AN:$AN) -> 592.208 | AT12: =SUMIF(Cliente!$H:$H,Rede!$F12,Cliente!$AO:$AO) -> 10 | AU12: =SUMIF(Cliente!$H:$H,Rede!$F12,Cliente!$AP:$AP) -> 0 | AW12: =BE12+BI12+BM12 -> 135.066 | AX12: =_xlfn.XLOOKUP(Rede!F12,Metas!B:B,Metas!S:S,0,0,1) -> 765.40424 | AY12: =BF12+BJ12+BN12 -> 801.854 | AZ12: =BG12+BK12+BO12 -> 47.583 | BA12: =BH12+BL12+BP12 -> 0 | BB12: =IFERROR(((AY12+AZ12+BA12)/AX12),0) -> 1.1097887 | BC12: =IFERROR(((AY12+AZ12+BA12)/AW12-1),0) -> 5.2890513 | BD12: =AX12-AY12-AZ12-BA12 -> -84.032759 | BE12: =SUMIF(Cliente!$H:$H,Rede!F12,Cliente!$AV:$AV) -> 10.396 | BF12: =SUMIF(Cliente!$H:$H,Rede!F12,Cliente!$AW:$AW) -> 294.021 | BG12: =SUMIF(Cliente!$H:$H,Rede!$F12,Cliente!$AX:$AX) -> 7.75 | BH12: =SUMIF(Cliente!$H:$H,Rede!$F12,Cliente!$AY:$AY) -> 0 | BI12: =SUMIF(Cliente!$H:$H,Rede!F12,Cliente!$AZ:$AZ) -> 70.463 | BJ12: =SUMIF(Cliente!$H:$H,Rede!F12,Cliente!$BA:$BA) -> 110.583 | BK12: =SUMIF(Cliente!$H:$H,Rede!$F12,Cliente!$BB:$BB) -> 9.583 | BL12: =SUMIF(Cliente!$H:$H,Rede!$F12,Cliente!$BC:$BC) -> 0 | BM12: =SUMIF(Cliente!$H:$H,Rede!F12,Cliente!$BD:$BD) -> 54.207 | BN12: =SUMIF(Cliente!$H:$H,Rede!F12,Cliente!$BE:$BE) -> 397.25 | BO12: =SUMIF(Cliente!$H:$H,Rede!$F12,Cliente!$BF:$BF) -> 30.25 | BP12: =SUMIF(Cliente!$H:$H,Rede!$F12,Cliente!$BG:$BG) -> 0 | BR12: =BZ12+CD12+CH12 -> 135.585 | BS12: =_xlfn.XLOOKUP(Rede!F12,Metas!B:B,Metas!T:T,0,0,1) -> 816 | BT12: =CA12+CE12+CI12 -> 427.067 | BU12: =CC12+CG12+CK12 -> 0 | BV12: =CB12+CF12+CJ12 -> 8.5 | BW12: =IFERROR(((BT12+BV12+BU12)/BS12),0) -> 0.53378309 | BX12: =IFERROR(((BT12+BU12+BV12)/BR12-1),0) -> 2.2125014 | BY12: =BS12-BT12-BU12-BV12 -> 380.433 | BZ12: =SUMIF(Cliente!$H:$H,Rede!F12,Cliente!$BM:$BM) -> -3.583 | CA12: =SUMIF(Cliente!$H:$H,Rede!F12,Cliente!$BN:$BN) -> 220.667 | CB12: =SUMIF(Cliente!$H:$H,Rede!$F12,Cliente!$BO:$BO) -> 4.667 | CC12: =SUMIF(Cliente!$H:$H,Rede!$F12,Cliente!$BP:$BP) -> 0 | CD12: =SUMIF(Cliente!$H:$H,Rede!F12,Cliente!$BQ:$BQ) -> 154.175 | CE12: =SUMIF(Cliente!$H:$H,Rede!F12,Cliente!$BR:$BR) -> 215.179 | CF12: =SUMIF(Cliente!$H:$H,Rede!$F12,Cliente!$BS:$BS) -> 3.083 | CG12: =SUMIF(Cliente!$H:$H,Rede!$F12,Cliente!$BT:$BT) -> 0 | CH12: =SUMIF(Cliente!$H:$H,Rede!$F12,Cliente!$BU:$BU) -> -15.007 | CI12: =SUMIF(Cliente!$H:$H,Rede!$F12,Cliente!$BV:$BV) -> -8.779 | CJ12: =SUMIF(Cliente!$H:$H,Rede!$F12,Cliente!$BW:$BW) -> 0.75 | CK12: =SUMIF(Cliente!$H:$H,Rede!$F12,Cliente!$BX:$BX) -> 0 | CM12: =G12+AB12+AW12+BR12 -> 3084.543 | CN12: =H12+AC12+AX12+BS12 -> 3344.6493 | CO12: =I12+AD12+AY12+BT12 -> 3957.164 | CP12: =J12+AE12+AZ12+BU12 -> 117.583 | CQ12: =K12+AF12+BA12+BV12 -> 8.5 | CR12: =IFERROR(((CO12+CQ12+CP12)/CN12),0) -> 1.2208296 | CS12: =IFERROR(((CO12+CP12+CQ12)/CM12-1),0) -> 0.32377697 | CT12: =CN12-CO12-CP12-CQ12 -> -738.5977
C13: FLP-SUL MC/KA D | D13: 3919 | E13: MC-TBCR D | F13: REDE VENCEDOR | G13: =O13+S13+W13 -> 617.167 | H13: =_xlfn.XLOOKUP($F13,Metas!$B:$B,Metas!Q:Q,0,0,1) -> 529.5 | I13: =P13+T13+X13 -> 331.25 | J13: =Q13+U13+Y13 -> 14 | K13: =R13+V13+Z13 -> 0 | L13: =IFERROR(((I13+K13+J13)/H13),0) -> 0.65203022 | M13: =IFERROR(((I13+J13+K13)/G13-1),0) -> -0.44058901 | N13: =H13-I13-J13-K13 -> 184.25 | O13: =SUMIF(Cliente!$H:$H,Rede!F13,Cliente!$N:$N) -> -0.083 | P13: =SUMIF(Cliente!$H:$H,Rede!$F13,Cliente!$O:$O) -> 130.708 | Q13: =SUMIF(Cliente!$H:$H,Rede!$F13,Cliente!$P:$P) -> 12 | R13: =SUMIF(Cliente!$H:$H,Rede!$F13,Cliente!$Q:$Q) -> 0 | S13: =SUMIF(Cliente!$H:$H,Rede!$F13,Cliente!$R:$R) -> 120.583 | T13: =SUMIF(Cliente!$H:$H,Rede!$F13,Cliente!$S:$S) -> 64 | U13: =SUMIF(Cliente!$H:$H,Rede!$F13,Cliente!$T:$T) -> 2 | V13: =SUMIF(Cliente!$H:$H,Rede!$F13,Cliente!$U:$U) -> 0 | W13: =SUMIF(Cliente!$H:$H,Rede!$F13,Cliente!$V:$V) -> 496.667 | X13: =SUMIF(Cliente!$H:$H,Rede!$F13,Cliente!$W:$W) -> 136.542 | Y13: =SUMIF(Cliente!$H:$H,Rede!$F13,Cliente!$X:$X) -> 0 | Z13: =SUMIF(Cliente!$H:$H,Rede!$F13,Cliente!$Y:$Y) -> 0 | AB13: =AJ13+AN13+AR13 -> 407 | AC13: =_xlfn.XLOOKUP(F13,Metas!B:B,Metas!R:R,0,0,1) -> 453.85469 | AD13: =AK13+AO13+AS13 -> 547.417 | AE13: =AL13+AP13+AT13 -> 2 | AF13: =AM13+AQ13+AU13 -> 0 | AG13: =IFERROR(((AD13+AE13+AF13)/AC13),0) -> 1.2105571 | AH13: =IFERROR(((AD13+AE13+AF13)/AB13-1),0) -> 0.34991892 | AI13: =AC13-AD13-AE13-AF13 -> -95.562312 | AJ13: =SUMIF(Cliente!$H:$H,Rede!$F13,Cliente!$AE:$AE) -> 117 | AK13: =SUMIF(Cliente!$H:$H,Rede!$F13,Cliente!$AF:$AF) -> 214 | AL13: =SUMIF(Cliente!$H:$H,Rede!$F13,Cliente!$AG:$AG) -> 0 | AM13: =SUMIF(Cliente!$H:$H,Rede!$F13,Cliente!$AH:$AH) -> 0 | AN13: =SUMIF(Cliente!$H:$H,Rede!$F13,Cliente!$AI:$AI) -> 0 | AO13: =SUMIF(Cliente!$H:$H,Rede!$F13,Cliente!$AJ:$AJ) -> 204 | AP13: =SUMIF(Cliente!$H:$H,Rede!$F13,Cliente!$AK:$AK) -> 0 | AQ13: =SUMIF(Cliente!$H:$H,Rede!$F13,Cliente!$AL:$AL) -> 0 | AR13: =SUMIF(Cliente!$H:$H,Rede!$F13,Cliente!$AM:$AM) -> 290 | AS13: =SUMIF(Cliente!$H:$H,Rede!$F13,Cliente!$AN:$AN) -> 129.417 | AT13: =SUMIF(Cliente!$H:$H,Rede!$F13,Cliente!$AO:$AO) -> 2 | AU13: =SUMIF(Cliente!$H:$H,Rede!$F13,Cliente!$AP:$AP) -> 0 | AW13: =BE13+BI13+BM13 -> 485.708 | AX13: =_xlfn.XLOOKUP(Rede!F13,Metas!B:B,Metas!S:S,0,0,1) -> 426.86181 | AY13: =BF13+BJ13+BN13 -> 597.646 | AZ13: =BG13+BK13+BO13 -> 0 | BA13: =BH13+BL13+BP13 -> 0 | BB13: =IFERROR(((AY13+AZ13+BA13)/AX13),0) -> 1.4000924 | BC13: =IFERROR(((AY13+AZ13+BA13)/AW13-1),0) -> 0.23046357 | BD13: =AX13-AY13-AZ13-BA13 -> -170.78419 | BE13: =SUMIF(Cliente!$H:$H,Rede!F13,Cliente!$AV:$AV) -> -8 | BF13: =SUMIF(Cliente!$H:$H,Rede!F13,Cliente!$AW:$AW) -> 9.979 | BG13: =SUMIF(Cliente!$H:$H,Rede!$F13,Cliente!$AX:$AX) -> 0 | BH13: =SUMIF(Cliente!$H:$H,Rede!$F13,Cliente!$AY:$AY) -> 0 | BI13: =SUMIF(Cliente!$H:$H,Rede!F13,Cliente!$AZ:$AZ) -> 215.708 | BJ13: =SUMIF(Cliente!$H:$H,Rede!F13,Cliente!$BA:$BA) -> 192.167 | BK13: =SUMIF(Cliente!$H:$H,Rede!$F13,Cliente!$BB:$BB) -> 0 | BL13: =SUMIF(Cliente!$H:$H,Rede!$F13,Cliente!$BC:$BC) -> 0 | BM13: =SUMIF(Cliente!$H:$H,Rede!F13,Cliente!$BD:$BD) -> 278 | BN13: =SUMIF(Cliente!$H:$H,Rede!F13,Cliente!$BE:$BE) -> 395.5 | BO13: =SUMIF(Cliente!$H:$H,Rede!$F13,Cliente!$BF:$BF) -> 0 | BP13: =SUMIF(Cliente!$H:$H,Rede!$F13,Cliente!$BG:$BG) -> 0 | BR13: =BZ13+CD13+CH13 -> 260.625 | BS13: =_xlfn.XLOOKUP(Rede!F13,Metas!B:B,Metas!T:T,0,0,1) -> 456 | BT13: =CA13+CE13+CI13 -> 335.709 | BU13: =CC13+CG13+CK13 -> 0 | BV13: =CB13+CF13+CJ13 -> 0 | BW13: =IFERROR(((BT13+BV13+BU13)/BS13),0) -> 0.73620395 | BX13: =IFERROR(((BT13+BU13+BV13)/BR13-1),0) -> 0.28809209 | BY13: =BS13-BT13-BU13-BV13 -> 120.291 | BZ13: =SUMIF(Cliente!$H:$H,Rede!F13,Cliente!$BM:$BM) -> 32 | CA13: =SUMIF(Cliente!$H:$H,Rede!F13,Cliente!$BN:$BN) -> -0.083 | CB13: =SUMIF(Cliente!$H:$H,Rede!$F13,Cliente!$BO:$BO) -> 0 | CC13: =SUMIF(Cliente!$H:$H,Rede!$F13,Cliente!$BP:$BP) -> 0 | CD13: =SUMIF(Cliente!$H:$H,Rede!F13,Cliente!$BQ:$BQ) -> 160.792 | CE13: =SUMIF(Cliente!$H:$H,Rede!F13,Cliente!$BR:$BR) -> 186.167 | CF13: =SUMIF(Cliente!$H:$H,Rede!$F13,Cliente!$BS:$BS) -> 0 | CG13: =SUMIF(Cliente!$H:$H,Rede!$F13,Cliente!$BT:$BT) -> 0 | CH13: =SUMIF(Cliente!$H:$H,Rede!$F13,Cliente!$BU:$BU) -> 67.833 | CI13: =SUMIF(Cliente!$H:$H,Rede!$F13,Cliente!$BV:$BV) -> 149.625 | CJ13: =SUMIF(Cliente!$H:$H,Rede!$F13,Cliente!$BW:$BW) -> 0 | CK13: =SUMIF(Cliente!$H:$H,Rede!$F13,Cliente!$BX:$BX) -> 0 | CM13: =G13+AB13+AW13+BR13 -> 1770.5 | CN13: =H13+AC13+AX13+BS13 -> 1866.2165 | CO13: =I13+AD13+AY13+BT13 -> 1812.022 | CP13: =J13+AE13+AZ13+BU13 -> 16 | CQ13: =K13+AF13+BA13+BV13 -> 0 | CR13: =IFERROR(((CO13+CQ13+CP13)/CN13),0) -> 0.97953372 | CS13: =IFERROR(((CO13+CP13+CQ13)/CM13-1),0) -> 0.032489127 | CT13: =CN13-CO13-CP13-CQ13 -> 38.194503
C14: FLP-SUL MC/KA D | D14: 3919 | E14: MC-TBCR D | F14: REDE ABIMAR | G14: =O14+S14+W14 -> 1055.126 | H14: =_xlfn.XLOOKUP($F14,Metas!$B:$B,Metas!Q:Q,0,0,1) -> 632.71 | I14: =P14+T14+X14 -> 1616.022 | J14: =Q14+U14+Y14 -> 15.75 | K14: =R14+V14+Z14 -> 0 | L14: =IFERROR(((I14+K14+J14)/H14),0) -> 2.5790204 | M14: =IFERROR(((I14+J14+K14)/G14-1),0) -> 0.54651861 | N14: =H14-I14-J14-K14 -> -999.062 | O14: =SUMIF(Cliente!$H:$H,Rede!F14,Cliente!$N:$N) -> 118.792 | P14: =SUMIF(Cliente!$H:$H,Rede!$F14,Cliente!$O:$O) -> 182.938 | Q14: =SUMIF(Cliente!$H:$H,Rede!$F14,Cliente!$P:$P) -> 1.75 | R14: =SUMIF(Cliente!$H:$H,Rede!$F14,Cliente!$Q:$Q) -> 0 | S14: =SUMIF(Cliente!$H:$H,Rede!$F14,Cliente!$R:$R) -> 22.167 | T14: =SUMIF(Cliente!$H:$H,Rede!$F14,Cliente!$S:$S) -> 684.042 | U14: =SUMIF(Cliente!$H:$H,Rede!$F14,Cliente!$T:$T) -> 11 | V14: =SUMIF(Cliente!$H:$H,Rede!$F14,Cliente!$U:$U) -> 0 | W14: =SUMIF(Cliente!$H:$H,Rede!$F14,Cliente!$V:$V) -> 914.167 | X14: =SUMIF(Cliente!$H:$H,Rede!$F14,Cliente!$W:$W) -> 749.042 | Y14: =SUMIF(Cliente!$H:$H,Rede!$F14,Cliente!$X:$X) -> 3 | Z14: =SUMIF(Cliente!$H:$H,Rede!$F14,Cliente!$Y:$Y) -> 0 | AB14: =AJ14+AN14+AR14 -> 679.333 | AC14: =_xlfn.XLOOKUP(F14,Metas!B:B,Metas!R:R,0,0,1) -> 542.31898 | AD14: =AK14+AO14+AS14 -> 927.208 | AE14: =AL14+AP14+AT14 -> 20.75 | AF14: =AM14+AQ14+AU14 -> 0 | AG14: =IFERROR(((AD14+AE14+AF14)/AC14),0) -> 1.7479713 | AH14: =IFERROR(((AD14+AE14+AF14)/AB14-1),0) -> 0.39542463 | AI14: =AC14-AD14-AE14-AF14 -> -405.63902 | AJ14: =SUMIF(Cliente!$H:$H,Rede!$F14,Cliente!$AE:$AE) -> 102.583 | AK14: =SUMIF(Cliente!$H:$H,Rede!$F14,Cliente!$AF:$AF) -> 98 | AL14: =SUMIF(Cliente!$H:$H,Rede!$F14,Cliente!$AG:$AG) -> 1 | AM14: =SUMIF(Cliente!$H:$H,Rede!$F14,Cliente!$AH:$AH) -> 0 | AN14: =SUMIF(Cliente!$H:$H,Rede!$F14,Cliente!$AI:$AI) -> 127 | AO14: =SUMIF(Cliente!$H:$H,Rede!$F14,Cliente!$AJ:$AJ) -> 237 | AP14: =SUMIF(Cliente!$H:$H,Rede!$F14,Cliente!$AK:$AK) -> 3 | AQ14: =SUMIF(Cliente!$H:$H,Rede!$F14,Cliente!$AL:$AL) -> 0 | AR14: =SUMIF(Cliente!$H:$H,Rede!$F14,Cliente!$AM:$AM) -> 449.75 | AS14: =SUMIF(Cliente!$H:$H,Rede!$F14,Cliente!$AN:$AN) -> 592.208 | AT14: =SUMIF(Cliente!$H:$H,Rede!$F14,Cliente!$AO:$AO) -> 16.75 | AU14: =SUMIF(Cliente!$H:$H,Rede!$F14,Cliente!$AP:$AP) -> 0 | AW14: =BE14+BI14+BM14 -> 258.663 | AX14: =_xlfn.XLOOKUP(Rede!F14,Metas!B:B,Metas!S:S,0,0,1) -> 510.06472 | AY14: =BF14+BJ14+BN14 -> 304.041 | AZ14: =BG14+BK14+BO14 -> 35.5 | BA14: =BH14+BL14+BP14 -> 0 | BB14: =IFERROR(((AY14+AZ14+BA14)/AX14),0) -> 0.6656822 | BC14: =IFERROR(((AY14+AZ14+BA14)/AW14-1),0) -> 0.31267711 | BD14: =AX14-AY14-AZ14-BA14 -> 170.52372 | BE14: =SUMIF(Cliente!$H:$H,Rede!F14,Cliente!$AV:$AV) -> -2.858 | BF14: =SUMIF(Cliente!$H:$H,Rede!F14,Cliente!$AW:$AW) -> 5.625 | BG14: =SUMIF(Cliente!$H:$H,Rede!$F14,Cliente!$AX:$AX) -> 1.5 | BH14: =SUMIF(Cliente!$H:$H,Rede!$F14,Cliente!$AY:$AY) -> 0 | BI14: =SUMIF(Cliente!$H:$H,Rede!F14,Cliente!$AZ:$AZ) -> 67.667 | BJ14: =SUMIF(Cliente!$H:$H,Rede!F14,Cliente!$BA:$BA) -> 56.833 | BK14: =SUMIF(Cliente!$H:$H,Rede!$F14,Cliente!$BB:$BB) -> 2 | BL14: =SUMIF(Cliente!$H:$H,Rede!$F14,Cliente!$BC:$BC) -> 0 | BM14: =SUMIF(Cliente!$H:$H,Rede!F14,Cliente!$BD:$BD) -> 193.854 | BN14: =SUMIF(Cliente!$H:$H,Rede!F14,Cliente!$BE:$BE) -> 241.583 | BO14: =SUMIF(Cliente!$H:$H,Rede!$F14,Cliente!$BF:$BF) -> 32 | BP14: =SUMIF(Cliente!$H:$H,Rede!$F14,Cliente!$BG:$BG) -> 0 | BR14: =BZ14+CD14+CH14 -> 56.875 | BS14: =_xlfn.XLOOKUP(Rede!F14,Metas!B:B,Metas!T:T,0,0,1) -> 543 | BT14: =CA14+CE14+CI14 -> 549 | BU14: =CC14+CG14+CK14 -> 0 | BV14: =CB14+CF14+CJ14 -> 31.083 | BW14: =IFERROR(((BT14+BV14+BU14)/BS14),0) -> 1.0682928 | BX14: =IFERROR(((BT14+BU14+BV14)/BR14-1),0) -> 9.1992615 | BY14: =BS14-BT14-BU14-BV14 -> -37.083 | BZ14: =SUMIF(Cliente!$H:$H,Rede!F14,Cliente!$BM:$BM) -> 0.542 | CA14: =SUMIF(Cliente!$H:$H,Rede!F14,Cliente!$BN:$BN) -> 44.917 | CB14: =SUMIF(Cliente!$H:$H,Rede!$F14,Cliente!$BO:$BO) -> 4.083 | CC14: =SUMIF(Cliente!$H:$H,Rede!$F14,Cliente!$BP:$BP) -> 0 | CD14: =SUMIF(Cliente!$H:$H,Rede!F14,Cliente!$BQ:$BQ) -> 56.333 | CE14: =SUMIF(Cliente!$H:$H,Rede!F14,Cliente!$BR:$BR) -> 193.25 | CF14: =SUMIF(Cliente!$H:$H,Rede!$F14,Cliente!$BS:$BS) -> 18 | CG14: =SUMIF(Cliente!$H:$H,Rede!$F14,Cliente!$BT:$BT) -> 0 | CH14: =SUMIF(Cliente!$H:$H,Rede!$F14,Cliente!$BU:$BU) -> 0 | CI14: =SUMIF(Cliente!$H:$H,Rede!$F14,Cliente!$BV:$BV) -> 310.833 | CJ14: =SUMIF(Cliente!$H:$H,Rede!$F14,Cliente!$BW:$BW) -> 9 | CK14: =SUMIF(Cliente!$H:$H,Rede!$F14,Cliente!$BX:$BX) -> 0 | CM14: =G14+AB14+AW14+BR14 -> 2049.997 | CN14: =H14+AC14+AX14+BS14 -> 2228.0937 | CO14: =I14+AD14+AY14+BT14 -> 3396.271 | CP14: =J14+AE14+AZ14+BU14 -> 72 | CQ14: =K14+AF14+BA14+BV14 -> 31.083 | CR14: =IFERROR(((CO14+CQ14+CP14)/CN14),0) -> 1.5705596 | CS14: =IFERROR(((CO14+CP14+CQ14)/CM14-1),0) -> 0.70700445 | CT14: =CN14-CO14-CP14-CQ14 -> -1271.2603
C15: FLP-SUL MC/KA D | D15: 3956 | E15: MC-IMB D | F15: REDE SM SILVEIRA | G15: =O15+S15+W15 -> 902.167 | H15: =_xlfn.XLOOKUP($F15,Metas!$B:$B,Metas!Q:Q,0,0,1) -> 684.6 | I15: =P15+T15+X15 -> 1216.569 | J15: =Q15+U15+Y15 -> 0 | K15: =R15+V15+Z15 -> 0 | L15: =IFERROR(((I15+K15+J15)/H15),0) -> 1.7770508 | M15: =IFERROR(((I15+J15+K15)/G15-1),0) -> 0.34849645 | N15: =H15-I15-J15-K15 -> -531.969 | O15: =SUMIF(Cliente!$H:$H,Rede!F15,Cliente!$N:$N) -> 44.625 | P15: =SUMIF(Cliente!$H:$H,Rede!$F15,Cliente!$O:$O) -> 70.833 | Q15: =SUMIF(Cliente!$H:$H,Rede!$F15,Cliente!$P:$P) -> 0 | R15: =SUMIF(Cliente!$H:$H,Rede!$F15,Cliente!$Q:$Q) -> 0 | S15: =SUMIF(Cliente!$H:$H,Rede!$F15,Cliente!$R:$R) -> 854.875 | T15: =SUMIF(Cliente!$H:$H,Rede!$F15,Cliente!$S:$S) -> 10.5 | U15: =SUMIF(Cliente!$H:$H,Rede!$F15,Cliente!$T:$T) -> 0 | V15: =SUMIF(Cliente!$H:$H,Rede!$F15,Cliente!$U:$U) -> 0 | W15: =SUMIF(Cliente!$H:$H,Rede!$F15,Cliente!$V:$V) -> 2.667 | X15: =SUMIF(Cliente!$H:$H,Rede!$F15,Cliente!$W:$W) -> 1135.236 | Y15: =SUMIF(Cliente!$H:$H,Rede!$F15,Cliente!$X:$X) -> 0 | Z15: =SUMIF(Cliente!$H:$H,Rede!$F15,Cliente!$Y:$Y) -> 0 | AB15: =AJ15+AN15+AR15 -> 468.896 | AC15: =_xlfn.XLOOKUP(F15,Metas!B:B,Metas!R:R,0,0,1) -> 586.80029 | AD15: =AK15+AO15+AS15 -> 259.119 | AE15: =AL15+AP15+AT15 -> 3.5 | AF15: =AM15+AQ15+AU15 -> 0 | AG15: =IFERROR(((AD15+AE15+AF15)/AC15),0) -> 0.44754409 | AH15: =IFERROR(((AD15+AE15+AF15)/AB15-1),0) -> -0.43992058 | AI15: =AC15-AD15-AE15-AF15 -> 324.18129 | AJ15: =SUMIF(Cliente!$H:$H,Rede!$F15,Cliente!$AE:$AE) -> 259.313 | AK15: =SUMIF(Cliente!$H:$H,Rede!$F15,Cliente!$AF:$AF) -> 22.167 | AL15: =SUMIF(Cliente!$H:$H,Rede!$F15,Cliente!$AG:$AG) -> 3.5 | AM15: =SUMIF(Cliente!$H:$H,Rede!$F15,Cliente!$AH:$AH) -> 0 | AN15: =SUMIF(Cliente!$H:$H,Rede!$F15,Cliente!$AI:$AI) -> 15 | AO15: =SUMIF(Cliente!$H:$H,Rede!$F15,Cliente!$AJ:$AJ) -> 42.285 | AP15: =SUMIF(Cliente!$H:$H,Rede!$F15,Cliente!$AK:$AK) -> 0 | AQ15: =SUMIF(Cliente!$H:$H,Rede!$F15,Cliente!$AL:$AL) -> 0 | AR15: =SUMIF(Cliente!$H:$H,Rede!$F15,Cliente!$AM:$AM) -> 194.583 | AS15: =SUMIF(Cliente!$H:$H,Rede!$F15,Cliente!$AN:$AN) -> 194.667 | AT15: =SUMIF(Cliente!$H:$H,Rede!$F15,Cliente!$AO:$AO) -> 0 | AU15: =SUMIF(Cliente!$H:$H,Rede!$F15,Cliente!$AP:$AP) -> 0 | AW15: =BE15+BI15+BM15 -> 660.291 | AX15: =_xlfn.XLOOKUP(Rede!F15,Metas!B:B,Metas!S:S,0,0,1) -> 551.90051 | AY15: =BF15+BJ15+BN15 -> 399.251 | AZ15: =BG15+BK15+BO15 -> 6.583 | BA15: =BH15+BL15+BP15 -> 0 | BB15: =IFERROR(((AY15+AZ15+BA15)/AX15),0) -> 0.73533905 | BC15: =IFERROR(((AY15+AZ15+BA15)/AW15-1),0) -> -0.385371 | BD15: =AX15-AY15-AZ15-BA15 -> 146.06651 | BE15: =SUMIF(Cliente!$H:$H,Rede!F15,Cliente!$AV:$AV) -> 281.667 | BF15: =SUMIF(Cliente!$H:$H,Rede!F15,Cliente!$AW:$AW) -> 183.667 | BG15: =SUMIF(Cliente!$H:$H,Rede!$F15,Cliente!$AX:$AX) -> 5 | BH15: =SUMIF(Cliente!$H:$H,Rede!$F15,Cliente!$AY:$AY) -> 0 | BI15: =SUMIF(Cliente!$H:$H,Rede!F15,Cliente!$AZ:$AZ) -> 202.666 | BJ15: =SUMIF(Cliente!$H:$H,Rede!F15,Cliente!$BA:$BA) -> 37.334 | BK15: =SUMIF(Cliente!$H:$H,Rede!$F15,Cliente!$BB:$BB) -> 0 | BL15: =SUMIF(Cliente!$H:$H,Rede!$F15,Cliente!$BC:$BC) -> 0 | BM15: =SUMIF(Cliente!$H:$H,Rede!F15,Cliente!$BD:$BD) -> 175.958 | BN15: =SUMIF(Cliente!$H:$H,Rede!F15,Cliente!$BE:$BE) -> 178.25 | BO15: =SUMIF(Cliente!$H:$H,Rede!$F15,Cliente!$BF:$BF) -> 1.583 | BP15: =SUMIF(Cliente!$H:$H,Rede!$F15,Cliente!$BG:$BG) -> 0 | BR15: =BZ15+CD15+CH15 -> 181.833 | BS15: =_xlfn.XLOOKUP(Rede!F15,Metas!B:B,Metas!T:T,0,0,1) -> 588 | BT15: =CA15+CE15+CI15 -> 202.083 | BU15: =CC15+CG15+CK15 -> 0 | BV15: =CB15+CF15+CJ15 -> 4.75 | BW15: =IFERROR(((BT15+BV15+BU15)/BS15),0) -> 0.3517568 | BX15: =IFERROR(((BT15+BU15+BV15)/BR15-1),0) -> 0.13748879 | BY15: =BS15-BT15-BU15-BV15 -> 381.167 | BZ15: =SUMIF(Cliente!$H:$H,Rede!F15,Cliente!$BM:$BM) -> 50.791 | CA15: =SUMIF(Cliente!$H:$H,Rede!F15,Cliente!$BN:$BN) -> 102.458 | CB15: =SUMIF(Cliente!$H:$H,Rede!$F15,Cliente!$BO:$BO) -> 0 | CC15: =SUMIF(Cliente!$H:$H,Rede!$F15,Cliente!$BP:$BP) -> 0 | CD15: =SUMIF(Cliente!$H:$H,Rede!F15,Cliente!$BQ:$BQ) -> 73.334 | CE15: =SUMIF(Cliente!$H:$H,Rede!F15,Cliente!$BR:$BR) -> 50.167 | CF15: =SUMIF(Cliente!$H:$H,Rede!$F15,Cliente!$BS:$BS) -> 0 | CG15: =SUMIF(Cliente!$H:$H,Rede!$F15,Cliente!$BT:$BT) -> 0 | CH15: =SUMIF(Cliente!$H:$H,Rede!$F15,Cliente!$BU:$BU) -> 57.708 | CI15: =SUMIF(Cliente!$H:$H,Rede!$F15,Cliente!$BV:$BV) -> 49.458 | CJ15: =SUMIF(Cliente!$H:$H,Rede!$F15,Cliente!$BW:$BW) -> 4.75 | CK15: =SUMIF(Cliente!$H:$H,Rede!$F15,Cliente!$BX:$BX) -> 0 | CM15: =G15+AB15+AW15+BR15 -> 2213.187 | CN15: =H15+AC15+AX15+BS15 -> 2411.3008 | CO15: =I15+AD15+AY15+BT15 -> 2077.022 | CP15: =J15+AE15+AZ15+BU15 -> 10.083 | CQ15: =K15+AF15+BA15+BV15 -> 4.75 | CR15: =IFERROR(((CO15+CQ15+CP15)/CN15),0) -> 0.86752138 | CS15: =IFERROR(((CO15+CP15+CQ15)/CM15-1),0) -> -0.054822299 | CT15: =CN15-CO15-CP15-CQ15 -> 319.4458
C16: FLP-SUL MC/KA D | D16: 4054 | E16: MC-ARA D | F16: REDE COOPER AGRO | G16: =O16+S16+W16 -> 620.375 | H16: =_xlfn.XLOOKUP($F16,Metas!$B:$B,Metas!Q:Q,0,0,1) -> 419.34 | I16: =P16+T16+X16 -> 616 | J16: =Q16+U16+Y16 -> 1 | K16: =R16+V16+Z16 -> 0 | L16: =IFERROR(((I16+K16+J16)/H16),0) -> 1.4713598 | M16: =IFERROR(((I16+J16+K16)/G16-1),0) -> -0.0054402579 | N16: =H16-I16-J16-K16 -> -197.66 | O16: =SUMIF(Cliente!$H:$H,Rede!F16,Cliente!$N:$N) -> 73.958 | P16: =SUMIF(Cliente!$H:$H,Rede!$F16,Cliente!$O:$O) -> 105.5 | Q16: =SUMIF(Cliente!$H:$H,Rede!$F16,Cliente!$P:$P) -> 1 | R16: =SUMIF(Cliente!$H:$H,Rede!$F16,Cliente!$Q:$Q) -> 0 | S16: =SUMIF(Cliente!$H:$H,Rede!$F16,Cliente!$R:$R) -> 2 | T16: =SUMIF(Cliente!$H:$H,Rede!$F16,Cliente!$S:$S) -> 70.5 | U16: =SUMIF(Cliente!$H:$H,Rede!$F16,Cliente!$T:$T) -> 0 | V16: =SUMIF(Cliente!$H:$H,Rede!$F16,Cliente!$U:$U) -> 0 | W16: =SUMIF(Cliente!$H:$H,Rede!$F16,Cliente!$V:$V) -> 544.417 | X16: =SUMIF(Cliente!$H:$H,Rede!$F16,Cliente!$W:$W) -> 440 | Y16: =SUMIF(Cliente!$H:$H,Rede!$F16,Cliente!$X:$X) -> 0 | Z16: =SUMIF(Cliente!$H:$H,Rede!$F16,Cliente!$Y:$Y) -> 0 | AB16: =AJ16+AN16+AR16 -> 127.458 | AC16: =_xlfn.XLOOKUP(F16,Metas!B:B,Metas!R:R,0,0,1) -> 359.43158 | AD16: =AK16+AO16+AS16 -> 651.166 | AE16: =AL16+AP16+AT16 -> 12 | AF16: =AM16+AQ16+AU16 -> 0 | AG16: =IFERROR(((AD16+AE16+AF16)/AC16),0) -> 1.845041 | AH16: =IFERROR(((AD16+AE16+AF16)/AB16-1),0) -> 4.2030159 | AI16: =AC16-AD16-AE16-AF16 -> -303.73442 | AJ16: =SUMIF(Cliente!$H:$H,Rede!$F16,Cliente!$AE:$AE) -> 6.333 | AK16: =SUMIF(Cliente!$H:$H,Rede!$F16,Cliente!$AF:$AF) -> 87.333 | AL16: =SUMIF(Cliente!$H:$H,Rede!$F16,Cliente!$AG:$AG) -> 0 | AM16: =SUMIF(Cliente!$H:$H,Rede!$F16,Cliente!$AH:$AH) -> 0 | AN16: =SUMIF(Cliente!$H:$H,Rede!$F16,Cliente!$AI:$AI) -> 109.5 | AO16: =SUMIF(Cliente!$H:$H,Rede!$F16,Cliente!$AJ:$AJ) -> 86.833 | AP16: =SUMIF(Cliente!$H:$H,Rede!$F16,Cliente!$AK:$AK) -> 0 | AQ16: =SUMIF(Cliente!$H:$H,Rede!$F16,Cliente!$AL:$AL) -> 0 | AR16: =SUMIF(Cliente!$H:$H,Rede!$F16,Cliente!$AM:$AM) -> 11.625 | AS16: =SUMIF(Cliente!$H:$H,Rede!$F16,Cliente!$AN:$AN) -> 477 | AT16: =SUMIF(Cliente!$H:$H,Rede!$F16,Cliente!$AO:$AO) -> 12 | AU16: =SUMIF(Cliente!$H:$H,Rede!$F16,Cliente!$AP:$AP) -> 0 | AW16: =BE16+BI16+BM16 -> 327.896 | AX16: =_xlfn.XLOOKUP(Rede!F16,Metas!B:B,Metas!S:S,0,0,1) -> 338.0545 | AY16: =BF16+BJ16+BN16 -> 846 | AZ16: =BG16+BK16+BO16 -> 53 | BA16: =BH16+BL16+BP16 -> 0 | BB16: =IFERROR(((AY16+AZ16+BA16)/AX16),0) -> 2.6593345 | BC16: =IFERROR(((AY16+AZ16+BA16)/AW16-1),0) -> 1.741723 | BD16: =AX16-AY16-AZ16-BA16 -> -560.9455 | BE16: =SUMIF(Cliente!$H:$H,Rede!F16,Cliente!$AV:$AV) -> 161.925 | BF16: =SUMIF(Cliente!$H:$H,Rede!F16,Cliente!$AW:$AW) -> 75 | BG16: =SUMIF(Cliente!$H:$H,Rede!$F16,Cliente!$AX:$AX) -> 0 | BH16: =SUMIF(Cliente!$H:$H,Rede!$F16,Cliente!$AY:$AY) -> 0 | BI16: =SUMIF(Cliente!$H:$H,Rede!F16,Cliente!$AZ:$AZ) -> 47.275 | BJ16: =SUMIF(Cliente!$H:$H,Rede!F16,Cliente!$BA:$BA) -> 106 | BK16: =SUMIF(Cliente!$H:$H,Rede!$F16,Cliente!$BB:$BB) -> 0 | BL16: =SUMIF(Cliente!$H:$H,Rede!$F16,Cliente!$BC:$BC) -> 0 | BM16: =SUMIF(Cliente!$H:$H,Rede!F16,Cliente!$BD:$BD) -> 118.696 | BN16: =SUMIF(Cliente!$H:$H,Rede!F16,Cliente!$BE:$BE) -> 665 | BO16: =SUMIF(Cliente!$H:$H,Rede!$F16,Cliente!$BF:$BF) -> 53 | BP16: =SUMIF(Cliente!$H:$H,Rede!$F16,Cliente!$BG:$BG) -> 0 | BR16: =BZ16+CD16+CH16 -> 318.5 | BS16: =_xlfn.XLOOKUP(Rede!F16,Metas!B:B,Metas!T:T,0,0,1) -> 360 | BT16: =CA16+CE16+CI16 -> 349.458 | BU16: =CC16+CG16+CK16 -> 0 | BV16: =CB16+CF16+CJ16 -> 0 | BW16: =IFERROR(((BT16+BV16+BU16)/BS16),0) -> 0.97071667 | BX16: =IFERROR(((BT16+BU16+BV16)/BR16-1),0) -> 0.097199372 | BY16: =BS16-BT16-BU16-BV16 -> 10.542 | BZ16: =SUMIF(Cliente!$H:$H,Rede!F16,Cliente!$BM:$BM) -> 34 | CA16: =SUMIF(Cliente!$H:$H,Rede!F16,Cliente!$BN:$BN) -> 5.458 | CB16: =SUMIF(Cliente!$H:$H,Rede!$F16,Cliente!$BO:$BO) -> 0 | CC16: =SUMIF(Cliente!$H:$H,Rede!$F16,Cliente!$BP:$BP) -> 0 | CD16: =SUMIF(Cliente!$H:$H,Rede!F16,Cliente!$BQ:$BQ) -> 101 | CE16: =SUMIF(Cliente!$H:$H,Rede!F16,Cliente!$BR:$BR) -> 66 | CF16: =SUMIF(Cliente!$H:$H,Rede!$F16,Cliente!$BS:$BS) -> 0 | CG16: =SUMIF(Cliente!$H:$H,Rede!$F16,Cliente!$BT:$BT) -> 0 | CH16: =SUMIF(Cliente!$H:$H,Rede!$F16,Cliente!$BU:$BU) -> 183.5 | CI16: =SUMIF(Cliente!$H:$H,Rede!$F16,Cliente!$BV:$BV) -> 278 | CJ16: =SUMIF(Cliente!$H:$H,Rede!$F16,Cliente!$BW:$BW) -> 0 | CK16: =SUMIF(Cliente!$H:$H,Rede!$F16,Cliente!$BX:$BX) -> 0 | CM16: =G16+AB16+AW16+BR16 -> 1394.229 | CN16: =H16+AC16+AX16+BS16 -> 1476.8261 | CO16: =I16+AD16+AY16+BT16 -> 2462.624 | CP16: =J16+AE16+AZ16+BU16 -> 66 | CQ16: =K16+AF16+BA16+BV16 -> 0 | CR16: =IFERROR(((CO16+CQ16+CP16)/CN16),0) -> 1.7122016 | CS16: =IFERROR(((CO16+CP16+CQ16)/CM16-1),0) -> 0.81363607 | CT16: =CN16-CO16-CP16-CQ16 -> -1051.7979
C17: FLP-SUL MC/KA D | D17: 4054 | E17: MC-ARA D | F17: REDE FEGOAGRO | G17: =O17+S17+W17 -> 630.75 | H17: =_xlfn.XLOOKUP($F17,Metas!$B:$B,Metas!Q:Q,0,0,1) -> 325.91 | I17: =P17+T17+X17 -> 173.375 | J17: =Q17+U17+Y17 -> 0 | K17: =R17+V17+Z17 -> 0 | L17: =IFERROR(((I17+K17+J17)/H17),0) -> 0.53197202 | M17: =IFERROR(((I17+J17+K17)/G17-1),0) -> -0.72512881 | N17: =H17-I17-J17-K17 -> 152.535 | O17: =SUMIF(Cliente!$H:$H,Rede!F17,Cliente!$N:$N) -> 68 | P17: =SUMIF(Cliente!$H:$H,Rede!$F17,Cliente!$O:$O) -> 28 | Q17: =SUMIF(Cliente!$H:$H,Rede!$F17,Cliente!$P:$P) -> 0 | R17: =SUMIF(Cliente!$H:$H,Rede!$F17,Cliente!$Q:$Q) -> 0 | S17: =SUMIF(Cliente!$H:$H,Rede!$F17,Cliente!$R:$R) -> 512.625 | T17: =SUMIF(Cliente!$H:$H,Rede!$F17,Cliente!$S:$S) -> 131 | U17: =SUMIF(Cliente!$H:$H,Rede!$F17,Cliente!$T:$T) -> 0 | V17: =SUMIF(Cliente!$H:$H,Rede!$F17,Cliente!$U:$U) -> 0 | W17: =SUMIF(Cliente!$H:$H,Rede!$F17,Cliente!$V:$V) -> 50.125 | X17: =SUMIF(Cliente!$H:$H,Rede!$F17,Cliente!$W:$W) -> 14.375 | Y17: =SUMIF(Cliente!$H:$H,Rede!$F17,Cliente!$X:$X) -> 0 | Z17: =SUMIF(Cliente!$H:$H,Rede!$F17,Cliente!$Y:$Y) -> 0 | AB17: =AJ17+AN17+AR17 -> 180.069 | AC17: =_xlfn.XLOOKUP(F17,Metas!B:B,Metas!R:R,0,0,1) -> 279.3528 | AD17: =AK17+AO17+AS17 -> 132.167 | AE17: =AL17+AP17+AT17 -> 15.5 | AF17: =AM17+AQ17+AU17 -> 0 | AG17: =IFERROR(((AD17+AE17+AF17)/AC17),0) -> 0.52860397 | AH17: =IFERROR(((AD17+AE17+AF17)/AB17-1),0) -> -0.17994213 | AI17: =AC17-AD17-AE17-AF17 -> 131.6858 | AJ17: =SUMIF(Cliente!$H:$H,Rede!$F17,Cliente!$AE:$AE) -> 34 | AK17: =SUMIF(Cliente!$H:$H,Rede!$F17,Cliente!$AF:$AF) -> 31.25 | AL17: =SUMIF(Cliente!$H:$H,Rede!$F17,Cliente!$AG:$AG) -> 0 | AM17: =SUMIF(Cliente!$H:$H,Rede!$F17,Cliente!$AH:$AH) -> 0 | AN17: =SUMIF(Cliente!$H:$H,Rede!$F17,Cliente!$AI:$AI) -> 27.583 | AO17: =SUMIF(Cliente!$H:$H,Rede!$F17,Cliente!$AJ:$AJ) -> 34.917 | AP17: =SUMIF(Cliente!$H:$H,Rede!$F17,Cliente!$AK:$AK) -> 3.25 | AQ17: =SUMIF(Cliente!$H:$H,Rede!$F17,Cliente!$AL:$AL) -> 0 | AR17: =SUMIF(Cliente!$H:$H,Rede!$F17,Cliente!$AM:$AM) -> 118.486 | AS17: =SUMIF(Cliente!$H:$H,Rede!$F17,Cliente!$AN:$AN) -> 66 | AT17: =SUMIF(Cliente!$H:$H,Rede!$F17,Cliente!$AO:$AO) -> 12.25 | AU17: =SUMIF(Cliente!$H:$H,Rede!$F17,Cliente!$AP:$AP) -> 0 | AW17: =BE17+BI17+BM17 -> 162.25 | AX17: =_xlfn.XLOOKUP(Rede!F17,Metas!B:B,Metas!S:S,0,0,1) -> 262.73837 | AY17: =BF17+BJ17+BN17 -> 136.5 | AZ17: =BG17+BK17+BO17 -> 4.125 | BA17: =BH17+BL17+BP17 -> 0 | BB17: =IFERROR(((AY17+AZ17+BA17)/AX17),0) -> 0.53522825 | BC17: =IFERROR(((AY17+AZ17+BA17)/AW17-1),0) -> -0.13328197 | BD17: =AX17-AY17-AZ17-BA17 -> 122.11337 | BE17: =SUMIF(Cliente!$H:$H,Rede!F17,Cliente!$AV:$AV) -> 37.5 | BF17: =SUMIF(Cliente!$H:$H,Rede!F17,Cliente!$AW:$AW) -> 87.5 | BG17: =SUMIF(Cliente!$H:$H,Rede!$F17,Cliente!$AX:$AX) -> 0 | BH17: =SUMIF(Cliente!$H:$H,Rede!$F17,Cliente!$AY:$AY) -> 0 | BI17: =SUMIF(Cliente!$H:$H,Rede!F17,Cliente!$AZ:$AZ) -> 21 | BJ17: =SUMIF(Cliente!$H:$H,Rede!F17,Cliente!$BA:$BA) -> 0 | BK17: =SUMIF(Cliente!$H:$H,Rede!$F17,Cliente!$BB:$BB) -> 0 | BL17: =SUMIF(Cliente!$H:$H,Rede!$F17,Cliente!$BC:$BC) -> 0 | BM17: =SUMIF(Cliente!$H:$H,Rede!F17,Cliente!$BD:$BD) -> 103.75 | BN17: =SUMIF(Cliente!$H:$H,Rede!F17,Cliente!$BE:$BE) -> 49 | BO17: =SUMIF(Cliente!$H:$H,Rede!$F17,Cliente!$BF:$BF) -> 4.125 | BP17: =SUMIF(Cliente!$H:$H,Rede!$F17,Cliente!$BG:$BG) -> 0 | BR17: =BZ17+CD17+CH17 -> 88.333 | BS17: =_xlfn.XLOOKUP(Rede!F17,Metas!B:B,Metas!T:T,0,0,1) -> 282 | BT17: =CA17+CE17+CI17 -> 212.542 | BU17: =CC17+CG17+CK17 -> 0 | BV17: =CB17+CF17+CJ17 -> 0 | BW17: =IFERROR(((BT17+BV17+BU17)/BS17),0) -> 0.75369504 | BX17: =IFERROR(((BT17+BU17+BV17)/BR17-1),0) -> 1.4061449 | BY17: =BS17-BT17-BU17-BV17 -> 69.458 | BZ17: =SUMIF(Cliente!$H:$H,Rede!F17,Cliente!$BM:$BM) -> 43.333 | CA17: =SUMIF(Cliente!$H:$H,Rede!F17,Cliente!$BN:$BN) -> 33 | CB17: =SUMIF(Cliente!$H:$H,Rede!$F17,Cliente!$BO:$BO) -> 0 | CC17: =SUMIF(Cliente!$H:$H,Rede!$F17,Cliente!$BP:$BP) -> 0 | CD17: =SUMIF(Cliente!$H:$H,Rede!F17,Cliente!$BQ:$BQ) -> 23 | CE17: =SUMIF(Cliente!$H:$H,Rede!F17,Cliente!$BR:$BR) -> 139 | CF17: =SUMIF(Cliente!$H:$H,Rede!$F17,Cliente!$BS:$BS) -> 0 | CG17: =SUMIF(Cliente!$H:$H,Rede!$F17,Cliente!$BT:$BT) -> 0 | CH17: =SUMIF(Cliente!$H:$H,Rede!$F17,Cliente!$BU:$BU) -> 22 | CI17: =SUMIF(Cliente!$H:$H,Rede!$F17,Cliente!$BV:$BV) -> 40.542 | CJ17: =SUMIF(Cliente!$H:$H,Rede!$F17,Cliente!$BW:$BW) -> 0 | CK17: =SUMIF(Cliente!$H:$H,Rede!$F17,Cliente!$BX:$BX) -> 0 | CM17: =G17+AB17+AW17+BR17 -> 1061.402 | CN17: =H17+AC17+AX17+BS17 -> 1150.0012 | CO17: =I17+AD17+AY17+BT17 -> 654.584 | CP17: =J17+AE17+AZ17+BU17 -> 19.625 | CQ17: =K17+AF17+BA17+BV17 -> 0 | CR17: =IFERROR(((CO17+CQ17+CP17)/CN17),0) -> 0.5862681 | CS17: =IFERROR(((CO17+CP17+CQ17)/CM17-1),0) -> -0.36479392 | CT17: =CN17-CO17-CP17-CQ17 -> 475.79217
C18: NORTE MC/KA D | D18: 179 | E18: KA-BRQ | F18: REDE ARCHER | G18: =O18+S18+W18 -> 1707.958 | H18: =_xlfn.XLOOKUP($F18,Metas!$B:$B,Metas!Q:Q,0,0,1) -> 2181.26 | I18: =P18+T18+X18 -> 1828 | J18: =Q18+U18+Y18 -> 15 | K18: =R18+V18+Z18 -> 0 | L18: =IFERROR(((I18+K18+J18)/H18),0) -> 0.84492449 | M18: =IFERROR(((I18+J18+K18)/G18-1),0) -> 0.079066347 | N18: =H18-I18-J18-K18 -> 338.26 | O18: =SUMIF(Cliente!$H:$H,Rede!F18,Cliente!$N:$N) -> 504 | P18: =SUMIF(Cliente!$H:$H,Rede!$F18,Cliente!$O:$O) -> 109 | Q18: =SUMIF(Cliente!$H:$H,Rede!$F18,Cliente!$P:$P) -> 0 | R18: =SUMIF(Cliente!$H:$H,Rede!$F18,Cliente!$Q:$Q) -> 0 | S18: =SUMIF(Cliente!$H:$H,Rede!$F18,Cliente!$R:$R) -> 204.958 | T18: =SUMIF(Cliente!$H:$H,Rede!$F18,Cliente!$S:$S) -> 1458 | U18: =SUMIF(Cliente!$H:$H,Rede!$F18,Cliente!$T:$T) -> 15 | V18: =SUMIF(Cliente!$H:$H,Rede!$F18,Cliente!$U:$U) -> 0 | W18: =SUMIF(Cliente!$H:$H,Rede!$F18,Cliente!$V:$V) -> 999 | X18: =SUMIF(Cliente!$H:$H,Rede!$F18,Cliente!$W:$W) -> 261 | Y18: =SUMIF(Cliente!$H:$H,Rede!$F18,Cliente!$X:$X) -> 0 | Z18: =SUMIF(Cliente!$H:$H,Rede!$F18,Cliente!$Y:$Y) -> 0 | AB18: =AJ18+AN18+AR18 -> 2156 | AC18: =_xlfn.XLOOKUP(F18,Metas!B:B,Metas!R:R,0,0,1) -> 1869.6433 | AD18: =AK18+AO18+AS18 -> 1741.75 | AE18: =AL18+AP18+AT18 -> 3 | AF18: =AM18+AQ18+AU18 -> 0 | AG18: =IFERROR(((AD18+AE18+AF18)/AC18),0) -> 0.9331994 | AH18: =IFERROR(((AD18+AE18+AF18)/AB18-1),0) -> -0.19074675 | AI18: =AC18-AD18-AE18-AF18 -> 124.8933 | AJ18: =SUMIF(Cliente!$H:$H,Rede!$F18,Cliente!$AE:$AE) -> 624 | AK18: =SUMIF(Cliente!$H:$H,Rede!$F18,Cliente!$AF:$AF) -> 548.75 | AL18: =SUMIF(Cliente!$H:$H,Rede!$F18,Cliente!$AG:$AG) -> 0 | AM18: =SUMIF(Cliente!$H:$H,Rede!$F18,Cliente!$AH:$AH) -> 0 | AN18: =SUMIF(Cliente!$H:$H,Rede!$F18,Cliente!$AI:$AI) -> 945 | AO18: =SUMIF(Cliente!$H:$H,Rede!$F18,Cliente!$AJ:$AJ) -> 578 | AP18: =SUMIF(Cliente!$H:$H,Rede!$F18,Cliente!$AK:$AK) -> 3 | AQ18: =SUMIF(Cliente!$H:$H,Rede!$F18,Cliente!$AL:$AL) -> 0 | AR18: =SUMIF(Cliente!$H:$H,Rede!$F18,Cliente!$AM:$AM) -> 587 | AS18: =SUMIF(Cliente!$H:$H,Rede!$F18,Cliente!$AN:$AN) -> 615 | AT18: =SUMIF(Cliente!$H:$H,Rede!$F18,Cliente!$AO:$AO) -> 0 | AU18: =SUMIF(Cliente!$H:$H,Rede!$F18,Cliente!$AP:$AP) -> 0 | AW18: =BE18+BI18+BM18 -> 2145.417 | AX18: =_xlfn.XLOOKUP(Rede!F18,Metas!B:B,Metas!S:S,0,0,1) -> 1758.4468 | AY18: =BF18+BJ18+BN18 -> 1714.875 | AZ18: =BG18+BK18+BO18 -> 25 | BA18: =BH18+BL18+BP18 -> 0 | BB18: =IFERROR(((AY18+AZ18+BA18)/AX18),0) -> 0.98943851 | BC18: =IFERROR(((AY18+AZ18+BA18)/AW18-1),0) -> -0.18902712 | BD18: =AX18-AY18-AZ18-BA18 -> 18.571814 | BE18: =SUMIF(Cliente!$H:$H,Rede!F18,Cliente!$AV:$AV) -> 517 | BF18: =SUMIF(Cliente!$H:$H,Rede!F18,Cliente!$AW:$AW) -> 235.917 | BG18: =SUMIF(Cliente!$H:$H,Rede!$F18,Cliente!$AX:$AX) -> 0 | BH18: =SUMIF(Cliente!$H:$H,Rede!$F18,Cliente!$AY:$AY) -> 0 | BI18: =SUMIF(Cliente!$H:$H,Rede!F18,Cliente!$AZ:$AZ) -> 408 | BJ18: =SUMIF(Cliente!$H:$H,Rede!F18,Cliente!$BA:$BA) -> 790.958 | BK18: =SUMIF(Cliente!$H:$H,Rede!$F18,Cliente!$BB:$BB) -> 12 | BL18: =SUMIF(Cliente!$H:$H,Rede!$F18,Cliente!$BC:$BC) -> 0 | BM18: =SUMIF(Cliente!$H:$H,Rede!F18,Cliente!$BD:$BD) -> 1220.417 | BN18: =SUMIF(Cliente!$H:$H,Rede!F18,Cliente!$BE:$BE) -> 688 | BO18: =SUMIF(Cliente!$H:$H,Rede!$F18,Cliente!$BF:$BF) -> 13 | BP18: =SUMIF(Cliente!$H:$H,Rede!$F18,Cliente!$BG:$BG) -> 0 | BR18: =BZ18+CD18+CH18 -> 1078.25 | BS18: =_xlfn.XLOOKUP(Rede!F18,Metas!B:B,Metas!T:T,0,0,1) -> 1872 | BT18: =CA18+CE18+CI18 -> 1087 | BU18: =CC18+CG18+CK18 -> 59 | BV18: =CB18+CF18+CJ18 -> 18 | BW18: =IFERROR(((BT18+BV18+BU18)/BS18),0) -> 0.62179487 | BX18: =IFERROR(((BT18+BU18+BV18)/BR18-1),0) -> 0.079527011 | BY18: =BS18-BT18-BU18-BV18 -> 708 | BZ18: =SUMIF(Cliente!$H:$H,Rede!F18,Cliente!$BM:$BM) -> 179.25 | CA18: =SUMIF(Cliente!$H:$H,Rede!F18,Cliente!$BN:$BN) -> 365 | CB18: =SUMIF(Cliente!$H:$H,Rede!$F18,Cliente!$BO:$BO) -> 3 | CC18: =SUMIF(Cliente!$H:$H,Rede!$F18,Cliente!$BP:$BP) -> 0 | CD18: =SUMIF(Cliente!$H:$H,Rede!F18,Cliente!$BQ:$BQ) -> 490 | CE18: =SUMIF(Cliente!$H:$H,Rede!F18,Cliente!$BR:$BR) -> 518 | CF18: =SUMIF(Cliente!$H:$H,Rede!$F18,Cliente!$BS:$BS) -> 15 | CG18: =SUMIF(Cliente!$H:$H,Rede!$F18,Cliente!$BT:$BT) -> 0 | CH18: =SUMIF(Cliente!$H:$H,Rede!$F18,Cliente!$BU:$BU) -> 409 | CI18: =SUMIF(Cliente!$H:$H,Rede!$F18,Cliente!$BV:$BV) -> 204 | CJ18: =SUMIF(Cliente!$H:$H,Rede!$F18,Cliente!$BW:$BW) -> 0 | CK18: =SUMIF(Cliente!$H:$H,Rede!$F18,Cliente!$BX:$BX) -> 59 | CM18: =G18+AB18+AW18+BR18 -> 7087.625 | CN18: =H18+AC18+AX18+BS18 -> 7681.3501 | CO18: =I18+AD18+AY18+BT18 -> 6371.625 | CP18: =J18+AE18+AZ18+BU18 -> 102 | CQ18: =K18+AF18+BA18+BV18 -> 18 | CR18: =IFERROR(((CO18+CQ18+CP18)/CN18),0) -> 0.8451151 | CS18: =IFERROR(((CO18+CP18+CQ18)/CM18-1),0) -> -0.084090228 | CT18: =CN18-CO18-CP18-CQ18 -> 1189.7251
C19: NORTE MC/KA D | D19: 359 | E19: MC-ITPE D | F19: REDE UBER | G19: =O19+S19+W19 -> 667.104 | H19: =_xlfn.XLOOKUP($F19,Metas!$B:$B,Metas!Q:Q,0,0,1) -> 482.46 | I19: =P19+T19+X19 -> 350.083 | J19: =Q19+U19+Y19 -> 13.625 | K19: =R19+V19+Z19 -> 0 | L19: =IFERROR(((I19+K19+J19)/H19),0) -> 0.75386146 | M19: =IFERROR(((I19+J19+K19)/G19-1),0) -> -0.45479565 | N19: =H19-I19-J19-K19 -> 118.752 | O19: =SUMIF(Cliente!$H:$H,Rede!F19,Cliente!$N:$N) -> 28 | P19: =SUMIF(Cliente!$H:$H,Rede!$F19,Cliente!$O:$O) -> 20.25 | Q19: =SUMIF(Cliente!$H:$H,Rede!$F19,Cliente!$P:$P) -> 11 | R19: =SUMIF(Cliente!$H:$H,Rede!$F19,Cliente!$Q:$Q) -> 0 | S19: =SUMIF(Cliente!$H:$H,Rede!$F19,Cliente!$R:$R) -> 28.021 | T19: =SUMIF(Cliente!$H:$H,Rede!$F19,Cliente!$S:$S) -> 285 | U19: =SUMIF(Cliente!$H:$H,Rede!$F19,Cliente!$T:$T) -> 2.625 | V19: =SUMIF(Cliente!$H:$H,Rede!$F19,Cliente!$U:$U) -> 0 | W19: =SUMIF(Cliente!$H:$H,Rede!$F19,Cliente!$V:$V) -> 611.083 | X19: =SUMIF(Cliente!$H:$H,Rede!$F19,Cliente!$W:$W) -> 44.833 | Y19: =SUMIF(Cliente!$H:$H,Rede!$F19,Cliente!$X:$X) -> 0 | Z19: =SUMIF(Cliente!$H:$H,Rede!$F19,Cliente!$Y:$Y) -> 0 | AB19: =AJ19+AN19+AR19 -> 310.667 | AC19: =_xlfn.XLOOKUP(F19,Metas!B:B,Metas!R:R,0,0,1) -> 413.54064 | AD19: =AK19+AO19+AS19 -> 132.501 | AE19: =AL19+AP19+AT19 -> 0 | AF19: =AM19+AQ19+AU19 -> 0 | AG19: =IFERROR(((AD19+AE19+AF19)/AC19),0) -> 0.32040624 | AH19: =IFERROR(((AD19+AE19+AF19)/AB19-1),0) -> -0.57349509 | AI19: =AC19-AD19-AE19-AF19 -> 281.03964 | AJ19: =SUMIF(Cliente!$H:$H,Rede!$F19,Cliente!$AE:$AE) -> 249.625 | AK19: =SUMIF(Cliente!$H:$H,Rede!$F19,Cliente!$AF:$AF) -> 9.625 | AL19: =SUMIF(Cliente!$H:$H,Rede!$F19,Cliente!$AG:$AG) -> 0 | AM19: =SUMIF(Cliente!$H:$H,Rede!$F19,Cliente!$AH:$AH) -> 0 | AN19: =SUMIF(Cliente!$H:$H,Rede!$F19,Cliente!$AI:$AI) -> 41.042 | AO19: =SUMIF(Cliente!$H:$H,Rede!$F19,Cliente!$AJ:$AJ) -> 48.542 | AP19: =SUMIF(Cliente!$H:$H,Rede!$F19,Cliente!$AK:$AK) -> 0 | AQ19: =SUMIF(Cliente!$H:$H,Rede!$F19,Cliente!$AL:$AL) -> 0 | AR19: =SUMIF(Cliente!$H:$H,Rede!$F19,Cliente!$AM:$AM) -> 20 | AS19: =SUMIF(Cliente!$H:$H,Rede!$F19,Cliente!$AN:$AN) -> 74.334 | AT19: =SUMIF(Cliente!$H:$H,Rede!$F19,Cliente!$AO:$AO) -> 0 | AU19: =SUMIF(Cliente!$H:$H,Rede!$F19,Cliente!$AP:$AP) -> 0 | AW19: =BE19+BI19+BM19 -> 366.625 | AX19: =_xlfn.XLOOKUP(Rede!F19,Metas!B:B,Metas!S:S,0,0,1) -> 388.94543 | AY19: =BF19+BJ19+BN19 -> 332.499 | AZ19: =BG19+BK19+BO19 -> 11 | BA19: =BH19+BL19+BP19 -> 0 | BB19: =IFERROR(((AY19+AZ19+BA19)/AX19),0) -> 0.88315473 | BC19: =IFERROR(((AY19+AZ19+BA19)/AW19-1),0) -> -0.063078077 | BD19: =AX19-AY19-AZ19-BA19 -> 45.446433 | BE19: =SUMIF(Cliente!$H:$H,Rede!F19,Cliente!$AV:$AV) -> 69 | BF19: =SUMIF(Cliente!$H:$H,Rede!F19,Cliente!$AW:$AW) -> 83.541 | BG19: =SUMIF(Cliente!$H:$H,Rede!$F19,Cliente!$AX:$AX) -> 5 | BH19: =SUMIF(Cliente!$H:$H,Rede!$F19,Cliente!$AY:$AY) -> 0 | BI19: =SUMIF(Cliente!$H:$H,Rede!F19,Cliente!$AZ:$AZ) -> 75.375 | BJ19: =SUMIF(Cliente!$H:$H,Rede!F19,Cliente!$BA:$BA) -> 39.5 | BK19: =SUMIF(Cliente!$H:$H,Rede!$F19,Cliente!$BB:$BB) -> 0 | BL19: =SUMIF(Cliente!$H:$H,Rede!$F19,Cliente!$BC:$BC) -> 0 | BM19: =SUMIF(Cliente!$H:$H,Rede!F19,Cliente!$BD:$BD) -> 222.25 | BN19: =SUMIF(Cliente!$H:$H,Rede!F19,Cliente!$BE:$BE) -> 209.458 | BO19: =SUMIF(Cliente!$H:$H,Rede!$F19,Cliente!$BF:$BF) -> 6 | BP19: =SUMIF(Cliente!$H:$H,Rede!$F19,Cliente!$BG:$BG) -> 0 | BR19: =BZ19+CD19+CH19 -> 236.958 | BS19: =_xlfn.XLOOKUP(Rede!F19,Metas!B:B,Metas!T:T,0,0,1) -> 414 | BT19: =CA19+CE19+CI19 -> 109.917 | BU19: =CC19+CG19+CK19 -> 0 | BV19: =CB19+CF19+CJ19 -> 0 | BW19: =IFERROR(((BT19+BV19+BU19)/BS19),0) -> 0.2655 | BX19: =IFERROR(((BT19+BU19+BV19)/BR19-1),0) -> -0.53613299 | BY19: =BS19-BT19-BU19-BV19 -> 304.083 | BZ19: =SUMIF(Cliente!$H:$H,Rede!F19,Cliente!$BM:$BM) -> 27.958 | CA19: =SUMIF(Cliente!$H:$H,Rede!F19,Cliente!$BN:$BN) -> 54.916 | CB19: =SUMIF(Cliente!$H:$H,Rede!$F19,Cliente!$BO:$BO) -> 0 | CC19: =SUMIF(Cliente!$H:$H,Rede!$F19,Cliente!$BP:$BP) -> 0 | CD19: =SUMIF(Cliente!$H:$H,Rede!F19,Cliente!$BQ:$BQ) -> 6 | CE19: =SUMIF(Cliente!$H:$H,Rede!F19,Cliente!$BR:$BR) -> 22.917 | CF19: =SUMIF(Cliente!$H:$H,Rede!$F19,Cliente!$BS:$BS) -> 0 | CG19: =SUMIF(Cliente!$H:$H,Rede!$F19,Cliente!$BT:$BT) -> 0 | CH19: =SUMIF(Cliente!$H:$H,Rede!$F19,Cliente!$BU:$BU) -> 203 | CI19: =SUMIF(Cliente!$H:$H,Rede!$F19,Cliente!$BV:$BV) -> 32.084 | CJ19: =SUMIF(Cliente!$H:$H,Rede!$F19,Cliente!$BW:$BW) -> 0 | CK19: =SUMIF(Cliente!$H:$H,Rede!$F19,Cliente!$BX:$BX) -> 0 | CM19: =G19+AB19+AW19+BR19 -> 1581.354 | CN19: =H19+AC19+AX19+BS19 -> 1698.9461 | CO19: =I19+AD19+AY19+BT19 -> 925 | CP19: =J19+AE19+AZ19+BU19 -> 24.625 | CQ19: =K19+AF19+BA19+BV19 -> 0 | CR19: =IFERROR(((CO19+CQ19+CP19)/CN19),0) -> 0.55894947 | CS19: =IFERROR(((CO19+CP19+CQ19)/CM19-1),0) -> -0.39948614 | CT19: =CN19-CO19-CP19-CQ19 -> 749.32107
C20: NORTE MC/KA D | D20: 359 | E20: MC-ITPE D | F20: REDE NILO GOEDERT | G20: =O20+S20+W20 -> 1600.075 | H20: =_xlfn.XLOOKUP($F20,Metas!$B:$B,Metas!Q:Q,0,0,1) -> 985.46 | I20: =P20+T20+X20 -> 741.792 | J20: =Q20+U20+Y20 -> 6.625 | K20: =R20+V20+Z20 -> 0 | L20: =IFERROR(((I20+K20+J20)/H20),0) -> 0.75945954 | M20: =IFERROR(((I20+J20+K20)/G20-1),0) -> -0.5322613 | N20: =H20-I20-J20-K20 -> 237.043 | O20: =SUMIF(Cliente!$H:$H,Rede!F20,Cliente!$N:$N) -> 139.908 | P20: =SUMIF(Cliente!$H:$H,Rede!$F20,Cliente!$O:$O) -> 76.792 | Q20: =SUMIF(Cliente!$H:$H,Rede!$F20,Cliente!$P:$P) -> 0.75 | R20: =SUMIF(Cliente!$H:$H,Rede!$F20,Cliente!$Q:$Q) -> 0 | S20: =SUMIF(Cliente!$H:$H,Rede!$F20,Cliente!$R:$R) -> 1105 | T20: =SUMIF(Cliente!$H:$H,Rede!$F20,Cliente!$S:$S) -> 379 | U20: =SUMIF(Cliente!$H:$H,Rede!$F20,Cliente!$T:$T) -> 1.375 | V20: =SUMIF(Cliente!$H:$H,Rede!$F20,Cliente!$U:$U) -> 0 | W20: =SUMIF(Cliente!$H:$H,Rede!$F20,Cliente!$V:$V) -> 355.167 | X20: =SUMIF(Cliente!$H:$H,Rede!$F20,Cliente!$W:$W) -> 286 | Y20: =SUMIF(Cliente!$H:$H,Rede!$F20,Cliente!$X:$X) -> 4.5 | Z20: =SUMIF(Cliente!$H:$H,Rede!$F20,Cliente!$Y:$Y) -> 0 | AB20: =AJ20+AN20+AR20 -> 635 | AC20: =_xlfn.XLOOKUP(F20,Metas!B:B,Metas!R:R,0,0,1) -> 844.67923 | AD20: =AK20+AO20+AS20 -> 403.5 | AE20: =AL20+AP20+AT20 -> 27.333 | AF20: =AM20+AQ20+AU20 -> 0 | AG20: =IFERROR(((AD20+AE20+AF20)/AC20),0) -> 0.51005516 | AH20: =IFERROR(((AD20+AE20+AF20)/AB20-1),0) -> -0.32152283 | AI20: =AC20-AD20-AE20-AF20 -> 413.84623 | AJ20: =SUMIF(Cliente!$H:$H,Rede!$F20,Cliente!$AE:$AE) -> 142 | AK20: =SUMIF(Cliente!$H:$H,Rede!$F20,Cliente!$AF:$AF) -> 69 | AL20: =SUMIF(Cliente!$H:$H,Rede!$F20,Cliente!$AG:$AG) -> 0 | AM20: =SUMIF(Cliente!$H:$H,Rede!$F20,Cliente!$AH:$AH) -> 0 | AN20: =SUMIF(Cliente!$H:$H,Rede!$F20,Cliente!$AI:$AI) -> 493 | AO20: =SUMIF(Cliente!$H:$H,Rede!$F20,Cliente!$AJ:$AJ) -> 107 | AP20: =SUMIF(Cliente!$H:$H,Rede!$F20,Cliente!$AK:$AK) -> 7.333 | AQ20: =SUMIF(Cliente!$H:$H,Rede!$F20,Cliente!$AL:$AL) -> 0 | AR20: =SUMIF(Cliente!$H:$H,Rede!$F20,Cliente!$AM:$AM) -> 0 | AS20: =SUMIF(Cliente!$H:$H,Rede!$F20,Cliente!$AN:$AN) -> 227.5 | AT20: =SUMIF(Cliente!$H:$H,Rede!$F20,Cliente!$AO:$AO) -> 20 | AU20: =SUMIF(Cliente!$H:$H,Rede!$F20,Cliente!$AP:$AP) -> 0 | AW20: =BE20+BI20+BM20 -> 641.583 | AX20: =_xlfn.XLOOKUP(Rede!F20,Metas!B:B,Metas!S:S,0,0,1) -> 794.44218 | AY20: =BF20+BJ20+BN20 -> 433.375 | AZ20: =BG20+BK20+BO20 -> 67 | BA20: =BH20+BL20+BP20 -> 0 | BB20: =IFERROR(((AY20+AZ20+BA20)/AX20),0) -> 0.62984445 | BC20: =IFERROR(((AY20+AZ20+BA20)/AW20-1),0) -> -0.22009311 | BD20: =AX20-AY20-AZ20-BA20 -> 294.06718 | BE20: =SUMIF(Cliente!$H:$H,Rede!F20,Cliente!$AV:$AV) -> 63 | BF20: =SUMIF(Cliente!$H:$H,Rede!F20,Cliente!$AW:$AW) -> 107 | BG20: =SUMIF(Cliente!$H:$H,Rede!$F20,Cliente!$AX:$AX) -> 4 | BH20: =SUMIF(Cliente!$H:$H,Rede!$F20,Cliente!$AY:$AY) -> 0 | BI20: =SUMIF(Cliente!$H:$H,Rede!F20,Cliente!$AZ:$AZ) -> 146 | BJ20: =SUMIF(Cliente!$H:$H,Rede!F20,Cliente!$BA:$BA) -> 83.375 | BK20: =SUMIF(Cliente!$H:$H,Rede!$F20,Cliente!$BB:$BB) -> 25 | BL20: =SUMIF(Cliente!$H:$H,Rede!$F20,Cliente!$BC:$BC) -> 0 | BM20: =SUMIF(Cliente!$H:$H,Rede!F20,Cliente!$BD:$BD) -> 432.583 | BN20: =SUMIF(Cliente!$H:$H,Rede!F20,Cliente!$BE:$BE) -> 243 | BO20: =SUMIF(Cliente!$H:$H,Rede!$F20,Cliente!$BF:$BF) -> 38 | BP20: =SUMIF(Cliente!$H:$H,Rede!$F20,Cliente!$BG:$BG) -> 0 | BR20: =BZ20+CD20+CH20 -> 411.771 | BS20: =_xlfn.XLOOKUP(Rede!F20,Metas!B:B,Metas!T:T,0,0,1) -> 846 | BT20: =CA20+CE20+CI20 -> 555.709 | BU20: =CC20+CG20+CK20 -> 0 | BV20: =CB20+CF20+CJ20 -> 82.542 | BW20: =IFERROR(((BT20+BV20+BU20)/BS20),0) -> 0.75443381 | BX20: =IFERROR(((BT20+BU20+BV20)/BR20-1),0) -> 0.55001445 | BY20: =BS20-BT20-BU20-BV20 -> 207.749 | BZ20: =SUMIF(Cliente!$H:$H,Rede!F20,Cliente!$BM:$BM) -> 116.104 | CA20: =SUMIF(Cliente!$H:$H,Rede!F20,Cliente!$BN:$BN) -> 149.688 | CB20: =SUMIF(Cliente!$H:$H,Rede!$F20,Cliente!$BO:$BO) -> 30.292 | CC20: =SUMIF(Cliente!$H:$H,Rede!$F20,Cliente!$BP:$BP) -> 0 | CD20: =SUMIF(Cliente!$H:$H,Rede!F20,Cliente!$BQ:$BQ) -> 75.667 | CE20: =SUMIF(Cliente!$H:$H,Rede!F20,Cliente!$BR:$BR) -> 102 | CF20: =SUMIF(Cliente!$H:$H,Rede!$F20,Cliente!$BS:$BS) -> 8.417 | CG20: =SUMIF(Cliente!$H:$H,Rede!$F20,Cliente!$BT:$BT) -> 0 | CH20: =SUMIF(Cliente!$H:$H,Rede!$F20,Cliente!$BU:$BU) -> 220 | CI20: =SUMIF(Cliente!$H:$H,Rede!$F20,Cliente!$BV:$BV) -> 304.021 | CJ20: =SUMIF(Cliente!$H:$H,Rede!$F20,Cliente!$BW:$BW) -> 43.833 | CK20: =SUMIF(Cliente!$H:$H,Rede!$F20,Cliente!$BX:$BX) -> 0 | CM20: =G20+AB20+AW20+BR20 -> 3288.429 | CN20: =H20+AC20+AX20+BS20 -> 3470.5814 | CO20: =I20+AD20+AY20+BT20 -> 2134.376 | CP20: =J20+AE20+AZ20+BU20 -> 100.958 | CQ20: =K20+AF20+BA20+BV20 -> 82.542 | CR20: =IFERROR(((CO20+CQ20+CP20)/CN20),0) -> 0.66786389 | CS20: =IFERROR(((CO20+CP20+CQ20)/CM20-1),0) -> -0.29514184 | CT20: =CN20-CO20-CP20-CQ20 -> 1152.7054
C21: NORTE MC/KA D | D21: 359 | E21: MC-ITPE D | F21: REDE MESCHKE | G21: =O21+S21+W21 -> 1265.208 | H21: =_xlfn.XLOOKUP($F21,Metas!$B:$B,Metas!Q:Q,0,0,1) -> 1028.44 | I21: =P21+T21+X21 -> 1507.417 | J21: =Q21+U21+Y21 -> 1 | K21: =R21+V21+Z21 -> 0 | L21: =IFERROR(((I21+K21+J21)/H21),0) -> 1.4667039 | M21: =IFERROR(((I21+J21+K21)/G21-1),0) -> 0.19222847 | N21: =H21-I21-J21-K21 -> -479.977 | O21: =SUMIF(Cliente!$H:$H,Rede!F21,Cliente!$N:$N) -> -0.667 | P21: =SUMIF(Cliente!$H:$H,Rede!$F21,Cliente!$O:$O) -> -1 | Q21: =SUMIF(Cliente!$H:$H,Rede!$F21,Cliente!$P:$P) -> 0 | R21: =SUMIF(Cliente!$H:$H,Rede!$F21,Cliente!$Q:$Q) -> 0 | S21: =SUMIF(Cliente!$H:$H,Rede!$F21,Cliente!$R:$R) -> 713.125 | T21: =SUMIF(Cliente!$H:$H,Rede!$F21,Cliente!$S:$S) -> 242.5 | U21: =SUMIF(Cliente!$H:$H,Rede!$F21,Cliente!$T:$T) -> 1 | V21: =SUMIF(Cliente!$H:$H,Rede!$F21,Cliente!$U:$U) -> 0 | W21: =SUMIF(Cliente!$H:$H,Rede!$F21,Cliente!$V:$V) -> 552.75 | X21: =SUMIF(Cliente!$H:$H,Rede!$F21,Cliente!$W:$W) -> 1265.917 | Y21: =SUMIF(Cliente!$H:$H,Rede!$F21,Cliente!$X:$X) -> 0 | Z21: =SUMIF(Cliente!$H:$H,Rede!$F21,Cliente!$Y:$Y) -> 0 | AB21: =AJ21+AN21+AR21 -> 969.896 | AC21: =_xlfn.XLOOKUP(F21,Metas!B:B,Metas!R:R,0,0,1) -> 881.52398 | AD21: =AK21+AO21+AS21 -> 252.876 | AE21: =AL21+AP21+AT21 -> 0 | AF21: =AM21+AQ21+AU21 -> 0 | AG21: =IFERROR(((AD21+AE21+AF21)/AC21),0) -> 0.2868623 | AH21: =IFERROR(((AD21+AE21+AF21)/AB21-1),0) -> -0.73927514 | AI21: =AC21-AD21-AE21-AF21 -> 628.64798 | AJ21: =SUMIF(Cliente!$H:$H,Rede!$F21,Cliente!$AE:$AE) -> 259.521 | AK21: =SUMIF(Cliente!$H:$H,Rede!$F21,Cliente!$AF:$AF) -> 52.542 | AL21: =SUMIF(Cliente!$H:$H,Rede!$F21,Cliente!$AG:$AG) -> 0 | AM21: =SUMIF(Cliente!$H:$H,Rede!$F21,Cliente!$AH:$AH) -> 0 | AN21: =SUMIF(Cliente!$H:$H,Rede!$F21,Cliente!$AI:$AI) -> 12.458 | AO21: =SUMIF(Cliente!$H:$H,Rede!$F21,Cliente!$AJ:$AJ) -> 118.334 | AP21: =SUMIF(Cliente!$H:$H,Rede!$F21,Cliente!$AK:$AK) -> 0 | AQ21: =SUMIF(Cliente!$H:$H,Rede!$F21,Cliente!$AL:$AL) -> 0 | AR21: =SUMIF(Cliente!$H:$H,Rede!$F21,Cliente!$AM:$AM) -> 697.917 | AS21: =SUMIF(Cliente!$H:$H,Rede!$F21,Cliente!$AN:$AN) -> 82 | AT21: =SUMIF(Cliente!$H:$H,Rede!$F21,Cliente!$AO:$AO) -> 0 | AU21: =SUMIF(Cliente!$H:$H,Rede!$F21,Cliente!$AP:$AP) -> 0 | AW21: =BE21+BI21+BM21 -> 691.396 | AX21: =_xlfn.XLOOKUP(Rede!F21,Metas!B:B,Metas!S:S,0,0,1) -> 829.09561 | AY21: =BF21+BJ21+BN21 -> 330.916 | AZ21: =BG21+BK21+BO21 -> 3 | BA21: =BH21+BL21+BP21 -> 0 | BB21: =IFERROR(((AY21+AZ21+BA21)/AX21),0) -> 0.40274728 | BC21: =IFERROR(((AY21+AZ21+BA21)/AW21-1),0) -> -0.51704089 | BD21: =AX21-AY21-AZ21-BA21 -> 495.17961 | BE21: =SUMIF(Cliente!$H:$H,Rede!F21,Cliente!$AV:$AV) -> 60.167 | BF21: =SUMIF(Cliente!$H:$H,Rede!F21,Cliente!$AW:$AW) -> 61.083 | BG21: =SUMIF(Cliente!$H:$H,Rede!$F21,Cliente!$AX:$AX) -> 0 | BH21: =SUMIF(Cliente!$H:$H,Rede!$F21,Cliente!$AY:$AY) -> 0 | BI21: =SUMIF(Cliente!$H:$H,Rede!F21,Cliente!$AZ:$AZ) -> 99.104 | BJ21: =SUMIF(Cliente!$H:$H,Rede!F21,Cliente!$BA:$BA) -> 70.083 | BK21: =SUMIF(Cliente!$H:$H,Rede!$F21,Cliente!$BB:$BB) -> 0 | BL21: =SUMIF(Cliente!$H:$H,Rede!$F21,Cliente!$BC:$BC) -> 0 | BM21: =SUMIF(Cliente!$H:$H,Rede!F21,Cliente!$BD:$BD) -> 532.125 | BN21: =SUMIF(Cliente!$H:$H,Rede!F21,Cliente!$BE:$BE) -> 199.75 | BO21: =SUMIF(Cliente!$H:$H,Rede!$F21,Cliente!$BF:$BF) -> 3 | BP21: =SUMIF(Cliente!$H:$H,Rede!$F21,Cliente!$BG:$BG) -> 0 | BR21: =BZ21+CD21+CH21 -> 523.083 | BS21: =_xlfn.XLOOKUP(Rede!F21,Metas!B:B,Metas!T:T,0,0,1) -> 882 | BT21: =CA21+CE21+CI21 -> 237.167 | BU21: =CC21+CG21+CK21 -> 121 | BV21: =CB21+CF21+CJ21 -> 12 | BW21: =IFERROR(((BT21+BV21+BU21)/BS21),0) -> 0.41969048 | BX21: =IFERROR(((BT21+BU21+BV21)/BR21-1),0) -> -0.29233602 | BY21: =BS21-BT21-BU21-BV21 -> 511.833 | BZ21: =SUMIF(Cliente!$H:$H,Rede!F21,Cliente!$BM:$BM) -> 188 | CA21: =SUMIF(Cliente!$H:$H,Rede!F21,Cliente!$BN:$BN) -> 80.333 | CB21: =SUMIF(Cliente!$H:$H,Rede!$F21,Cliente!$BO:$BO) -> 0 | CC21: =SUMIF(Cliente!$H:$H,Rede!$F21,Cliente!$BP:$BP) -> 0 | CD21: =SUMIF(Cliente!$H:$H,Rede!F21,Cliente!$BQ:$BQ) -> 40.083 | CE21: =SUMIF(Cliente!$H:$H,Rede!F21,Cliente!$BR:$BR) -> 98.834 | CF21: =SUMIF(Cliente!$H:$H,Rede!$F21,Cliente!$BS:$BS) -> 0 | CG21: =SUMIF(Cliente!$H:$H,Rede!$F21,Cliente!$BT:$BT) -> 0 | CH21: =SUMIF(Cliente!$H:$H,Rede!$F21,Cliente!$BU:$BU) -> 295 | CI21: =SUMIF(Cliente!$H:$H,Rede!$F21,Cliente!$BV:$BV) -> 58 | CJ21: =SUMIF(Cliente!$H:$H,Rede!$F21,Cliente!$BW:$BW) -> 12 | CK21: =SUMIF(Cliente!$H:$H,Rede!$F21,Cliente!$BX:$BX) -> 121 | CM21: =G21+AB21+AW21+BR21 -> 3449.583 | CN21: =H21+AC21+AX21+BS21 -> 3621.0596 | CO21: =I21+AD21+AY21+BT21 -> 2328.376 | CP21: =J21+AE21+AZ21+BU21 -> 125 | CQ21: =K21+AF21+BA21+BV21 -> 12 | CR21: =IFERROR(((CO21+CQ21+CP21)/CN21),0) -> 0.68084381 | CS21: =IFERROR(((CO21+CP21+CQ21)/CM21-1),0) -> -0.28531188 | CT21: =CN21-CO21-CP21-CQ21 -> 1155.6836
C22: NORTE MC/KA D | D22: 4066 | E22: MC-BNU D | F22: REDE MEES | G22: =O22+S22+W22 -> 651.25 | H22: =_xlfn.XLOOKUP($F22,Metas!$B:$B,Metas!Q:Q,0,0,1) -> 397.51 | I22: =P22+T22+X22 -> 396.458 | J22: =Q22+U22+Y22 -> 12.75 | K22: =R22+V22+Z22 -> 0 | L22: =IFERROR(((I22+K22+J22)/H22),0) -> 1.0294282 | M22: =IFERROR(((I22+J22+K22)/G22-1),0) -> -0.37165758 | N22: =H22-I22-J22-K22 -> -11.698 | O22: =SUMIF(Cliente!$H:$H,Rede!F22,Cliente!$N:$N) -> 75.833 | P22: =SUMIF(Cliente!$H:$H,Rede!$F22,Cliente!$O:$O) -> 145.375 | Q22: =SUMIF(Cliente!$H:$H,Rede!$F22,Cliente!$P:$P) -> 9.75 | R22: =SUMIF(Cliente!$H:$H,Rede!$F22,Cliente!$Q:$Q) -> 0 | S22: =SUMIF(Cliente!$H:$H,Rede!$F22,Cliente!$R:$R) -> 72.75 | T22: =SUMIF(Cliente!$H:$H,Rede!$F22,Cliente!$S:$S) -> 259.583 | U22: =SUMIF(Cliente!$H:$H,Rede!$F22,Cliente!$T:$T) -> 3 | V22: =SUMIF(Cliente!$H:$H,Rede!$F22,Cliente!$U:$U) -> 0 | W22: =SUMIF(Cliente!$H:$H,Rede!$F22,Cliente!$V:$V) -> 502.667 | X22: =SUMIF(Cliente!$H:$H,Rede!$F22,Cliente!$W:$W) -> -8.5 | Y22: =SUMIF(Cliente!$H:$H,Rede!$F22,Cliente!$X:$X) -> 0 | Z22: =SUMIF(Cliente!$H:$H,Rede!$F22,Cliente!$Y:$Y) -> 0 | AB22: =AJ22+AN22+AR22 -> 179 | AC22: =_xlfn.XLOOKUP(F22,Metas!B:B,Metas!R:R,0,0,1) -> 340.72555 | AD22: =AK22+AO22+AS22 -> 113.916 | AE22: =AL22+AP22+AT22 -> 1.25 | AF22: =AM22+AQ22+AU22 -> 0 | AG22: =IFERROR(((AD22+AE22+AF22)/AC22),0) -> 0.33800224 | AH22: =IFERROR(((AD22+AE22+AF22)/AB22-1),0) -> -0.35661453 | AI22: =AC22-AD22-AE22-AF22 -> 225.55955 | AJ22: =SUMIF(Cliente!$H:$H,Rede!$F22,Cliente!$AE:$AE) -> 78.5 | AK22: =SUMIF(Cliente!$H:$H,Rede!$F22,Cliente!$AF:$AF) -> 25.083 | AL22: =SUMIF(Cliente!$H:$H,Rede!$F22,Cliente!$AG:$AG) -> 0 | AM22: =SUMIF(Cliente!$H:$H,Rede!$F22,Cliente!$AH:$AH) -> 0 | AN22: =SUMIF(Cliente!$H:$H,Rede!$F22,Cliente!$AI:$AI) -> 58.5 | AO22: =SUMIF(Cliente!$H:$H,Rede!$F22,Cliente!$AJ:$AJ) -> 65 | AP22: =SUMIF(Cliente!$H:$H,Rede!$F22,Cliente!$AK:$AK) -> 1.25 | AQ22: =SUMIF(Cliente!$H:$H,Rede!$F22,Cliente!$AL:$AL) -> 0 | AR22: =SUMIF(Cliente!$H:$H,Rede!$F22,Cliente!$AM:$AM) -> 42 | AS22: =SUMIF(Cliente!$H:$H,Rede!$F22,Cliente!$AN:$AN) -> 23.833 | AT22: =SUMIF(Cliente!$H:$H,Rede!$F22,Cliente!$AO:$AO) -> 0 | AU22: =SUMIF(Cliente!$H:$H,Rede!$F22,Cliente!$AP:$AP) -> 0 | AW22: =BE22+BI22+BM22 -> 358.75 | AX22: =_xlfn.XLOOKUP(Rede!F22,Metas!B:B,Metas!S:S,0,0,1) -> 320.461 | AY22: =BF22+BJ22+BN22 -> 373.917 | AZ22: =BG22+BK22+BO22 -> 28.25 | BA22: =BH22+BL22+BP22 -> 0 | BB22: =IFERROR(((AY22+AZ22+BA22)/AX22),0) -> 1.2549639 | BC22: =IFERROR(((AY22+AZ22+BA22)/AW22-1),0) -> 0.121023 | BD22: =AX22-AY22-AZ22-BA22 -> -81.705999 | BE22: =SUMIF(Cliente!$H:$H,Rede!F22,Cliente!$AV:$AV) -> 38.5 | BF22: =SUMIF(Cliente!$H:$H,Rede!F22,Cliente!$AW:$AW) -> 65.167 | BG22: =SUMIF(Cliente!$H:$H,Rede!$F22,Cliente!$AX:$AX) -> 1.75 | BH22: =SUMIF(Cliente!$H:$H,Rede!$F22,Cliente!$AY:$AY) -> 0 | BI22: =SUMIF(Cliente!$H:$H,Rede!F22,Cliente!$AZ:$AZ) -> 152.25 | BJ22: =SUMIF(Cliente!$H:$H,Rede!F22,Cliente!$BA:$BA) -> 113.417 | BK22: =SUMIF(Cliente!$H:$H,Rede!$F22,Cliente!$BB:$BB) -> 2.5 | BL22: =SUMIF(Cliente!$H:$H,Rede!$F22,Cliente!$BC:$BC) -> 0 | BM22: =SUMIF(Cliente!$H:$H,Rede!F22,Cliente!$BD:$BD) -> 168 | BN22: =SUMIF(Cliente!$H:$H,Rede!F22,Cliente!$BE:$BE) -> 195.333 | BO22: =SUMIF(Cliente!$H:$H,Rede!$F22,Cliente!$BF:$BF) -> 24 | BP22: =SUMIF(Cliente!$H:$H,Rede!$F22,Cliente!$BG:$BG) -> 0 | BR22: =BZ22+CD22+CH22 -> 121.125 | BS22: =_xlfn.XLOOKUP(Rede!F22,Metas!B:B,Metas!T:T,0,0,1) -> 342 | BT22: =CA22+CE22+CI22 -> 160.667 | BU22: =CC22+CG22+CK22 -> 45 | BV22: =CB22+CF22+CJ22 -> 19.958 | BW22: =IFERROR(((BT22+BV22+BU22)/BS22),0) -> 0.65972222 | BX22: =IFERROR(((BT22+BU22+BV22)/BR22-1),0) -> 0.8627451 | BY22: =BS22-BT22-BU22-BV22 -> 116.375 | BZ22: =SUMIF(Cliente!$H:$H,Rede!F22,Cliente!$BM:$BM) -> 62.25 | CA22: =SUMIF(Cliente!$H:$H,Rede!F22,Cliente!$BN:$BN) -> 26.667 | CB22: =SUMIF(Cliente!$H:$H,Rede!$F22,Cliente!$BO:$BO) -> 0.833 | CC22: =SUMIF(Cliente!$H:$H,Rede!$F22,Cliente!$BP:$BP) -> 0 | CD22: =SUMIF(Cliente!$H:$H,Rede!F22,Cliente!$BQ:$BQ) -> 50.875 | CE22: =SUMIF(Cliente!$H:$H,Rede!F22,Cliente!$BR:$BR) -> 30.667 | CF22: =SUMIF(Cliente!$H:$H,Rede!$F22,Cliente!$BS:$BS) -> 3.167 | CG22: =SUMIF(Cliente!$H:$H,Rede!$F22,Cliente!$BT:$BT) -> 0 | CH22: =SUMIF(Cliente!$H:$H,Rede!$F22,Cliente!$BU:$BU) -> 8 | CI22: =SUMIF(Cliente!$H:$H,Rede!$F22,Cliente!$BV:$BV) -> 103.333 | CJ22: =SUMIF(Cliente!$H:$H,Rede!$F22,Cliente!$BW:$BW) -> 15.958 | CK22: =SUMIF(Cliente!$H:$H,Rede!$F22,Cliente!$BX:$BX) -> 45 | CM22: =G22+AB22+AW22+BR22 -> 1310.125 | CN22: =H22+AC22+AX22+BS22 -> 1400.6966 | CO22: =I22+AD22+AY22+BT22 -> 1044.958 | CP22: =J22+AE22+AZ22+BU22 -> 87.25 | CQ22: =K22+AF22+BA22+BV22 -> 19.958 | CR22: =IFERROR(((CO22+CQ22+CP22)/CN22),0) -> 0.82256646 | CS22: =IFERROR(((CO22+CP22+CQ22)/CM22-1),0) -> -0.12056788 | CT22: =CN22-CO22-CP22-CQ22 -> 248.53055
C23: NORTE MC/KA D | D23: 3655 | E23: KA-BNU | F23: REDE TOP | G23: =O23+S23+W23 -> 1092.75 | H23: =_xlfn.XLOOKUP($F23,Metas!$B:$B,Metas!Q:Q,0,0,1) -> 2551.88 | I23: =P23+T23+X23 -> 2591.659 | J23: =Q23+U23+Y23 -> 0.417 | K23: =R23+V23+Z23 -> 0 | L23: =IFERROR(((I23+K23+J23)/H23),0) -> 1.0157515 | M23: =IFERROR(((I23+J23+K23)/G23-1),0) -> 1.3720668 | N23: =H23-I23-J23-K23 -> -40.196 | O23: =SUMIF(Cliente!$H:$H,Rede!F23,Cliente!$N:$N) -> 436.75 | P23: =SUMIF(Cliente!$H:$H,Rede!$F23,Cliente!$O:$O) -> 626 | Q23: =SUMIF(Cliente!$H:$H,Rede!$F23,Cliente!$P:$P) -> 0 | R23: =SUMIF(Cliente!$H:$H,Rede!$F23,Cliente!$Q:$Q) -> 0 | S23: =SUMIF(Cliente!$H:$H,Rede!$F23,Cliente!$R:$R) -> 239 | T23: =SUMIF(Cliente!$H:$H,Rede!$F23,Cliente!$S:$S) -> 172.667 | U23: =SUMIF(Cliente!$H:$H,Rede!$F23,Cliente!$T:$T) -> 0.417 | V23: =SUMIF(Cliente!$H:$H,Rede!$F23,Cliente!$U:$U) -> 0 | W23: =SUMIF(Cliente!$H:$H,Rede!$F23,Cliente!$V:$V) -> 417 | X23: =SUMIF(Cliente!$H:$H,Rede!$F23,Cliente!$W:$W) -> 1792.992 | Y23: =SUMIF(Cliente!$H:$H,Rede!$F23,Cliente!$X:$X) -> 0 | Z23: =SUMIF(Cliente!$H:$H,Rede!$F23,Cliente!$Y:$Y) -> 0 | AB23: =AJ23+AN23+AR23 -> 4926.167 | AC23: =_xlfn.XLOOKUP(F23,Metas!B:B,Metas!R:R,0,0,1) -> 2187.3287 | AD23: =AK23+AO23+AS23 -> 2142.833 | AE23: =AL23+AP23+AT23 -> 11 | AF23: =AM23+AQ23+AU23 -> 0 | AG23: =IFERROR(((AD23+AE23+AF23)/AC23),0) -> 0.9846865 | AH23: =IFERROR(((AD23+AE23+AF23)/AB23-1),0) -> -0.5627771 | AI23: =AC23-AD23-AE23-AF23 -> 33.495656 | AJ23: =SUMIF(Cliente!$H:$H,Rede!$F23,Cliente!$AE:$AE) -> 2393.583 | AK23: =SUMIF(Cliente!$H:$H,Rede!$F23,Cliente!$AF:$AF) -> 1159.833 | AL23: =SUMIF(Cliente!$H:$H,Rede!$F23,Cliente!$AG:$AG) -> 0 | AM23: =SUMIF(Cliente!$H:$H,Rede!$F23,Cliente!$AH:$AH) -> 0 | AN23: =SUMIF(Cliente!$H:$H,Rede!$F23,Cliente!$AI:$AI) -> 1487.917 | AO23: =SUMIF(Cliente!$H:$H,Rede!$F23,Cliente!$AJ:$AJ) -> 319 | AP23: =SUMIF(Cliente!$H:$H,Rede!$F23,Cliente!$AK:$AK) -> 0 | AQ23: =SUMIF(Cliente!$H:$H,Rede!$F23,Cliente!$AL:$AL) -> 0 | AR23: =SUMIF(Cliente!$H:$H,Rede!$F23,Cliente!$AM:$AM) -> 1044.667 | AS23: =SUMIF(Cliente!$H:$H,Rede!$F23,Cliente!$AN:$AN) -> 664 | AT23: =SUMIF(Cliente!$H:$H,Rede!$F23,Cliente!$AO:$AO) -> 11 | AU23: =SUMIF(Cliente!$H:$H,Rede!$F23,Cliente!$AP:$AP) -> 0 | AW23: =BE23+BI23+BM23 -> 1411.25 | AX23: =_xlfn.XLOOKUP(Rede!F23,Metas!B:B,Metas!S:S,0,0,1) -> 2057.2379 | AY23: =BF23+BJ23+BN23 -> 3123.992 | AZ23: =BG23+BK23+BO23 -> 11 | BA23: =BH23+BL23+BP23 -> 0 | BB23: =IFERROR(((AY23+AZ23+BA23)/AX23),0) -> 1.523884 | BC23: =IFERROR(((AY23+AZ23+BA23)/AW23-1),0) -> 1.2214292 | BD23: =AX23-AY23-AZ23-BA23 -> -1077.7541 | BE23: =SUMIF(Cliente!$H:$H,Rede!F23,Cliente!$AV:$AV) -> 339 | BF23: =SUMIF(Cliente!$H:$H,Rede!F23,Cliente!$AW:$AW) -> 873 | BG23: =SUMIF(Cliente!$H:$H,Rede!$F23,Cliente!$AX:$AX) -> 11 | BH23: =SUMIF(Cliente!$H:$H,Rede!$F23,Cliente!$AY:$AY) -> 0 | BI23: =SUMIF(Cliente!$H:$H,Rede!F23,Cliente!$AZ:$AZ) -> 873.667 | BJ23: =SUMIF(Cliente!$H:$H,Rede!F23,Cliente!$BA:$BA) -> 1116.992 | BK23: =SUMIF(Cliente!$H:$H,Rede!$F23,Cliente!$BB:$BB) -> 0 | BL23: =SUMIF(Cliente!$H:$H,Rede!$F23,Cliente!$BC:$BC) -> 0 | BM23: =SUMIF(Cliente!$H:$H,Rede!F23,Cliente!$BD:$BD) -> 198.583 | BN23: =SUMIF(Cliente!$H:$H,Rede!F23,Cliente!$BE:$BE) -> 1134 | BO23: =SUMIF(Cliente!$H:$H,Rede!$F23,Cliente!$BF:$BF) -> 0 | BP23: =SUMIF(Cliente!$H:$H,Rede!$F23,Cliente!$BG:$BG) -> 0 | BR23: =BZ23+CD23+CH23 -> 1217.242 | BS23: =_xlfn.XLOOKUP(Rede!F23,Metas!B:B,Metas!T:T,0,0,1) -> 2190 | BT23: =CA23+CE23+CI23 -> 1228.5 | BU23: =CC23+CG23+CK23 -> 0 | BV23: =CB23+CF23+CJ23 -> 0 | BW23: =IFERROR(((BT23+BV23+BU23)/BS23),0) -> 0.5609589 | BX23: =IFERROR(((BT23+BU23+BV23)/BR23-1),0) -> 0.0092487772 | BY23: =BS23-BT23-BU23-BV23 -> 961.5 | BZ23: =SUMIF(Cliente!$H:$H,Rede!F23,Cliente!$BM:$BM) -> 326.325 | CA23: =SUMIF(Cliente!$H:$H,Rede!F23,Cliente!$BN:$BN) -> 126 | CB23: =SUMIF(Cliente!$H:$H,Rede!$F23,Cliente!$BO:$BO) -> 0 | CC23: =SUMIF(Cliente!$H:$H,Rede!$F23,Cliente!$BP:$BP) -> 0 | CD23: =SUMIF(Cliente!$H:$H,Rede!F23,Cliente!$BQ:$BQ) -> 606 | CE23: =SUMIF(Cliente!$H:$H,Rede!F23,Cliente!$BR:$BR) -> 1106.5 | CF23: =SUMIF(Cliente!$H:$H,Rede!$F23,Cliente!$BS:$BS) -> 0 | CG23: =SUMIF(Cliente!$H:$H,Rede!$F23,Cliente!$BT:$BT) -> 0 | CH23: =SUMIF(Cliente!$H:$H,Rede!$F23,Cliente!$BU:$BU) -> 284.917 | CI23: =SUMIF(Cliente!$H:$H,Rede!$F23,Cliente!$BV:$BV) -> -4 | CJ23: =SUMIF(Cliente!$H:$H,Rede!$F23,Cliente!$BW:$BW) -> 0 | CK23: =SUMIF(Cliente!$H:$H,Rede!$F23,Cliente!$BX:$BX) -> 0 | CM23: =G23+AB23+AW23+BR23 -> 8647.409 | CN23: =H23+AC23+AX23+BS23 -> 8986.4466 | CO23: =I23+AD23+AY23+BT23 -> 9086.984 | CP23: =J23+AE23+AZ23+BU23 -> 22.417 | CQ23: =K23+AF23+BA23+BV23 -> 0 | CR23: =IFERROR(((CO23+CQ23+CP23)/CN23),0) -> 1.0136822 | CS23: =IFERROR(((CO23+CP23+CQ23)/CM23-1),0) -> 0.053425483 | CT23: =CN23-CO23-CP23-CQ23 -> -122.95441

Sheet aux
A1: EQUIPE | B1: VEND | C1: AREA | E1: REDE | G1: EQUIPE | H1: VEND | I1: AREA | J1: REDE
A2: FLP-SUL MC/KA D | B2: 771 | C2: MC-FLP D | E2: REDE HIPER SELECT | G2: FLP-SUL MC/KA D | H2: 771 | I2: MC-FLP D | J2: REDE HIPER SELECT
A3: FLP-SUL MC/KA D | B3: 3919 | C3: MC-TBCR D | E3: REDE SM ROSSO | G3: FLP-SUL MC/KA D | H3: 3919 | I3: MC-TBCR D | J3: REDE SM ROSSO
A4: FLP-SUL MC/KA D | B4: 3956 | C4: MC-IMB D | E4: REDE MANENTI | G4: FLP-SUL MC/KA D | H4: 3919 | I4: MC-TBCR D | J4: REDE MANENTI
A5: FLP-SUL MC/KA D | B5: 4054 | C5: MC-ARA D | E5: REDE VENCEDOR | G5: FLP-SUL MC/KA D | H5: 3919 | I5: MC-TBCR D | J5: REDE VENCEDOR
A6: NORTE MC/KA D | B6: 179 | C6: KA-BRQ | E6: REDE ABIMAR | G6: FLP-SUL MC/KA D | H6: 3919 | I6: MC-TBCR D | J6: REDE ABIMAR
A7: NORTE MC/KA D | B7: 359 | C7: MC-ITPE D | E7: REDE SM SILVEIRA | G7: FLP-SUL MC/KA D | H7: 3956 | I7: MC-IMB D | J7: REDE SM SILVEIRA
A8: NORTE MC/KA D | B8: 4066 | C8: MC-BNU D | E8: REDE COOPER AGRO | G8: FLP-SUL MC/KA D | H8: 4054 | I8: MC-ARA D | J8: REDE COOPER AGRO
A9: NORTE MC/KA M | B9: 3655 | C9: KA-BNU | E9: REDE FEGOAGRO | G9: FLP-SUL MC/KA D | H9: 4054 | I9: MC-ARA D | J9: REDE FEGOAGRO
E10: REDE ARCHER | G10: NORTE MC/KA D | H10: 179 | I10: KA-BRQ | J10: REDE ARCHER
E11: REDE UBER | G11: NORTE MC/KA D | H11: 359 | I11: MC-ITPE D | J11: REDE UBER
E12: REDE NILO GOEDERT | G12: NORTE MC/KA D | H12: 359 | I12: MC-ITPE D | J12: REDE NILO GOEDERT
E13: REDE MESCHKE | G13: NORTE MC/KA D | H13: 359 | I13: MC-ITPE D | J13: REDE MESCHKE
E14: REDE MEES | G14: NORTE MC/KA D | H14: 4066 | I14: MC-BNU D | J14: REDE MEES
E15: REDE TOP | G15: NORTE MC/KA M | H15: 3655 | I15: KA-BNU | J15: REDE TOP

Sheet Cliente
N6: JUL/2024 | O6: JUL/2025 | R6: AGO/2024 | S6: AGO/2025 | V6: SET/2024 | W6: SET/2025 | AE6: OUT/2024 | AF6: OUT/2025 | AI6: NOV/2024 | AJ6: NOV/2025 | AM6: DEZ/2024 | AN6: DEZ/2025 | AV6: JAN/2025 | AW6: JAN/2026 | AZ6: FEV/2025 | BA6: FEV/2026 | BD6: MAR/2025 | BE6: MAR/2026 | BM6: ABR/2025 | BN6: ABR/2026 | BQ6: MAI/2025 | BR6: MAI/2026 | BU6: JUN/2025 | BV6: JUN/2026
I7: TOTAL: | J7: =SUBTOTAL(9,J10:J107) -> 14339.799 | K7: =SUBTOTAL(9,K10:K107) -> 15458.304 | L7: =SUBTOTAL(9,L10:L107) -> 125.5 | M7: =SUBTOTAL(9,M10:M107) -> 0 | N7: =SUBTOTAL(9,N10:N107) -> 1856.139 | O7: =SUBTOTAL(9,O10:O107) -> 1941.979 | P7: =SUBTOTAL(9,P10:P107) -> 54 | Q7: =SUBTOTAL(9,Q10:Q107) -> 0 | ... BX7: =SUBTOTAL(9,BX10:BX107) -> 225
J8: Q1 - JULHO A SETEMBRO | N8: JULHO | R8: AGOSTO | V8: SETEMBRO | AA8: Q2 - OUTUBRO A DEZEMBRO | AE8: OUTUBRO | AI8: NOVEMBRO | AM8: DEZEMBRO | AR8: Q3 - JANEIRO A MARÇO | AV8: JANEIRO | AZ8: FEVEREIRO | BD8: MARÇO | BI8: Q4 - ABRIL A JUNHO | BM8: ABRIL | BQ8: MAIO | BU8: JUNHO
B9: EQUIPE | C9: CÓD | D9: ÁREA | E9: CÓD. | F9: CNPJ | G9: CLIENTE | H9: REDE | I9: STATUS | J9: HIST | K9: FAT | L9: BONIF | M9: MÁQ | N9: HIST | O9: FAT | P9: BONIF | Q9: MÁQ | R9: HIST | S9: FAT | T9: BONIF | U9: MÁQ | V9: HIST | W9: FAT | X9: BONIF | Y9: MÁQ | AA9: HIST | AB9: FAT | AC9: BONIF | AD9: MÁQ | AE9: HIST | AF9: FAT | AG9: BONIF | AH9: MÁQ | AI9: HIST | AJ9: FAT | AK9: BONIF | AL9: MÁQ | AM9: HIST | AN9: FAT | AO9: BONIF | AP9: MÁQ | AR9: HIST | AS9: FAT | AT9: BONIF | AU9: MÁQ | AV9: HIST | AW9: FAT | AX9: BONIF | AY9: MÁQ | AZ9: HIST | BA9: FAT | BB9: BONIF | BC9: MÁQ | BD9: HIST | BE9: FAT | BF9: BONIF | BG9: MÁQ | BI9: HIST | BJ9: FAT | BK9: BONIF | BL9: MÁQ | BM9: HIST | BN9: FAT | BO9: BONIF | BP9: MÁQ | BQ9: HIST | BR9: FAT | BS9: BONIF | BT9: MÁQ | BU9: HIST | BV9: FAT | BW9: BONIF | BX9: MÁQ
B10: FLP-SUL MC/KA D | C10: 771 | D10: MC-FLP D | E10: 142393 | F10: 040310260004-09 | G10: HIPER SELECT SUPERMERCADOS LTDA. | H10: REDE HIPER SELECT | I10: ATIVO | J10: =N10+R10+V10 -> 1650.944 | K10: =O10+S10+W10 -> -134.05 | L10: =P10+T10+X10 -> 0 | M10: =Q10+U10+Y10 -> 0 | N10: =IFERROR(VLOOKUP($E10&N$6,Base!$A:$E,5,0),0) -> 270.844 | O10: 7.875 | P10: 0 | R10: =IFERROR(VLOOKUP($E10&R$6,Base!$A:$E,5,0),0) -> 854.558 | S10: =IFERROR(VLOOKUP($E10&S$6,Base!$G:$K,5,0),0) -> -1.092 | T10: =IFERROR(VLOOKUP($E10&S$6,Base!$M:$Q,5,0),0) -> 0 | V10: =IFERROR(VLOOKUP($E10&V$6,Base!$A:$E,5,0),0) -> 525.542 | W10: =IFERROR(VLOOKUP($E10&W$6,Base!$G:$K,5,0),0) -> -140.833 | X10: =IFERROR(VLOOKUP($E10&W$6,Base!$M:$Q,5,0),0) -> 0 | AA10: =AE10+AI10+AM10 -> 993.408 | AB10: =AF10+AJ10+AN10 -> -4.608 | AC10: =AG10+AK10+AO10 -> 0 | AD10: =AH10+AL10+AP10 -> 0 | AE10: =IFERROR(VLOOKUP($E10&AE$6,Base!$A:$E,5,0),0) -> 814.133 | AF10: =IFERROR(VLOOKUP($E10&AF$6,Base!$G:$K,5,0),0) -> -4.225 | AG10: =IFERROR(VLOOKUP($E10&AF$6,Base!$M:$Q,5,0),0) -> 0 | AI10: =IFERROR(VLOOKUP($E10&AI$6,Base!$A:$E,5,0),0) -> 79.108 | AJ10: =IFERROR(VLOOKUP($E10&AJ$6,Base!$G:$K,5,0),0) -> 0 | AK10: =IFERROR(VLOOKUP($E10&AJ$6,Base!$M:$Q,5,0),0) -> 0 | AL10: 0 | AM10: =IFERROR(VLOOKUP($E10&AM$6,Base!$A:$E,5,0),0) -> 100.167 | AN10: =IFERROR(VLOOKUP($E10&AN$6,Base!$G:$K,5,0),0) -> -0.383 | AO10: =IFERROR(VLOOKUP($E10&AN$6,Base!$M:$Q,5,0),0) -> 0 | AR10: =AV10+AZ10+BD10 -> 281.404 | AS10: =AW10+BA10+BE10 -> -0.608 | AT10: =AX10+BB10+BF10 -> 0 | AU10: =AY10+BC10+BG10 -> 0 | AV10: =IFERROR(VLOOKUP($E10&AV$6,Base!$A:$E,5,0),0) -> 180.779 | AW10: =IFERROR(VLOOKUP($E10&AW$6,Base!$G:$K,5,0),0) -> -0.608 | AX10: =IFERROR(VLOOKUP($E10&AW$6,Base!$M:$Q,5,0),0) -> 0 | AY10: 0 | AZ10: =IFERROR(VLOOKUP($E10&AZ$6,Base!$A:$E,5,0),0) -> 47.792 | BA10: =IFERROR(VLOOKUP($E10&BA$6,Base!$G:$K,5,0),0) -> 0 | BB10: =IFERROR(VLOOKUP($E10&BA$6,Base!$M:$Q,5,0),0) -> 0 | BC10: 0 | BD10: =IFERROR(VLOOKUP($E10&BD$6,Base!$A:$E,5,0),0) -> 52.833 | BE10: =IFERROR(VLOOKUP($E10&BE$6,Base!$G:$K,5,0),0) -> 0 | BF10: =IFERROR(VLOOKUP($E10&BE$6,Base!$M:$Q,5,0),0) -> 0 | BG10: 0 | BI10: =BM10+BQ10+BU10 -> 44.396 | BJ10: =BN10+BR10+BV10 -> -1 | BK10: =BO10+BS10+BW10 -> 0 | BL10: =BP10+BT10+BX10 -> 0 | BM10: =IFERROR(VLOOKUP($E10&BM$6,Base!$A:$E,5,0),0) -> 14.333 | BN10: =IFERROR(VLOOKUP($E10&BN$6,Base!$G:$K,5,0),0) -> -0.167 | BO10: =IFERROR(VLOOKUP($E10&BN$6,Base!$M:$Q,5,0),0) -> 0 | BP10: 0 | BQ10: =IFERROR(VLOOKUP($E10&BQ$6,Base!$A:$E,5,0),0) -> 14.825 | BR10: =IFERROR(VLOOKUP($E10&BR$6,Base!$G:$K,5,0),0) -> 0 | BS10: =IFERROR(VLOOKUP($E10&BR$6,Base!$M:$Q,5,0),0) -> 0 | BT10: 0 | BU10: =IFERROR(VLOOKUP($E10&BU$6,Base!$A:$E,5,0),0) -> 15.238 | BV10: =IFERROR(VLOOKUP($E10&BV$6,Base!$G:$K,5,0),0) -> -0.833 | BW10: =IFERROR(VLOOKUP($E10&BV$6,Base!$M:$Q,5,0),0) -> 0 | BX10: =IFERROR(VLOOKUP($E10,Base!$U:$W,3,0),0) -> 0
B11: FLP-SUL MC/KA D | C11: 771 | D11: MC-FLP D | E11: 55070 | F11: 036508310001-05 | G11: HIPER SELECT SUPERMERCADOS LTDA | H11: REDE HIPER SELECT | I11: ATIVO | J11: =N11+R11+V11 -> 0 | K11: =O11+S11+W11 -> 0 | L11: =P11+T11+X11 -> 0 | M11: =Q11+U11+Y11 -> 0 | N11: =IFERROR(VLOOKUP($E11&N$6,Base!$A:$E,5,0),0) -> 0 | O11: 0 | P11: 0 | R11: =IFERROR(VLOOKUP($E11&R$6,Base!$A:$E,5,0),0) -> 0 | S11: =IFERROR(VLOOKUP($E11&S$6,Base!$G:$K,5,0),0) -> 0 | T11: =IFERROR(VLOOKUP($E11&S$6,Base!$M:$Q,5,0),0) -> 0 | V11: =IFERROR(VLOOKUP($E11&V$6,Base!$A:$E,5,0),0) -> 0 | W11: =IFERROR(VLOOKUP($E11&W$6,Base!$G:$K,5,0),0) -> 0 | X11: =IFERROR(VLOOKUP($E11&W$6,Base!$M:$Q,5,0),0) -> 0 | AA11: =AE11+AI11+AM11 -> 0 | AB11: =AF11+AJ11+AN11 -> 0 | AC11: =AG11+AK11+AO11 -> 0 | AD11: =AH11+AL11+AP11 -> 0 | AE11: =IFERROR(VLOOKUP($E11&AE$6,Base!$A:$E,5,0),0) -> 0 | AF11: =IFERROR(VLOOKUP($E11&AF$6,Base!$G:$K,5,0),0) -> 0 | AG11: =IFERROR(VLOOKUP($E11&AF$6,Base!$M:$Q,5,0),0) -> 0 | AI11: =IFERROR(VLOOKUP($E11&AI$6,Base!$A:$E,5,0),0) -> 0 | AJ11: =IFERROR(VLOOKUP($E11&AJ$6,Base!$G:$K,5,0),0) -> 0 | AK11: =IFERROR(VLOOKUP($E11&AJ$6,Base!$M:$Q,5,0),0) -> 0 | AL11: 0 | AM11: =IFERROR(VLOOKUP($E11&AM$6,Base!$A:$E,5,0),0) -> 0 | AN11: =IFERROR(VLOOKUP($E11&AN$6,Base!$G:$K,5,0),0) -> 0 | AO11: =IFERROR(VLOOKUP($E11&AN$6,Base!$M:$Q,5,0),0) -> 0 | AR11: =AV11+AZ11+BD11 -> 0 | AS11: =AW11+BA11+BE11 -> 0 | AT11: =AX11+BB11+BF11 -> 0 | AU11: =AY11+BC11+BG11 -> 0 | AV11: =IFERROR(VLOOKUP($E11&AV$6,Base!$A:$E,5,0),0) -> 0 | AW11: =IFERROR(VLOOKUP($E11&AW$6,Base!$G:$K,5,0),0) -> 0 | AX11: =IFERROR(VLOOKUP($E11&AW$6,Base!$M:$Q,5,0),0) -> 0 | AY11: 0 | AZ11: =IFERROR(VLOOKUP($E11&AZ$6,Base!$A:$E,5,0),0) -> 0 | BA11: =IFERROR(VLOOKUP($E11&BA$6,Base!$G:$K,5,0),0) -> 0 | BB11: =IFERROR(VLOOKUP($E11&BA$6,Base!$M:$Q,5,0),0) -> 0 | BC11: 0 | BD11: =IFERROR(VLOOKUP($E11&BD$6,Base!$A:$E,5,0),0) -> 0 | BE11: =IFERROR(VLOOKUP($E11&BE$6,Base!$G:$K,5,0),0) -> 0 | BF11: =IFERROR(VLOOKUP($E11&BE$6,Base!$M:$Q,5,0),0) -> 0 | BG11: 0 | BI11: =BM11+BQ11+BU11 -> 0 | BJ11: =BN11+BR11+BV11 -> 0 | BK11: =BO11+BS11+BW11 -> 0 | BL11: =BP11+BT11+BX11 -> 0 | BM11: =IFERROR(VLOOKUP($E11&BM$6,Base!$A:$E,5,0),0) -> 0 | BN11: =IFERROR(VLOOKUP($E11&BN$6,Base!$G:$K,5,0),0) -> 0 | BO11: =IFERROR(VLOOKUP($E11&BN$6,Base!$M:$Q,5,0),0) -> 0 | BP11: 0 | BQ11: =IFERROR(VLOOKUP($E11&BQ$6,Base!$A:$E,5,0),0) -> 0 | BR11: =IFERROR(VLOOKUP($E11&BR$6,Base!$G:$K,5,0),0) -> 0 | BS11: =IFERROR(VLOOKUP($E11&BR$6,Base!$M:$Q,5,0),0) -> 0 | BT11: 0 | BU11: =IFERROR(VLOOKUP($E11&BU$6,Base!$A:$E,5,0),0) -> 0 | BV11: =IFERROR(VLOOKUP($E11&BV$6,Base!$G:$K,5,0),0) -> 0 | BW11: =IFERROR(VLOOKUP($E11&BV$6,Base!$M:$Q,5,0),0) -> 0 | BX11: =IFERROR(VLOOKUP($E11,Base!$U:$W,3,0),0) -> 0
B12: FLP-SUL MC/KA D | C12: 771 | D12: MC-FLP D | E12: 69413 | F12: 040310260001-58 | G12: SUPERMERCADO FELIPE ROYER LTDA | H12: REDE HIPER SELECT | I12: ATIVO | J12: =N12+R12+V12 -> 0 | K12: =O12+S12+W12 -> 0 | L12: =P12+T12+X12 -> 0 | M12: =Q12+U12+Y12 -> 0 | N12: =IFERROR(VLOOKUP($E12&N$6,Base!$A:$E,5,0),0) -> 0 | O12: 0 | P12: 0 | R12: =IFERROR(VLOOKUP($E12&R$6,Base!$A:$E,5,0),0) -> 0 | S12: =IFERROR(VLOOKUP($E12&S$6,Base!$G:$K,5,0),0) -> 0 | T12: =IFERROR(VLOOKUP($E12&S$6,Base!$M:$Q,5,0),0) -> 0 | V12: =IFERROR(VLOOKUP($E12&V$6,Base!$A:$E,5,0),0) -> 0 | W12: =IFERROR(VLOOKUP($E12&W$6,Base!$G:$K,5,0),0) -> 0 | X12: =IFERROR(VLOOKUP($E12&W$6,Base!$M:$Q,5,0),0) -> 0 | AA12: =AE12+AI12+AM12 -> 0 | AB12: =AF12+AJ12+AN12 -> 0 | AC12: =AG12+AK12+AO12 -> 0 | AD12: =AH12+AL12+AP12 -> 0 | AE12: =IFERROR(VLOOKUP($E12&AE$6,Base!$A:$E,5,0),0) -> 0 | AF12: =IFERROR(VLOOKUP($E12&AF$6,Base!$G:$K,5,0),0) -> 0 | AG12: =IFERROR(VLOOKUP($E12&AF$6,Base!$M:$Q,5,0),0) -> 0 | AI12: =IFERROR(VLOOKUP($E12&AI$6,Base!$A:$E,5,0),0) -> 0 | AJ12: =IFERROR(VLOOKUP($E12&AJ$6,Base!$G:$K,5,0),0) -> 0 | AK12: =IFERROR(VLOOKUP($E12&AJ$6,Base!$M:$Q,5,0),0) -> 0 | AL12: 0 | AM12: =IFERROR(VLOOKUP($E12&AM$6,Base!$A:$E,5,0),0) -> 0 | AN12: =IFERROR(VLOOKUP($E12&AN$6,Base!$G:$K,5,0),0) -> 0 | AO12: =IFERROR(VLOOKUP($E12&AN$6,Base!$M:$Q,5,0),0) -> 0 | AR12: =AV12+AZ12+BD12 -> 0 | AS12: =AW12+BA12+BE12 -> 0 | AT12: =AX12+BB12+BF12 -> 0 | AU12: =AY12+BC12+BG12 -> 0 | AV12: =IFERROR(VLOOKUP($E12&AV$6,Base!$A:$E,5,0),0) -> 0 | AW12: =IFERROR(VLOOKUP($E12&AW$6,Base!$G:$K,5,0),0) -> 0 | AX12: =IFERROR(VLOOKUP($E12&AW$6,Base!$M:$Q,5,0),0) -> 0 | AY12: 0 | AZ12: =IFERROR(VLOOKUP($E12&AZ$6,Base!$A:$E,5,0),0) -> 0 | BA12: =IFERROR(VLOOKUP($E12&BA$6,Base!$G:$K,5,0),0) -> 0 | BB12: =IFERROR(VLOOKUP($E12&BA$6,Base!$M:$Q,5,0),0) -> 0 | BC12: 0 | BD12: =IFERROR(VLOOKUP($E12&BD$6,Base!$A:$E,5,0),0) -> 0 | BE12: =IFERROR(VLOOKUP($E12&BE$6,Base!$G:$K,5,0),0) -> 0 | BF12: =IFERROR(VLOOKUP($E12&BE$6,Base!$M:$Q,5,0),0) -> 0 | BG12: 0 | BI12: =BM12+BQ12+BU12 -> 0 | BJ12: =BN12+BR12+BV12 -> 0 | BK12: =BO12+BS12+BW12 -> 0 | BL12: =BP12+BT12+BX12 -> 0 | BM12: =IFERROR(VLOOKUP($E12&BM$6,Base!$A:$E,5,0),0) -> 0 | BN12: =IFERROR(VLOOKUP($E12&BN$6,Base!$G:$K,5,0),0) -> 0 | BO12: =IFERROR(VLOOKUP($E12&BN$6,Base!$M:$Q,5,0),0) -> 0 | BP12: 0 | BQ12: =IFERROR(VLOOKUP($E12&BQ$6,Base!$A:$E,5,0),0) -> 0 | BR12: =IFERROR(VLOOKUP($E12&BR$6,Base!$G:$K,5,0),0) -> 0 | BS12: =IFERROR(VLOOKUP($E12&BR$6,Base!$M:$Q,5,0),0) -> 0 | BT12: 0 | BU12: =IFERROR(VLOOKUP($E12&BU$6,Base!$A:$E,5,0),0) -> 0 | BV12: =IFERROR(VLOOKUP($E12&BV$6,Base!$G:$K,5,0),0) -> 0 | BW12: =IFERROR(VLOOKUP($E12&BV$6,Base!$M:$Q,5,0),0) -> 0 | BX12: =IFERROR(VLOOKUP($E12,Base!$U:$W,3,0),0) -> 0
B13: FLP-SUL MC/KA D | C13: 771 | D13: MC-FLP D | E13: 116011 | F13: 040310260002-39 | G13: SUPERMERCADO FELIPE ROYER LTDA | H13: REDE HIPER SELECT | I13: ATIVO | J13: =N13+R13+V13 -> 0 | K13: =O13+S13+W13 -> 0 | L13: =P13+T13+X13 -> 0 | M13: =Q13+U13+Y13 -> 0 | N13: =IFERROR(VLOOKUP($E13&N$6,Base!$A:$E,5,0),0) -> 0 | O13: 0 | P13: 0 | R13: =IFERROR(VLOOKUP($E13&R$6,Base!$A:$E,5,0),0) -> 0 | S13: =IFERROR(VLOOKUP($E13&S$6,Base!$G:$K,5,0),0) -> 0 | T13: =IFERROR(VLOOKUP($E13&S$6,Base!$M:$Q,5,0),0) -> 0 | V13: =IFERROR(VLOOKUP($E13&V$6,Base!$A:$E,5,0),0) -> 0 | W13: =IFERROR(VLOOKUP($E13&W$6,Base!$G:$K,5,0),0) -> 0 | X13: =IFERROR(VLOOKUP($E13&W$6,Base!$M:$Q,5,0),0) -> 0 | AA13: =AE13+AI13+AM13 -> 0 | AB13: =AF13+AJ13+AN13 -> 0 | AC13: =AG13+AK13+AO13 -> 0 | AD13: =AH13+AL13+AP13 -> 0 | AE13: =IFERROR(VLOOKUP($E13&AE$6,Base!$A:$E,5,0),0) -> 0 | AF13: =IFERROR(VLOOKUP($E13&AF$6,Base!$G:$K,5,0),0) -> 0 | AG13: =IFERROR(VLOOKUP($E13&AF$6,Base!$M:$Q,5,0),0) -> 0 | AI13: =IFERROR(VLOOKUP($E13&AI$6,Base!$A:$E,5,0),0) -> 0 | AJ13: =IFERROR(VLOOKUP($E13&AJ$6,Base!$G:$K,5,0),0) -> 0 | AK13: =IFERROR(VLOOKUP($E13&AJ$6,Base!$M:$Q,5,0),0) -> 0 | AL13: 0 | AM13: =IFERROR(VLOOKUP($E13&AM$6,Base!$A:$E,5,0),0) -> 0 | AN13: =IFERROR(VLOOKUP($E13&AN$6,Base!$G:$K,5,0),0) -> 0 | AO13: =IFERROR(VLOOKUP($E13&AN$6,Base!$M:$Q,5,0),0) -> 0 | AR13: =AV13+AZ13+BD13 -> 0 | AS13: =AW13+BA13+BE13 -> 0 | AT13: =AX13+BB13+BF13 -> 0 | AU13: =AY13+BC13+BG13 -> 0 | AV13: =IFERROR(VLOOKUP($E13&AV$6,Base!$A:$E,5,0),0) -> 0 | AW13: =IFERROR(VLOOKUP($E13&AW$6,Base!$G:$K,5,0),0) -> 0 | AX13: =IFERROR(VLOOKUP($E13&AW$6,Base!$M:$Q,5,0),0) -> 0 | AY13: 0 | AZ13: =IFERROR(VLOOKUP($E13&AZ$6,Base!$A:$E,5,0),0) -> 0 | BA13: =IFERROR(VLOOKUP($E13&BA$6,Base!$G:$K,5,0),0) -> 0 | BB13: =IFERROR(VLOOKUP($E13&BA$6,Base!$M:$Q,5,0),0) -> 0 | BC13: 0 | BD13: =IFERROR(VLOOKUP($E13&BD$6,Base!$A:$E,5,0),0) -> 0 | BE13: =IFERROR(VLOOKUP($E13&BE$6,Base!$G:$K,5,0),0) -> 0 | BF13: =IFERROR(VLOOKUP($E13&BE$6,Base!$M:$Q,5,0),0) -> 0 | BG13: 0 | BI13: =BM13+BQ13+BU13 -> 0 | BJ13: =BN13+BR13+BV13 -> 0 | BK13: =BO13+BS13+BW13 -> 0 | BL13: =BP13+BT13+BX13 -> 0 | BM13: =IFERROR(VLOOKUP($E13&BM$6,Base!$A:$E,5,0),0) -> 0 | BN13: =IFERROR(VLOOKUP($E13&BN$6,Base!$G:$K,5,0),0) -> 0 | BO13: =IFERROR(VLOOKUP($E13&BN$6,Base!$M:$Q,5,0),0) -> 0 | BP13: 0 | BQ13: =IFERROR(VLOOKUP($E13&BQ$6,Base!$A:$E,5,0),0) -> 0 | BR13: =IFERROR(VLOOKUP($E13&BR$6,Base!$G:$K,5,0),0) -> 0 | BS13: =IFERROR(VLOOKUP($E13&BR$6,Base!$M:$Q,5,0),0) -> 0 | BT13: 0 | BU13: =IFERROR(VLOOKUP($E13&BU$6,Base!$A:$E,5,0),0) -> 0 | BV13: =IFERROR(VLOOKUP($E13&BV$6,Base!$G:$K,5,0),0) -> 0 | BW13: =IFERROR(VLOOKUP($E13&BV$6,Base!$M:$Q,5,0),0) -> 0 | BX13: =IFERROR(VLOOKUP($E13,Base!$U:$W,3,0),0) -> 0
B14: FLP-SUL MC/KA D | C14: 771 | D14: MC-FLP D | E14: 143128 | F14: 040310260003-10 | G14: HIPER SELECT SUPERMERCADOS LTDA. | H14: REDE HIPER SELECT | I14: ATIVO | J14: =N14+R14+V14 -> 0 | K14: =O14+S14+W14 -> 0 | L14: =P14+T14+X14 -> 0 | M14: =Q14+U14+Y14 -> 0 | N14: =IFERROR(VLOOKUP($E14&N$6,Base!$A:$E,5,0),0) -> 0 | O14: 0 | P14: 0 | R14: =IFERROR(VLOOKUP($E14&R$6,Base!$A:$E,5,0),0) -> 0 | S14: =IFERROR(VLOOKUP($E14&S$6,Base!$G:$K,5,0),0) -> 0 | T14: =IFERROR(VLOOKUP($E14&S$6,Base!$M:$Q,5,0),0) -> 0 | V14: =IFERROR(VLOOKUP($E14&V$6,Base!$A:$E,5,0),0) -> 0 | W14: =IFERROR(VLOOKUP($E14&W$6,Base!$G:$K,5,0),0) -> 0 | X14: =IFERROR(VLOOKUP($E14&W$6,Base!$M:$Q,5,0),0) -> 0 | AA14: =AE14+AI14+AM14 -> 0 | AB14: =AF14+AJ14+AN14 -> 0 | AC14: =AG14+AK14+AO14 -> 0 | AD14: =AH14+AL14+AP14 -> 0 | AE14: =IFERROR(VLOOKUP($E14&AE$6,Base!$A:$E,5,0),0) -> 0 | AF14: =IFERROR(VLOOKUP($E14&AF$6,Base!$G:$K,5,0),0) -> 0 | AG14: =IFERROR(VLOOKUP($E14&AF$6,Base!$M:$Q,5,0),0) -> 0 | AI14: =IFERROR(VLOOKUP($E14&AI$6,Base!$A:$E,5,0),0) -> 0 | AJ14: =IFERROR(VLOOKUP($E14&AJ$6,Base!$G:$K,5,0),0) -> 0 | AK14: =IFERROR(VLOOKUP($E14&AJ$6,Base!$M:$Q,5,0),0) -> 0 | AL14: 0 | AM14: =IFERROR(VLOOKUP($E14&AM$6,Base!$A:$E,5,0),0) -> 0 | AN14: =IFERROR(VLOOKUP($E14&AN$6,Base!$G:$K,5,0),0) -> 0 | AO14: =IFERROR(VLOOKUP($E14&AN$6,Base!$M:$Q,5,0),0) -> 0 | AR14: =AV14+AZ14+BD14 -> 0 | AS14: =AW14+BA14+BE14 -> 0 | AT14: =AX14+BB14+BF14 -> 0 | AU14: =AY14+BC14+BG14 -> 0 | AV14: =IFERROR(VLOOKUP($E14&AV$6,Base!$A:$E,5,0),0) -> 0 | AW14: =IFERROR(VLOOKUP($E14&AW$6,Base!$G:$K,5,0),0) -> 0 | AX14: =IFERROR(VLOOKUP($E14&AW$6,Base!$M:$Q,5,0),0) -> 0 | AY14: 0 | AZ14: =IFERROR(VLOOKUP($E14&AZ$6,Base!$A:$E,5,0),0) -> 0 | BA14: =IFERROR(VLOOKUP($E14&BA$6,Base!$G:$K,5,0),0) -> 0 | BB14: =IFERROR(VLOOKUP($E14&BA$6,Base!$M:$Q,5,0),0) -> 0 | BC14: 0 | BD14: =IFERROR(VLOOKUP($E14&BD$6,Base!$A:$E,5,0),0) -> 0 | BE14: =IFERROR(VLOOKUP($E14&BE$6,Base!$G:$K,5,0),0) -> 0 | BF14: =IFERROR(VLOOKUP($E14&BE$6,Base!$M:$Q,5,0),0) -> 0 | BG14: 0 | BI14: =BM14+BQ14+BU14 -> 0 | BJ14: =BN14+BR14+BV14 -> 0 | BK14: =BO14+BS14+BW14 -> 0 | BL14: =BP14+BT14+BX14 -> 0 | BM14: =IFERROR(VLOOKUP($E14&BM$6,Base!$A:$E,5,0),0) -> 0 | BN14: =IFERROR(VLOOKUP($E14&BN$6,Base!$G:$K,5,0),0) -> 0 | BO14: =IFERROR(VLOOKUP($E14&BN$6,Base!$M:$Q,5,0),0) -> 0 | BP14: 0 | BQ14: =IFERROR(VLOOKUP($E14&BQ$6,Base!$A:$E,5,0),0) -> 0 | BR14: =IFERROR(VLOOKUP($E14&BR$6,Base!$G:$K,5,0),0) -> 0 | BS14: =IFERROR(VLOOKUP($E14&BR$6,Base!$M:$Q,5,0),0) -> 0 | BT14: 0 | BU14: =IFERROR(VLOOKUP($E14&BU$6,Base!$A:$E,5,0),0) -> 0 | BV14: =IFERROR(VLOOKUP($E14&BV$6,Base!$G:$K,5,0),0) -> 0 | BW14: =IFERROR(VLOOKUP($E14&BV$6,Base!$M:$Q,5,0),0) -> 0 | BX14: =IFERROR(VLOOKUP($E14,Base!$U:$W,3,0),0) -> 0
B15: FLP-SUL MC/KA D | C15: 771 | D15: MC-FLP D | E15: 171117 | F15: 040310260006-62 | G15: SUPERMERCADO FELIPE ROYER LTDA | H15: REDE HIPER SELECT | I15: ATIVO | J15: =N15+R15+V15 -> 0 | K15: =O15+S15+W15 -> 0 | L15: =P15+T15+X15 -> 0 | M15: =Q15+U15+Y15 -> 0 | N15: =IFERROR(VLOOKUP($E15&N$6,Base!$A:$E,5,0),0) -> 0 | O15: 0 | P15: 0 | R15: =IFERROR(VLOOKUP($E15&R$6,Base!$A:$E,5,0),0) -> 0 | S15: =IFERROR(VLOOKUP($E15&S$6,Base!$G:$K,5,0),0) -> 0 | T15: =IFERROR(VLOOKUP($E15&S$6,Base!$M:$Q,5,0),0) -> 0 | V15: =IFERROR(VLOOKUP($E15&V$6,Base!$A:$E,5,0),0) -> 0 | W15: =IFERROR(VLOOKUP($E15&W$6,Base!$G:$K,5,0),0) -> 0 | X15: =IFERROR(VLOOKUP($E15&W$6,Base!$M:$Q,5,0),0) -> 0 | AA15: =AE15+AI15+AM15 -> 0 | AB15: =AF15+AJ15+AN15 -> 0 | AC15: =AG15+AK15+AO15 -> 0 | AD15: =AH15+AL15+AP15 -> 0 | AE15: =IFERROR(VLOOKUP($E15&AE$6,Base!$A:$E,5,0),0) -> 0 | AF15: =IFERROR(VLOOKUP($E15&AF$6,Base!$G:$K,5,0),0) -> 0 | AG15: =IFERROR(VLOOKUP($E15&AF$6,Base!$M:$Q,5,0),0) -> 0 | AI15: =IFERROR(VLOOKUP($E15&AI$6,Base!$A:$E,5,0),0) -> 0 | AJ15: =IFERROR(VLOOKUP($E15&AJ$6,Base!$G:$K,5,0),0) -> 0 | AK15: =IFERROR(VLOOKUP($E15&AJ$6,Base!$M:$Q,5,0),0) -> 0 | AL15: 0 | AM15: =IFERROR(VLOOKUP($E15&AM$6,Base!$A:$E,5,0),0) -> 0 | AN15: =IFERROR(VLOOKUP($E15&AN$6,Base!$G:$K,5,0),0) -> 0 | AO15: =IFERROR(VLOOKUP($E15&AN$6,Base!$M:$Q,5,0),0) -> 0 | AR15: =AV15+AZ15+BD15 -> 0 | AS15: =AW15+BA15+BE15 -> 0 | AT15: =AX15+BB15+BF15 -> 0 | AU15: =AY15+BC15+BG15 -> 0 | AV15: =IFERROR(VLOOKUP($E15&AV$6,Base!$A:$E,5,0),0) -> 0 | AW15: =IFERROR(VLOOKUP($E15&AW$6,Base!$G:$K,5,0),0) -> 0 | AX15: =IFERROR(VLOOKUP($E15&AW$6,Base!$M:$Q,5,0),0) -> 0 | AY15: 0 | AZ15: =IFERROR(VLOOKUP($E15&AZ$6,Base!$A:$E,5,0),0) -> 0 | BA15: =IFERROR(VLOOKUP($E15&BA$6,Base!$G:$K,5,0),0) -> 0 | BB15: =IFERROR(VLOOKUP($E15&BA$6,Base!$M:$Q,5,0),0) -> 0 | BC15: 0 | BD15: =IFERROR(VLOOKUP($E15&BD$6,Base!$A:$E,5,0),0) -> 0 | BE15: =IFERROR(VLOOKUP($E15&BE$6,Base!$G:$K,5,0),0) -> 0 | BF15: =IFERROR(VLOOKUP($E15&BE$6,Base!$M:$Q,5,0),0) -> 0 | BG15: 0 | BI15: =BM15+BQ15+BU15 -> 0 | BJ15: =BN15+BR15+BV15 -> 0 | BK15: =BO15+BS15+BW15 -> 0 | BL15: =BP15+BT15+BX15 -> 0 | BM15: =IFERROR(VLOOKUP($E15&BM$6,Base!$A:$E,5,0),0) -> 0 | BN15: =IFERROR(VLOOKUP($E15&BN$6,Base!$G:$K,5,0),0) -> 0 | BO15: =IFERROR(VLOOKUP($E15&BN$6,Base!$M:$Q,5,0),0) -> 0 | BP15: 0 | BQ15: =IFERROR(VLOOKUP($E15&BQ$6,Base!$A:$E,5,0),0) -> 0 | BR15: =IFERROR(VLOOKUP($E15&BR$6,Base!$G:$K,5,0),0) -> 0 | BS15: =IFERROR(VLOOKUP($E15&BR$6,Base!$M:$Q,5,0),0) -> 0 | BT15: 0 | BU15: =IFERROR(VLOOKUP($E15&BU$6,Base!$A:$E,5,0),0) -> 0 | BV15: =IFERROR(VLOOKUP($E15&BV$6,Base!$G:$K,5,0),0) -> 0 | BW15: =IFERROR(VLOOKUP($E15&BV$6,Base!$M:$Q,5,0),0) -> 0 | BX15: =IFERROR(VLOOKUP($E15,Base!$U:$W,3,0),0) -> 0
B16: FLP-SUL MC/KA D | C16: 771 | D16: MC-FLP D | E16: 184604 | F16: 040310260009-05 | G16: HIPER SELECT SUPERMERCADOS LTDA. | H16: REDE HIPER SELECT | I16: ATIVO | J16: =N16+R16+V16 -> 0 | K16: =O16+S16+W16 -> 0 | L16: =P16+T16+X16 -> 0 | M16: =Q16+U16+Y16 -> 0 | N16: =IFERROR(VLOOKUP($E16&N$6,Base!$A:$E,5,0),0) -> 0 | O16: 0 | P16: 0 | R16: =IFERROR(VLOOKUP($E16&R$6,Base!$A:$E,5,0),0) -> 0 | S16: =IFERROR(VLOOKUP($E16&S$6,Base!$G:$K,5,0),0) -> 0 | T16: =IFERROR(VLOOKUP($E16&S$6,Base!$M:$Q,5,0),0) -> 0 | V16: =IFERROR(VLOOKUP($E16&V$6,Base!$A:$E,5,0),0) -> 0 | W16: =IFERROR(VLOOKUP($E16&W$6,Base!$G:$K,5,0),0) -> 0 | X16: =IFERROR(VLOOKUP($E16&W$6,Base!$M:$Q,5,0),0) -> 0 | AA16: =AE16+AI16+AM16 -> 0 | AB16: =AF16+AJ16+AN16 -> 0 | AC16: =AG16+AK16+AO16 -> 0 | AD16: =AH16+AL16+AP16 -> 0 | AE16: =IFERROR(VLOOKUP($E16&AE$6,Base!$A:$E,5,0),0) -> 0 | AF16: =IFERROR(VLOOKUP($E16&AF$6,Base!$G:$K,5,0),0) -> 0 | AG16: =IFERROR(VLOOKUP($E16&AF$6,Base!$M:$Q,5,0),0) -> 0 | AI16: =IFERROR(VLOOKUP($E16&AI$6,Base!$A:$E,5,0),0) -> 0 | AJ16: =IFERROR(VLOOKUP($E16&AJ$6,Base!$G:$K,5,0),0) -> 0 | AK16: =IFERROR(VLOOKUP($E16&AJ$6,Base!$M:$Q,5,0),0) -> 0 | AL16: 0 | AM16: =IFERROR(VLOOKUP($E16&AM$6,Base!$A:$E,5,0),0) -> 0 | AN16: =IFERROR(VLOOKUP($E16&AN$6,Base!$G:$K,5,0),0) -> 0 | AO16: =IFERROR(VLOOKUP($E16&AN$6,Base!$M:$Q,5,0),0) -> 0 | AR16: =AV16+AZ16+BD16 -> 0 | AS16: =AW16+BA16+BE16 -> 0 | AT16: =AX16+BB16+BF16 -> 0 | AU16: =AY16+BC16+BG16 -> 0 | AV16: =IFERROR(VLOOKUP($E16&AV$6,Base!$A:$E,5,0),0) -> 0 | AW16: =IFERROR(VLOOKUP($E16&AW$6,Base!$G:$K,5,0),0) -> 0 | AX16: =IFERROR(VLOOKUP($E16&AW$6,Base!$M:$Q,5,0),0) -> 0 | AY16: 0 | AZ16: =IFERROR(VLOOKUP($E16&AZ$6,Base!$A:$E,5,0),0) -> 0 | BA16: =IFERROR(VLOOKUP($E16&BA$6,Base!$G:$K,5,0),0) -> 0 | BB16: =IFERROR(VLOOKUP($E16&BA$6,Base!$M:$Q,5,0),0) -> 0 | BC16: 0 | BD16: =IFERROR(VLOOKUP($E16&BD$6,Base!$A:$E,5,0),0) -> 0 | BE16: =IFERROR(VLOOKUP($E16&BE$6,Base!$G:$K,5,0),0) -> 0 | BF16: =IFERROR(VLOOKUP($E16&BE$6,Base!$M:$Q,5,0),0) -> 0 | BG16: 0 | BI16: =BM16+BQ16+BU16 -> 0 | BJ16: =BN16+BR16+BV16 -> 0 | BK16: =BO16+BS16+BW16 -> 0 | BL16: =BP16+BT16+BX16 -> 0 | BM16: =IFERROR(VLOOKUP($E16&BM$6,Base!$A:$E,5,0),0) -> 0 | BN16: =IFERROR(VLOOKUP($E16&BN$6,Base!$G:$K,5,0),0) -> 0 | BO16: =IFERROR(VLOOKUP($E16&BN$6,Base!$M:$Q,5,0),0) -> 0 | BP16: 0 | BQ16: =IFERROR(VLOOKUP($E16&BQ$6,Base!$A:$E,5,0),0) -> 0 | BR16: =IFERROR(VLOOKUP($E16&BR$6,Base!$G:$K,5,0),0) -> 0 | BS16: =IFERROR(VLOOKUP($E16&BR$6,Base!$M:$Q,5,0),0) -> 0 | BT16: 0 | BU16: =IFERROR(VLOOKUP($E16&BU$6,Base!$A:$E,5,0),0) -> 0 | BV16: =IFERROR(VLOOKUP($E16&BV$6,Base!$G:$K,5,0),0) -> 0 | BW16: =IFERROR(VLOOKUP($E16&BV$6,Base!$M:$Q,5,0),0) -> 0 | BX16: =IFERROR(VLOOKUP($E16,Base!$U:$W,3,0),0) -> 0
B17: FLP-SUL MC/KA D | C17: 771 | D17: MC-FLP D | E17: 185710 | F17: 040310260008-24 | G17: HIPER SELECT SUPERMERCADOS LTDA | H17: REDE HIPER SELECT | I17: ATIVO | J17: =N17+R17+V17 -> 0 | K17: =O17+S17+W17 -> 0 | L17: =P17+T17+X17 -> 0 | M17: =Q17+U17+Y17 -> 0 | N17: =IFERROR(VLOOKUP($E17&N$6,Base!$A:$E,5,0),0) -> 0 | O17: 0 | P17: 0 | R17: =IFERROR(VLOOKUP($E17&R$6,Base!$A:$E,5,0),0) -> 0 | S17: =IFERROR(VLOOKUP($E17&S$6,Base!$G:$K,5,0),0) -> 0 | T17: =IFERROR(VLOOKUP($E17&S$6,Base!$M:$Q,5,0),0) -> 0 | V17: =IFERROR(VLOOKUP($E17&V$6,Base!$A:$E,5,0),0) -> 0 | W17: =IFERROR(VLOOKUP($E17&W$6,Base!$G:$K,5,0),0) -> 0 | X17: =IFERROR(VLOOKUP($E17&W$6,Base!$M:$Q,5,0),0) -> 0 | AA17: =AE17+AI17+AM17 -> 0 | AB17: =AF17+AJ17+AN17 -> 0 | AC17: =AG17+AK17+AO17 -> 0 | AD17: =AH17+AL17+AP17 -> 0 | AE17: =IFERROR(VLOOKUP($E17&AE$6,Base!$A:$E,5,0),0) -> 0 | AF17: =IFERROR(VLOOKUP($E17&AF$6,Base!$G:$K,5,0),0) -> 0 | AG17: =IFERROR(VLOOKUP($E17&AF$6,Base!$M:$Q,5,0),0) -> 0 | AI17: =IFERROR(VLOOKUP($E17&AI$6,Base!$A:$E,5,0),0) -> 0 | AJ17: =IFERROR(VLOOKUP($E17&AJ$6,Base!$G:$K,5,0),0) -> 0 | AK17: =IFERROR(VLOOKUP($E17&AJ$6,Base!$M:$Q,5,0),0) -> 0 | AL17: 0 | AM17: =IFERROR(VLOOKUP($E17&AM$6,Base!$A:$E,5,0),0) -> 0 | AN17: =IFERROR(VLOOKUP($E17&AN$6,Base!$G:$K,5,0),0) -> 0 | AO17: =IFERROR(VLOOKUP($E17&AN$6,Base!$M:$Q,5,0),0) -> 0 | AR17: =AV17+AZ17+BD17 -> 0 | AS17: =AW17+BA17+BE17 -> 0 | AT17: =AX17+BB17+BF17 -> 0 | AU17: =AY17+BC17+BG17 -> 0 | AV17: =IFERROR(VLOOKUP($E17&AV$6,Base!$A:$E,5,0),0) -> 0 | AW17: =IFERROR(VLOOKUP($E17&AW$6,Base!$G:$K,5,0),0) -> 0 | AX17: =IFERROR(VLOOKUP($E17&AW$6,Base!$M:$Q,5,0),0) -> 0 | AY17: 0 | AZ17: =IFERROR(VLOOKUP($E17&AZ$6,Base!$A:$E,5,0),0) -> 0 | BA17: =IFERROR(VLOOKUP($E17&BA$6,Base!$G:$K,5,0),0) -> 0 | BB17: =IFERROR(VLOOKUP($E17&BA$6,Base!$M:$Q,5,0),0) -> 0 | BC17: 0 | BD17: =IFERROR(VLOOKUP($E17&BD$6,Base!$A:$E,5,0),0) -> 0 | BE17: =IFERROR(VLOOKUP($E17&BE$6,Base!$G:$K,5,0),0) -> 0 | BF17: =IFERROR(VLOOKUP($E17&BE$6,Base!$M:$Q,5,0),0) -> 0 | BG17: 0 | BI17: =BM17+BQ17+BU17 -> 0 | BJ17: =BN17+BR17+BV17 -> 0 | BK17: =BO17+BS17+BW17 -> 0 | BL17: =BP17+BT17+BX17 -> 0 | BM17: =IFERROR(VLOOKUP($E17&BM$6,Base!$A:$E,5,0),0) -> 0 | BN17: =IFERROR(VLOOKUP($E17&BN$6,Base!$G:$K,5,0),0) -> 0 | BO17: =IFERROR(VLOOKUP($E17&BN$6,Base!$M:$Q,5,0),0) -> 0 | BP17: 0 | BQ17: =IFERROR(VLOOKUP($E17&BQ$6,Base!$A:$E,5,0),0) -> 0 | BR17: =IFERROR(VLOOKUP($E17&BR$6,Base!$G:$K,5,0),0) -> 0 | BS17: =IFERROR(VLOOKUP($E17&BR$6,Base!$M:$Q,5,0),0) -> 0 | BT17: 0 | BU17: =IFERROR(VLOOKUP($E17&BU$6,Base!$A:$E,5,0),0) -> 0 | BV17: =IFERROR(VLOOKUP($E17&BV$6,Base!$G:$K,5,0),0) -> 0 | BW17: =IFERROR(VLOOKUP($E17&BV$6,Base!$M:$Q,5,0),0) -> 0 | BX17: =IFERROR(VLOOKUP($E17,Base!$U:$W,3,0),0) -> 0
B18: FLP-SUL MC/KA D | C18: 771 | D18: MC-FLP D | E18: 185711 | F18: 040310260010-49 | G18: HIPER SELECT SUPERMERCADOS LTDA | H18: REDE HIPER SELECT | I18: ATIVO | J18: =N18+R18+V18 -> 0 | K18: =O18+S18+W18 -> 0 | L18: =P18+T18+X18 -> 0 | M18: =Q18+U18+Y18 -> 0 | N18: =IFERROR(VLOOKUP($E18&N$6,Base!$A:$E,5,0),0) -> 0 | O18: 0 | P18: 0 | R18: =IFERROR(VLOOKUP($E18&R$6,Base!$A:$E,5,0),0) -> 0 | S18: =IFERROR(VLOOKUP($E18&S$6,Base!$G:$K,5,0),0) -> 0 | T18: =IFERROR(VLOOKUP($E18&S$6,Base!$M:$Q,5,0),0) -> 0 | V18: =IFERROR(VLOOKUP($E18&V$6,Base!$A:$E,5,0),0) -> 0 | W18: =IFERROR(VLOOKUP($E18&W$6,Base!$G:$K,5,0),0) -> 0 | X18: =IFERROR(VLOOKUP($E18&W$6,Base!$M:$Q,5,0),0) -> 0 | AA18: =AE18+AI18+AM18 -> 0 | AB18: =AF18+AJ18+AN18 -> 0 | AC18: =AG18+AK18+AO18 -> 0 | AD18: =AH18+AL18+AP18 -> 0 | AE18: =IFERROR(VLOOKUP($E18&AE$6,Base!$A:$E,5,0),0) -> 0 | AF18: =IFERROR(VLOOKUP($E18&AF$6,Base!$G:$K,5,0),0) -> 0 | AG18: =IFERROR(VLOOKUP($E18&AF$6,Base!$M:$Q,5,0),0) -> 0 | AI18: =IFERROR(VLOOKUP($E18&AI$6,Base!$A:$E,5,0),0) -> 0 | AJ18: =IFERROR(VLOOKUP($E18&AJ$6,Base!$G:$K,5,0),0) -> 0 | AK18: =IFERROR(VLOOKUP($E18&AJ$6,Base!$M:$Q,5,0),0) -> 0 | AL18: 0 | AM18: =IFERROR(VLOOKUP($E18&AM$6,Base!$A:$E,5,0),0) -> 0 | AN18: =IFERROR(VLOOKUP($E18&AN$6,Base!$G:$K,5,0),0) -> 0 | AO18: =IFERROR(VLOOKUP($E18&AN$6,Base!$M:$Q,5,0),0) -> 0 | AR18: =AV18+AZ18+BD18 -> 0 | AS18: =AW18+BA18+BE18 -> 0 | AT18: =AX18+BB18+BF18 -> 0 | AU18: =AY18+BC18+BG18 -> 0 | AV18: =IFERROR(VLOOKUP($E18&AV$6,Base!$A:$E,5,0),0) -> 0 | AW18: =IFERROR(VLOOKUP($E18&AW$6,Base!$G:$K,5,0),0) -> 0 | AX18: =IFERROR(VLOOKUP($E18&AW$6,Base!$M:$Q,5,0),0) -> 0 | AY18: 0 | AZ18: =IFERROR(VLOOKUP($E18&AZ$6,Base!$A:$E,5,0),0) -> 0 | BA18: =IFERROR(VLOOKUP($E18&BA$6,Base!$G:$K,5,0),0) -> 0 | BB18: =IFERROR(VLOOKUP($E18&BA$6,Base!$M:$Q,5,0),0) -> 0 | BC18: 0 | BD18: =IFERROR(VLOOKUP($E18&BD$6,Base!$A:$E,5,0),0) -> 0 | BE18: =IFERROR(VLOOKUP($E18&BE$6,Base!$G:$K,5,0),0) -> 0 | BF18: =IFERROR(VLOOKUP($E18&BE$6,Base!$M:$Q,5,0),0) -> 0 | BG18: 0 | BI18: =BM18+BQ18+BU18 -> 0 | BJ18: =BN18+BR18+BV18 -> 0 | BK18: =BO18+BS18+BW18 -> 0 | BL18: =BP18+BT18+BX18 -> 0 | BM18: =IFERROR(VLOOKUP($E18&BM$6,Base!$A:$E,5,0),0) -> 0 | BN18: =IFERROR(VLOOKUP($E18&BN$6,Base!$G:$K,5,0),0) -> 0 | BO18: =IFERROR(VLOOKUP($E18&BN$6,Base!$M:$Q,5,0),0) -> 0 | BP18: 0 | BQ18: =IFERROR(VLOOKUP($E18&BQ$6,Base!$A:$E,5,0),0) -> 0 | BR18: =IFERROR(VLOOKUP($E18&BR$6,Base!$G:$K,5,0),0) -> 0 | BS18: =IFERROR(VLOOKUP($E18&BR$6,Base!$M:$Q,5,0),0) -> 0 | BT18: 0 | BU18: =IFERROR(VLOOKUP($E18&BU$6,Base!$A:$E,5,0),0) -> 0 | BV18: =IFERROR(VLOOKUP($E18&BV$6,Base!$G:$K,5,0),0) -> 0 | BW18: =IFERROR(VLOOKUP($E18&BV$6,Base!$M:$Q,5,0),0) -> 0 | BX18: =IFERROR(VLOOKUP($E18,Base!$U:$W,3,0),0) -> 0
B19: FLP-SUL MC/KA D | C19: 771 | D19: MC-FLP D | E19: 185712 | F19: 040310260011-20 | G19: HIPER SELECT SUPERMERCADOS LTDA | H19: REDE HIPER SELECT | I19: ATIVO | J19: =N19+R19+V19 -> 0 | K19: =O19+S19+W19 -> 0 | L19: =P19+T19+X19 -> 0 | M19: =Q19+U19+Y19 -> 0 | N19: =IFERROR(VLOOKUP($E19&N$6,Base!$A:$E,5,0),0) -> 0 | O19: 0 | P19: 0 | R19: =IFERROR(VLOOKUP($E19&R$6,Base!$A:$E,5,0),0) -> 0 | S19: =IFERROR(VLOOKUP($E19&S$6,Base!$G:$K,5,0),0) -> 0 | T19: =IFERROR(VLOOKUP($E19&S$6,Base!$M:$Q,5,0),0) -> 0 | V19: =IFERROR(VLOOKUP($E19&V$6,Base!$A:$E,5,0),0) -> 0 | W19: =IFERROR(VLOOKUP($E19&W$6,Base!$G:$K,5,0),0) -> 0 | X19: =IFERROR(VLOOKUP($E19&W$6,Base!$M:$Q,5,0),0) -> 0 | AA19: =AE19+AI19+AM19 -> 0 | AB19: =AF19+AJ19+AN19 -> 0 | AC19: =AG19+AK19+AO19 -> 0 | AD19: =AH19+AL19+AP19 -> 0 | AE19: =IFERROR(VLOOKUP($E19&AE$6,Base!$A:$E,5,0),0) -> 0 | AF19: =IFERROR(VLOOKUP($E19&AF$6,Base!$G:$K,5,0),0) -> 0 | AG19: =IFERROR(VLOOKUP($E19&AF$6,Base!$M:$Q,5,0),0) -> 0 | AI19: =IFERROR(VLOOKUP($E19&AI$6,Base!$A:$E,5,0),0) -> 0 | AJ19: =IFERROR(VLOOKUP($E19&AJ$6,Base!$G:$K,5,0),0) -> 0 | AK19: =IFERROR(VLOOKUP($E19&AJ$6,Base!$M:$Q,5,0),0) -> 0 | AL19: 0 | AM19: =IFERROR(VLOOKUP($E19&AM$6,Base!$A:$E,5,0),0) -> 0 | AN19: =IFERROR(VLOOKUP($E19&AN$6,Base!$G:$K,5,0),0) -> 0 | AO19: =IFERROR(VLOOKUP($E19&AN$6,Base!$M:$Q,5,0),0) -> 0 | AR19: =AV19+AZ19+BD19 -> 0 | AS19: =AW19+BA19+BE19 -> 0 | AT19: =AX19+BB19+BF19 -> 0 | AU19: =AY19+BC19+BG19 -> 0 | AV19: =IFERROR(VLOOKUP($E19&AV$6,Base!$A:$E,5,0),0) -> 0 | AW19: =IFERROR(VLOOKUP($E19&AW$6,Base!$G:$K,5,0),0) -> 0 | AX19: =IFERROR(VLOOKUP($E19&AW$6,Base!$M:$Q,5,0),0) -> 0 | AY19: 0 | AZ19: =IFERROR(VLOOKUP($E19&AZ$6,Base!$A:$E,5,0),0) -> 0 | BA19: =IFERROR(VLOOKUP($E19&BA$6,Base!$G:$K,5,0),0) -> 0 | BB19: =IFERROR(VLOOKUP($E19&BA$6,Base!$M:$Q,5,0),0) -> 0 | BC19: 0 | BD19: =IFERROR(VLOOKUP($E19&BD$6,Base!$A:$E,5,0),0) -> 0 | BE19: =IFERROR(VLOOKUP($E19&BE$6,Base!$G:$K,5,0),0) -> 0 | BF19: =IFERROR(VLOOKUP($E19&BE$6,Base!$M:$Q,5,0),0) -> 0 | BG19: 0 | BI19: =BM19+BQ19+BU19 -> 0 | BJ19: =BN19+BR19+BV19 -> 0 | BK19: =BO19+BS19+BW19 -> 0 | BL19: =BP19+BT19+BX19 -> 0 | BM19: =IFERROR(VLOOKUP($E19&BM$6,Base!$A:$E,5,0),0) -> 0 | BN19: =IFERROR(VLOOKUP($E19&BN$6,Base!$G:$K,5,0),0) -> 0 | BO19: =IFERROR(VLOOKUP($E19&BN$6,Base!$M:$Q,5,0),0) -> 0 | BP19: 0 | BQ19: =IFERROR(VLOOKUP($E19&BQ$6,Base!$A:$E,5,0),0) -> 0 | BR19: =IFERROR(VLOOKUP($E19&BR$6,Base!$G:$K,5,0),0) -> 0 | BS19: =IFERROR(VLOOKUP($E19&BR$6,Base!$M:$Q,5,0),0) -> 0 | BT19: 0 | BU19: =IFERROR(VLOOKUP($E19&BU$6,Base!$A:$E,5,0),0) -> 0 | BV19: =IFERROR(VLOOKUP($E19&BV$6,Base!$G:$K,5,0),0) -> 0 | BW19: =IFERROR(VLOOKUP($E19&BV$6,Base!$M:$Q,5,0),0) -> 0 | BX19: =IFERROR(VLOOKUP($E19,Base!$U:$W,3,0),0) -> 0
B20: FLP-SUL MC/KA D | C20: 771 | D20: MC-FLP D | E20: 185713 | F20: 040310260012-00 | G20: HIPER SELECT SUPERMERCADOS LTDA | H20: REDE HIPER SELECT | I20: ATIVO | J20: =N20+R20+V20 -> 0 | K20: =O20+S20+W20 -> 0 | L20: =P20+T20+X20 -> 0 | M20: =Q20+U20+Y20 -> 0 | N20: =IFERROR(VLOOKUP($E20&N$6,Base!$A:$E,5,0),0) -> 0 | O20: 0 | P20: 0 | R20: =IFERROR(VLOOKUP($E20&R$6,Base!$A:$E,5,0),0) -> 0 | S20: =IFERROR(VLOOKUP($E20&S$6,Base!$G:$K,5,0),0) -> 0 | T20: =IFERROR(VLOOKUP($E20&S$6,Base!$M:$Q,5,0),0) -> 0 | V20: =IFERROR(VLOOKUP($E20&V$6,Base!$A:$E,5,0),0) -> 0 | W20: =IFERROR(VLOOKUP($E20&W$6,Base!$G:$K,5,0),0) -> 0 | X20: =IFERROR(VLOOKUP($E20&W$6,Base!$M:$Q,5,0),0) -> 0 | AA20: =AE20+AI20+AM20 -> 0 | AB20: =AF20+AJ20+AN20 -> 0 | AC20: =AG20+AK20+AO20 -> 0 | AD20: =AH20+AL20+AP20 -> 0 | AE20: =IFERROR(VLOOKUP($E20&AE$6,Base!$A:$E,5,0),0) -> 0 | AF20: =IFERROR(VLOOKUP($E20&AF$6,Base!$G:$K,5,0),0) -> 0 | AG20: =IFERROR(VLOOKUP($E20&AF$6,Base!$M:$Q,5,0),0) -> 0 | AI20: =IFERROR(VLOOKUP($E20&AI$6,Base!$A:$E,5,0),0) -> 0 | AJ20: =IFERROR(VLOOKUP($E20&AJ$6,Base!$G:$K,5,0),0) -> 0 | AK20: =IFERROR(VLOOKUP($E20&AJ$6,Base!$M:$Q,5,0),0) -> 0 | AL20: 0 | AM20: =IFERROR(VLOOKUP($E20&AM$6,Base!$A:$E,5,0),0) -> 0 | AN20: =IFERROR(VLOOKUP($E20&AN$6,Base!$G:$K,5,0),0) -> 0 | AO20: =IFERROR(VLOOKUP($E20&AN$6,Base!$M:$Q,5,0),0) -> 0 | AR20: =AV20+AZ20+BD20 -> 0 | AS20: =AW20+BA20+BE20 -> 0 | AT20: =AX20+BB20+BF20 -> 0 | AU20: =AY20+BC20+BG20 -> 0 | AV20: =IFERROR(VLOOKUP($E20&AV$6,Base!$A:$E,5,0),0) -> 0 | AW20: =IFERROR(VLOOKUP($E20&AW$6,Base!$G:$K,5,0),0) -> 0 | AX20: =IFERROR(VLOOKUP($E20&AW$6,Base!$M:$Q,5,0),0) -> 0 | AY20: 0 | AZ20: =IFERROR(VLOOKUP($E20&AZ$6,Base!$A:$E,5,0),0) -> 0 | BA20: =IFERROR(VLOOKUP($E20&BA$6,Base!$G:$K,5,0),0) -> 0 | BB20: =IFERROR(VLOOKUP($E20&BA$6,Base!$M:$Q,5,0),0) -> 0 | BC20: 0 | BD20: =IFERROR(VLOOKUP($E20&BD$6,Base!$A:$E,5,0),0) -> 0 | BE20: =IFERROR(VLOOKUP($E20&BE$6,Base!$G:$K,5,0),0) -> 0 | BF20: =IFERROR(VLOOKUP($E20&BE$6,Base!$M:$Q,5,0),0) -> 0 | BG20: 0 | BI20: =BM20+BQ20+BU20 -> 0 | BJ20: =BN20+BR20+BV20 -> 0 | BK20: =BO20+BS20+BW20 -> 0 | BL20: =BP20+BT20+BX20 -> 0 | BM20: =IFERROR(VLOOKUP($E20&BM$6,Base!$A:$E,5,0),0) -> 0 | BN20: =IFERROR(VLOOKUP($E20&BN$6,Base!$G:$K,5,0),0) -> 0 | BO20: =IFERROR(VLOOKUP($E20&BN$6,Base!$M:$Q,5,0),0) -> 0 | BP20: 0 | BQ20: =IFERROR(VLOOKUP($E20&BQ$6,Base!$A:$E,5,0),0) -> 0 | BR20: =IFERROR(VLOOKUP($E20&BR$6,Base!$G:$K,5,0),0) -> 0 | BS20: =IFERROR(VLOOKUP($E20&BR$6,Base!$M:$Q,5,0),0) -> 0 | BT20: 0 | BU20: =IFERROR(VLOOKUP($E20&BU$6,Base!$A:$E,5,0),0) -> 0 | BV20: =IFERROR(VLOOKUP($E20&BV$6,Base!$G:$K,5,0),0) -> 0 | BW20: =IFERROR(VLOOKUP($E20&BV$6,Base!$M:$Q,5,0),0) -> 0 | BX20: =IFERROR(VLOOKUP($E20,Base!$U:$W,3,0),0) -> 0
B21: FLP-SUL MC/KA D | C21: 771 | D21: MC-FLP D | E21: 185714 | F21: 040310260013-91 | G21: HIPER SELECT SUPERMERCADOS LTDA | H21: REDE HIPER SELECT | I21: ATIVO | J21: =N21+R21+V21 -> 0 | K21: =O21+S21+W21 -> 0 | L21: =P21+T21+X21 -> 0 | M21: =Q21+U21+Y21 -> 0 | N21: =IFERROR(VLOOKUP($E21&N$6,Base!$A:$E,5,0),0) -> 0 | O21: 0 | P21: 0 | R21: =IFERROR(VLOOKUP($E21&R$6,Base!$A:$E,5,0),0) -> 0 | S21: =IFERROR(VLOOKUP($E21&S$6,Base!$G:$K,5,0),0) -> 0 | T21: =IFERROR(VLOOKUP($E21&S$6,Base!$M:$Q,5,0),0) -> 0 | V21: =IFERROR(VLOOKUP($E21&V$6,Base!$A:$E,5,0),0) -> 0 | W21: =IFERROR(VLOOKUP($E21&W$6,Base!$G:$K,5,0),0) -> 0 | X21: =IFERROR(VLOOKUP($E21&W$6,Base!$M:$Q,5,0),0) -> 0 | AA21: =AE21+AI21+AM21 -> 0 | AB21: =AF21+AJ21+AN21 -> 0 | AC21: =AG21+AK21+AO21 -> 0 | AD21: =AH21+AL21+AP21 -> 0 | AE21: =IFERROR(VLOOKUP($E21&AE$6,Base!$A:$E,5,0),0) -> 0 | AF21: =IFERROR(VLOOKUP($E21&AF$6,Base!$G:$K,5,0),0) -> 0 | AG21: =IFERROR(VLOOKUP($E21&AF$6,Base!$M:$Q,5,0),0) -> 0 | AI21: =IFERROR(VLOOKUP($E21&AI$6,Base!$A:$E,5,0),0) -> 0 | AJ21: =IFERROR(VLOOKUP($E21&AJ$6,Base!$G:$K,5,0),0) -> 0 | AK21: =IFERROR(VLOOKUP($E21&AJ$6,Base!$M:$Q,5,0),0) -> 0 | AL21: 0 | AM21: =IFERROR(VLOOKUP($E21&AM$6,Base!$A:$E,5,0),0) -> 0 | AN21: =IFERROR(VLOOKUP($E21&AN$6,Base!$G:$K,5,0),0) -> 0 | AO21: =IFERROR(VLOOKUP($E21&AN$6,Base!$M:$Q,5,0),0) -> 0 | AR21: =AV21+AZ21+BD21 -> 0 | AS21: =AW21+BA21+BE21 -> 0 | AT21: =AX21+BB21+BF21 -> 0 | AU21: =AY21+BC21+BG21 -> 0 | AV21: =IFERROR(VLOOKUP($E21&AV$6,Base!$A:$E,5,0),0) -> 0 | AW21: =IFERROR(VLOOKUP($E21&AW$6,Base!$G:$K,5,0),0) -> 0 | AX21: =IFERROR(VLOOKUP($E21&AW$6,Base!$M:$Q,5,0),0) -> 0 | AY21: 0 | AZ21: =IFERROR(VLOOKUP($E21&AZ$6,Base!$A:$E,5,0),0) -> 0 | BA21: =IFERROR(VLOOKUP($E21&BA$6,Base!$G:$K,5,0),0) -> 0 | BB21: =IFERROR(VLOOKUP($E21&BA$6,Base!$M:$Q,5,0),0) -> 0 | BC21: 0 | BD21: =IFERROR(VLOOKUP($E21&BD$6,Base!$A:$E,5,0),0) -> 0 | BE21: =IFERROR(VLOOKUP($E21&BE$6,Base!$G:$K,5,0),0) -> 0 | BF21: =IFERROR(VLOOKUP($E21&BE$6,Base!$M:$Q,5,0),0) -> 0 | BG21: 0 | BI21: =BM21+BQ21+BU21 -> 0 | BJ21: =BN21+BR21+BV21 -> 0 | BK21: =BO21+BS21+BW21 -> 0 | BL21: =BP21+BT21+BX21 -> 0 | BM21: =IFERROR(VLOOKUP($E21&BM$6,Base!$A:$E,5,0),0) -> 0 | BN21: =IFERROR(VLOOKUP($E21&BN$6,Base!$G:$K,5,0),0) -> 0 | BO21: =IFERROR(VLOOKUP($E21&BN$6,Base!$M:$Q,5,0),0) -> 0 | BP21: 0 | BQ21: =IFERROR(VLOOKUP($E21&BQ$6,Base!$A:$E,5,0),0) -> 0 | BR21: =IFERROR(VLOOKUP($E21&BR$6,Base!$G:$K,5,0),0) -> 0 | BS21: =IFERROR(VLOOKUP($E21&BR$6,Base!$M:$Q,5,0),0) -> 0 | BT21: 0 | BU21: =IFERROR(VLOOKUP($E21&BU$6,Base!$A:$E,5,0),0) -> 0 | BV21: =IFERROR(VLOOKUP($E21&BV$6,Base!$G:$K,5,0),0) -> 0 | BW21: =IFERROR(VLOOKUP($E21&BV$6,Base!$M:$Q,5,0),0) -> 0 | BX21: =IFERROR(VLOOKUP($E21,Base!$U:$W,3,0),0) -> 0
... B107: NORTE MC/KA D | C107: 3655 | D107: KA-BNU | E107: 189159 | F107: 188036540007-04 | G107: GTOP DISTRIBUICAO LTDA | H107: REDE TOP | I107: ATIVO | J107: =N107+R107+V107 -> 0 | K107: =O107+S107+W107 -> 0 | L107: =P107+T107+X107 -> 0 | M107: =Q107+U107+Y107 -> 0 | N107: =IFERROR(VLOOKUP($E107&N$6,Base!$A:$E,5,0),0) -> 0 | O107: 0 | P107: 0 | R107: =IFERROR(VLOOKUP($E107&R$6,Base!$A:$E,5,0),0) -> 0 | S107: =IFERROR(VLOOKUP($E107&S$6,Base!$G:$K,5,0),0) -> 0 | T107: =IFERROR(VLOOKUP($E107&S$6,Base!$M:$Q,5,0),0) -> 0 | V107: =IFERROR(VLOOKUP($E107&V$6,Base!$A:$E,5,0),0) -> 0 | W107: =IFERROR(VLOOKUP($E107&W$6,Base!$G:$K,5,0),0) -> 0 | X107: =IFERROR(VLOOKUP($E107&W$6,Base!$M:$Q,5,0),0) -> 0 | AA107: =AE107+AI107+AM107 -> 0 | AB107: =AF107+AJ107+AN107 -> 0 | AC107: =AG107+AK107+AO107 -> 0 | AD107: =AH107+AL107+AP107 -> 0 | AE107: =IFERROR(VLOOKUP($E107&AE$6,Base!$A:$E,5,0),0) -> 0 | AF107: =IFERROR(VLOOKUP($E107&AF$6,Base!$G:$K,5,0),0) -> 0 | AG107: =IFERROR(VLOOKUP($E107&AF$6,Base!$M:$Q,5,0),0) -> 0 | AI107: =IFERROR(VLOOKUP($E107&AI$6,Base!$A:$E,5,0),0) -> 0 | AJ107: =IFERROR(VLOOKUP($E107&AJ$6,Base!$G:$K,5,0),0) -> 0 | AK107: =IFERROR(VLOOKUP($E107&AJ$6,Base!$M:$Q,5,0),0) -> 0 | AL107: 0 | AM107: =IFERROR(VLOOKUP($E107&AM$6,Base!$A:$E,5,0),0) -> 0 | AN107: =IFERROR(VLOOKUP($E107&AN$6,Base!$G:$K,5,0),0) -> 0 | AO107: =IFERROR(VLOOKUP($E107&AN$6,Base!$M:$Q,5,0),0) -> 0 | AR107: =AV107+AZ107+BD107 -> 0 | AS107: =AW107+BA107+BE107 -> 0 | AT107: =AX107+BB107+BF107 -> 0 | AU107: =AY107+BC107+BG107 -> 0 | AV107: =IFERROR(VLOOKUP($E107&AV$6,Base!$A:$E,5,0),0) -> 0 | AW107: =IFERROR(VLOOKUP($E107&AW$6,Base!$G:$K,5,0),0) -> 0 | AX107: =IFERROR(VLOOKUP($E107&AW$6,Base!$M:$Q,5,0),0) -> 0 | AY107: 0 | AZ107: =IFERROR(VLOOKUP($E107&AZ$6,Base!$A:$E,5,0),0) -> 0 | BA107: =IFERROR(VLOOKUP($E107&BA$6,Base!$G:$K,5,0),0) -> 0 | BB107: =IFERROR(VLOOKUP($E107&BA$6,Base!$M:$Q,5,0),0) -> 0 | BC107: 0 | BD107: =IFERROR(VLOOKUP($E107&BD$6,Base!$A:$E,5,0),0) -> 0 | BE107: =IFERROR(VLOOKUP($E107&BE$6,Base!$G:$K,5,0),0) -> 0 | BF107: =IFERROR(VLOOKUP($E107&BE$6,Base!$M:$Q,5,0),0) -> 0 | BG107: 0 | BI107: =BM107+BQ107+BU107 -> 0 | BJ107: =BN107+BR107+BV107 -> 6.5 | BK107: =BO107+BS107+BW107 -> 0 | BL107: =BP107+BT107+BX107 -> 0 | BM107: =IFERROR(VLOOKUP($E107&BM$6,Base!$A:$E,5,0),0) -> 0 | BN107: =IFERROR(VLOOKUP($E107&BN$6,Base!$G:$K,5,0),0) -> 6.5 | BO107: =IFERROR(VLOOKUP($E107&BN$6,Base!$M:$Q,5,0),0) -> 0 | BP107: 0 | BQ107: =IFERROR(VLOOKUP($E107&BQ$6,Base!$A:$E,5,0),0) -> 0 | BR107: =IFERROR(VLOOKUP($E107&BR$6,Base!$G:$K,5,0),0) -> 0 | BS107: =IFERROR(VLOOKUP($E107&BR$6,Base!$M:$Q,5,0),0) -> 0 | BT107: 0 | BU107: =IFERROR(VLOOKUP($E107&BU$6,Base!$A:$E,5,0),0) -> 0 | BV107: =IFERROR(VLOOKUP($E107&BV$6,Base!$G:$K,5,0),0) -> 0 | BW107: =IFERROR(VLOOKUP($E107&BV$6,Base!$M:$Q,5,0),0) -> 0 | BX107: =IFERROR(VLOOKUP($E107,Base!$U:$W,3,0),0) -> 0

Sheet Metas
H1: 2025 | S1: 2026
B2: Nome da Rede | C2: JUL | D2: AGO | E2: SET | F2: OUT | G2: NOV | H2: DEZ | I2: JAN | J2: FEV | K2: MAR | L2: ABR | M2: MAI | N2: JUN | O2: FY25 | Q2: Q1 | R2: Q2 | S2: Q3 | T2: Q4 | U2: FY26 | V2: CLASSIFICAÇÃO
B3: REDE HIPER SELECT | C3: =SUMIF('Top Contas 04.07'!$K:$K,Metas!$B3,'Top Contas 04.07'!M:M) -> 270.844 | D3: =SUMIF('Top Contas 04.07'!$K:$K,Metas!$B3,'Top Contas 04.07'!N:N) -> 854.558 | E3: =SUMIF('Top Contas 04.07'!$K:$K,Metas!$B3,'Top Contas 04.07'!O:O) -> 525.542 | F3: =SUMIF('Top Contas 04.07'!$K:$K,Metas!$B3,'Top Contas 04.07'!P:P) -> 814.133 | G3: =SUMIF('Top Contas 04.07'!$K:$K,Metas!$B3,'Top Contas 04.07'!Q:Q) -> 111.858 | H3: =SUMIF('Top Contas 04.07'!$K:$K,Metas!$B3,'Top Contas 04.07'!R:R) -> 142.375 | I3: =SUMIF('Top Contas 04.07'!$K:$K,Metas!$B3,'Top Contas 04.07'!S:S) -> 286.55 | J3: =SUMIF('Top Contas 04.07'!$K:$K,Metas!$B3,'Top Contas 04.07'!T:T) -> 82.959 | K3: =SUMIF('Top Contas 04.07'!$K:$K,Metas!$B3,'Top Contas 04.07'!U:U) -> 86.083 | L3: =SUMIF('Top Contas 04.07'!$K:$K,Metas!$B3,'Top Contas 04.07'!V:V) -> 24.083 | M3: =SUMIF('Top Contas 04.07'!$K:$K,Metas!$B3,'Top Contas 04.07'!W:W) -> 59.867 | N3: =SUMIF('Top Contas 04.07'!$K:$K,Metas!$B3,'Top Contas 04.07'!X:X) -> 67.655 | O3: =SUM(C3:N3) -> 3326.507 | Q3: 898.53 | R3: 770.16614 | S3: 724.36074 | T3: 771 | U3: 3492.3862 | V3: =IF(AVERAGE(C3,D3,E3,F3,G3,H3,I3,J3,K3,L3,M3,N3)>=500,"Diamante","Estrela") -> Estrela
B4: REDE SM ROSSO | C4: =SUMIF('Top Contas 04.07'!$K:$K,Metas!$B4,'Top Contas 04.07'!M:M) -> -1 | D4: =SUMIF('Top Contas 04.07'!$K:$K,Metas!$B4,'Top Contas 04.07'!N:N) -> 84 | E4: =SUMIF('Top Contas 04.07'!$K:$K,Metas!$B4,'Top Contas 04.07'!O:O) -> -0.083 | F4: =SUMIF('Top Contas 04.07'!$K:$K,Metas!$B4,'Top Contas 04.07'!P:P) -> 1136.604 | G4: =SUMIF('Top Contas 04.07'!$K:$K,Metas!$B4,'Top Contas 04.07'!Q:Q) -> 60.75 | H4: =SUMIF('Top Contas 04.07'!$K:$K,Metas!$B4,'Top Contas 04.07'!R:R) -> 9 | I4: =SUMIF('Top Contas 04.07'!$K:$K,Metas!$B4,'Top Contas 04.07'!S:S) -> 211 | J4: =SUMIF('Top Contas 04.07'!$K:$K,Metas!$B4,'Top Contas 04.07'!T:T) -> -2.083 | K4: =SUMIF('Top Contas 04.07'!$K:$K,Metas!$B4,'Top Contas 04.07'!U:U) -> 184.625 | L4: =SUMIF('Top Contas 04.07'!$K:$K,Metas!$B4,'Top Contas 04.07'!V:V) -> 0 | M4: =SUMIF('Top Contas 04.07'!$K:$K,Metas!$B4,'Top Contas 04.07'!W:W) -> 102.917 | N4: =SUMIF('Top Contas 04.07'!$K:$K,Metas!$B4,'Top Contas 04.07'!X:X) -> 84 | O4: =SUM(C4:N4) -> 1869.73 | Q4: 574.64 | R4: 492.54739 | S4: 463.25328 | T4: 495 | U4: 2036.6686 | V4: =IF(AVERAGE(C4,D4,E4,F4,G4,H4,I4,J4,K4,L4,M4,N4)>=500,"Diamante","Estrela") -> Estrela
B5: REDE MANENTI | C5: =SUMIF('Top Contas 04.07'!$K:$K,Metas!$B5,'Top Contas 04.07'!M:M) -> 97.179 | D5: =SUMIF('Top Contas 04.07'!$K:$K,Metas!$B5,'Top Contas 04.07'!N:N) -> 80.521 | E5: =SUMIF('Top Contas 04.07'!$K:$K,Metas!$B5,'Top Contas 04.07'!O:O) -> 1618.308 | F5: =SUMIF('Top Contas 04.07'!$K:$K,Metas!$B5,'Top Contas 04.07'!P:P) -> 219.521 | G5: =SUMIF('Top Contas 04.07'!$K:$K,Metas!$B5,'Top Contas 04.07'!Q:Q) -> 125.863 | H5: =SUMIF('Top Contas 04.07'!$K:$K,Metas!$B5,'Top Contas 04.07'!R:R) -> 672.5 | I5: =SUMIF('Top Contas 04.07'!$K:$K,Metas!$B5,'Top Contas 04.07'!S:S) -> 10.396 | J5: =SUMIF('Top Contas 04.07'!$K:$K,Metas!$B5,'Top Contas 04.07'!T:T) -> 70.463 | K5: =SUMIF('Top Contas 04.07'!$K:$K,Metas!$B5,'Top Contas 04.07'!U:U) -> 54.207 | L5: =SUMIF('Top Contas 04.07'!$K:$K,Metas!$B5,'Top Contas 04.07'!V:V) -> -3.583 | M5: =SUMIF('Top Contas 04.07'!$K:$K,Metas!$B5,'Top Contas 04.07'!W:W) -> 154.175 | N5: =SUMIF('Top Contas 04.07'!$K:$K,Metas!$B5,'Top Contas 04.07'!X:X) -> -15.007 | O5: =SUM(C5:N5) -> 3084.543 | Q5: 949.44 | R5: 813.80506 | S5: 765.40424 | T5: 816 | U5: 3443.123 | V5: =IF(AVERAGE(C5,D5,E5,F5,G5,H5,I5,J5,K5,L5,M5,N5)>=500,"Diamante","Estrela") -> Estrela
B6: REDE VENCEDOR | C6: =SUMIF('Top Contas 04.07'!$K:$K,Metas!$B6,'Top Contas 04.07'!M:M) -> -0.083 | D6: =SUMIF('Top Contas 04.07'!$K:$K,Metas!$B6,'Top Contas 04.07'!N:N) -> 120.583 | E6: =SUMIF('Top Contas 04.07'!$K:$K,Metas!$B6,'Top Contas 04.07'!O:O) -> 496.667 | F6: =SUMIF('Top Contas 04.07'!$K:$K,Metas!$B6,'Top Contas 04.07'!P:P) -> 117 | G6: =SUMIF('Top Contas 04.07'!$K:$K,Metas!$B6,'Top Contas 04.07'!Q:Q) -> 0 | H6: =SUMIF('Top Contas 04.07'!$K:$K,Metas!$B6,'Top Contas 04.07'!R:R) -> 290 | I6: =SUMIF('Top Contas 04.07'!$K:$K,Metas!$B6,'Top Contas 04.07'!S:S) -> -8 | J6: =SUMIF('Top Contas 04.07'!$K:$K,Metas!$B6,'Top Contas 04.07'!T:T) -> 215.708 | K6: =SUMIF('Top Contas 04.07'!$K:$K,Metas!$B6,'Top Contas 04.07'!U:U) -> 278 | L6: =SUMIF('Top Contas 04.07'!$K:$K,Metas!$B6,'Top Contas 04.07'!V:V) -> 32 | M6: =SUMIF('Top Contas 04.07'!$K:$K,Metas!$B6,'Top Contas 04.07'!W:W) -> 160.792 | N6: =SUMIF('Top Contas 04.07'!$K:$K,Metas!$B6,'Top Contas 04.07'!X:X) -> 67.833 | O6: =SUM(C6:N6) -> 1770.5 | Q6: 529.5 | R6: 453.85469 | S6: 426.86181 | T6: 456 | U6: 1818.8 | V6: =IF(AVERAGE(C6,D6,E6,F6,G6,H6,I6,J6,K6,L6,M6,N6)>=500,"Diamante","Estrela") -> Estrela
B7: REDE ABIMAR | C7: =SUMIF('Top Contas 04.07'!$K:$K,Metas!$B7,'Top Contas 04.07'!M:M) -> 118.792 | D7: =SUMIF('Top Contas 04.07'!$K:$K,Metas!$B7,'Top Contas 04.07'!N:N) -> 22.167 | E7: =SUMIF('Top Contas 04.07'!$K:$K,Metas!$B7,'Top Contas 04.07'!O:O) -> 914.167 | F7: =SUMIF('Top Contas 04.07'!$K:$K,Metas!$B7,'Top Contas 04.07'!P:P) -> 102.583 | G7: =SUMIF('Top Contas 04.07'!$K:$K,Metas!$B7,'Top Contas 04.07'!Q:Q) -> 127 | H7: =SUMIF('Top Contas 04.07'!$K:$K,Metas!$B7,'Top Contas 04.07'!R:R) -> 449.75 | I7: =SUMIF('Top Contas 04.07'!$K:$K,Metas!$B7,'Top Contas 04.07'!S:S) -> -2.858 | J7: =SUMIF('Top Contas 04.07'!$K:$K,Metas!$B7,'Top Contas 04.07'!T:T) -> 67.667 | K7: =SUMIF('Top Contas 04.07'!$K:$K,Metas!$B7,'Top Contas 04.07'!U:U) -> 193.854 | L7: =SUMIF('Top Contas 04.07'!$K:$K,Metas!$B7,'Top Contas 04.07'!V:V) -> 0.542 | M7: =SUMIF('Top Contas 04.07'!$K:$K,Metas!$B7,'Top Contas 04.07'!W:W) -> 56.333 | N7: =SUMIF('Top Contas 04.07'!$K:$K,Metas!$B7,'Top Contas 04.07'!X:X) -> 0 | O7: =SUM(C7:N7) -> 2049.997 | Q7: 632.71 | R7: 542.31898 | S7: 510.06472 | T7: 543 | U7: 2405.3261 | V7: =IF(AVERAGE(C7,D7,E7,F7,G7,H7,I7,J7,K7,L7,M7,N7)>=500,"Diamante","Estrela") -> Estrela
B8: REDE SM SILVEIRA | C8: =SUMIF('Top Contas 04.07'!$K:$K,Metas!$B8,'Top Contas 04.07'!M:M) -> 44.625 | D8: =SUMIF('Top Contas 04.07'!$K:$K,Metas!$B8,'Top Contas 04.07'!N:N) -> 854.875 | E8: =SUMIF('Top Contas 04.07'!$K:$K,Metas!$B8,'Top Contas 04.07'!O:O) -> 2.667 | F8: =SUMIF('Top Contas 04.07'!$K:$K,Metas!$B8,'Top Contas 04.07'!P:P) -> 259.313 | G8: =SUMIF('Top Contas 04.07'!$K:$K,Metas!$B8,'Top Contas 04.07'!Q:Q) -> 15 | H8: =SUMIF('Top Contas 04.07'!$K:$K,Metas!$B8,'Top Contas 04.07'!R:R) -> 194.583 | I8: =SUMIF('Top Contas 04.07'!$K:$K,Metas!$B8,'Top Contas 04.07'!S:S) -> 281.667 | J8: =SUMIF('Top Contas 04.07'!$K:$K,Metas!$B8,'Top Contas 04.07'!T:T) -> 202.666 | K8: =SUMIF('Top Contas 04.07'!$K:$K,Metas!$B8,'Top Contas 04.07'!U:U) -> 175.958 | L8: =SUMIF('Top Contas 04.07'!$K:$K,Metas!$B8,'Top Contas 04.07'!V:V) -> 50.791 | M8: =SUMIF('Top Contas 04.07'!$K:$K,Metas!$B8,'Top Contas 04.07'!W:W) -> 73.334 | N8: =SUMIF('Top Contas 04.07'!$K:$K,Metas!$B8,'Top Contas 04.07'!X:X) -> 57.708 | O8: =SUM(C8:N8) -> 2213.187 | Q8: 684.6 | R8: 586.80029 | S8: 551.90051 | T8: 588 | U8: 2485.6642 | V8: =IF(AVERAGE(C8,D8,E8,F8,G8,H8,I8,J8,K8,L8,M8,N8)>=500,"Diamante","Estrela") -> Estrela
B9: REDE COOPER AGRO | C9: =SUMIF('Top Contas 04.07'!$K:$K,Metas!$B9,'Top Contas 04.07'!M:M) -> 73.958 | D9: =SUMIF('Top Contas 04.07'!$K:$K,Metas!$B9,'Top Contas 04.07'!N:N) -> 2 | E9: =SUMIF('Top Contas 04.07'!$K:$K,Metas!$B9,'Top Contas 04.07'!O:O) -> 544.417 | F9: =SUMIF('Top Contas 04.07'!$K:$K,Metas!$B9,'Top Contas 04.07'!P:P) -> 6.333 | G9: =SUMIF('Top Contas 04.07'!$K:$K,Metas!$B9,'Top Contas 04.07'!Q:Q) -> 109.5 | H9: =SUMIF('Top Contas 04.07'!$K:$K,Metas!$B9,'Top Contas 04.07'!R:R) -> 11.625 | I9: =SUMIF('Top Contas 04.07'!$K:$K,Metas!$B9,'Top Contas 04.07'!S:S) -> 161.925 | J9: =SUMIF('Top Contas 04.07'!$K:$K,Metas!$B9,'Top Contas 04.07'!T:T) -> 47.275 | K9: =SUMIF('Top Contas 04.07'!$K:$K,Metas!$B9,'Top Contas 04.07'!U:U) -> 118.696 | L9: =SUMIF('Top Contas 04.07'!$K:$K,Metas!$B9,'Top Contas 04.07'!V:V) -> 34 | M9: =SUMIF('Top Contas 04.07'!$K:$K,Metas!$B9,'Top Contas 04.07'!W:W) -> 101 | N9: =SUMIF('Top Contas 04.07'!$K:$K,Metas!$B9,'Top Contas 04.07'!X:X) -> 183.5 | O9: =SUM(C9:N9) -> 1394.229 | Q9: 419.34 | R9: 359.43158 | S9: 338.0545 | T9: 360 | U9: 1291.5769 | V9: =IF(AVERAGE(C9,D9,E9,F9,G9,H9,I9,J9,K9,L9,M9,N9)>=500,"Diamante","Estrela") -> Estrela
B10: REDE FEGOAGRO | C10: =SUMIF('Top Contas 04.07'!$K:$K,Metas!$B10,'Top Contas 04.07'!M:M) -> 68 | D10: =SUMIF('Top Contas 04.07'!$K:$K,Metas!$B10,'Top Contas 04.07'!N:N) -> 512.625 | E10: =SUMIF('Top Contas 04.07'!$K:$K,Metas!$B10,'Top Contas 04.07'!O:O) -> 50.125 | F10: =SUMIF('Top Contas 04.07'!$K:$K,Metas!$B10,'Top Contas 04.07'!P:P) -> 34 | G10: =SUMIF('Top Contas 04.07'!$K:$K,Metas!$B10,'Top Contas 04.07'!Q:Q) -> 27.583 | H10: =SUMIF('Top Contas 04.07'!$K:$K,Metas!$B10,'Top Contas 04.07'!R:R) -> 118.486 | I10: =SUMIF('Top Contas 04.07'!$K:$K,Metas!$B10,'Top Contas 04.07'!S:S) -> 37.5 | J10: =SUMIF('Top Contas 04.07'!$K:$K,Metas!$B10,'Top Contas 04.07'!T:T) -> 21 | K10: =SUMIF('Top Contas 04.07'!$K:$K,Metas!$B10,'Top Contas 04.07'!U:U) -> 103.75 | L10: =SUMIF('Top Contas 04.07'!$K:$K,Metas!$B10,'Top Contas 04.07'!V:V) -> 43.333 | M10: =SUMIF('Top Contas 04.07'!$K:$K,Metas!$B10,'Top Contas 04.07'!W:W) -> 23 | N10: =SUMIF('Top Contas 04.07'!$K:$K,Metas!$B10,'Top Contas 04.07'!X:X) -> 22 | O10: =SUM(C10:N10) -> 1061.402 | Q10: 325.91 | R10: 279.3528 | S10: 262.73837 | T10: 282 | U10: 1256.6693 | V10: =IF(AVERAGE(C10,D10,E10,F10,G10,H10,I10,J10,K10,L10,M10,N10)>=500,"Diamante","Estrela") -> Estrela
B11: REDE ARCHER | C11: =SUMIF('Top Contas 04.07'!$K:$K,Metas!$B11,'Top Contas 04.07'!M:M) -> 504 | D11: =SUMIF('Top Contas 04.07'!$K:$K,Metas!$B11,'Top Contas 04.07'!N:N) -> 204.958 | E11: =SUMIF('Top Contas 04.07'!$K:$K,Metas!$B11,'Top Contas 04.07'!O:O) -> 999 | F11: =SUMIF('Top Contas 04.07'!$K:$K,Metas!$B11,'Top Contas 04.07'!P:P) -> 624 | G11: =SUMIF('Top Contas 04.07'!$K:$K,Metas!$B11,'Top Contas 04.07'!Q:Q) -> 945 | H11: =SUMIF('Top Contas 04.07'!$K:$K,Metas!$B11,'Top Contas 04.07'!R:R) -> 587 | I11: =SUMIF('Top Contas 04.07'!$K:$K,Metas!$B11,'Top Contas 04.07'!S:S) -> 517 | J11: =SUMIF('Top Contas 04.07'!$K:$K,Metas!$B11,'Top Contas 04.07'!T:T) -> 408 | K11: =SUMIF('Top Contas 04.07'!$K:$K,Metas!$B11,'Top Contas 04.07'!U:U) -> 1220.417 | L11: =SUMIF('Top Contas 04.07'!$K:$K,Metas!$B11,'Top Contas 04.07'!V:V) -> 179.25 | M11: =SUMIF('Top Contas 04.07'!$K:$K,Metas!$B11,'Top Contas 04.07'!W:W) -> 490 | N11: =SUMIF('Top Contas 04.07'!$K:$K,Metas!$B11,'Top Contas 04.07'!X:X) -> 409 | O11: =SUM(C11:N11) -> 7087.625 | Q11: 2181.26 | R11: 1869.6433 | S11: 1758.4468 | T11: 1872 | U11: 7756.6915 | V11: =IF(AVERAGE(C11,D11,E11,F11,G11,H11,I11,J11,K11,L11,M11,N11)>=500,"Diamante","Estrela") -> Diamante
B12: REDE UBER | C12: =SUMIF('Top Contas 04.07'!$K:$K,Metas!$B12,'Top Contas 04.07'!M:M) -> 28 | D12: =SUMIF('Top Contas 04.07'!$K:$K,Metas!$B12,'Top Contas 04.07'!N:N) -> 28.021 | E12: =SUMIF('Top Contas 04.07'!$K:$K,Metas!$B12,'Top Contas 04.07'!O:O) -> 611.083 | F12: =SUMIF('Top Contas 04.07'!$K:$K,Metas!$B12,'Top Contas 04.07'!P:P) -> 249.625 | G12: =SUMIF('Top Contas 04.07'!$K:$K,Metas!$B12,'Top Contas 04.07'!Q:Q) -> 41.042 | H12: =SUMIF('Top Contas 04.07'!$K:$K,Metas!$B12,'Top Contas 04.07'!R:R) -> 20 | I12: =SUMIF('Top Contas 04.07'!$K:$K,Metas!$B12,'Top Contas 04.07'!S:S) -> 69 | J12: =SUMIF('Top Contas 04.07'!$K:$K,Metas!$B12,'Top Contas 04.07'!T:T) -> 75.375 | K12: =SUMIF('Top Contas 04.07'!$K:$K,Metas!$B12,'Top Contas 04.07'!U:U) -> 222.25 | L12: =SUMIF('Top Contas 04.07'!$K:$K,Metas!$B12,'Top Contas 04.07'!V:V) -> 27.958 | M12: =SUMIF('Top Contas 04.07'!$K:$K,Metas!$B12,'Top Contas 04.07'!W:W) -> 6 | N12: =SUMIF('Top Contas 04.07'!$K:$K,Metas!$B12,'Top Contas 04.07'!X:X) -> 203 | O12: =SUM(C12:N12) -> 1581.354 | Q12: 482.46 | R12: 413.54064 | S12: 388.94543 | T12: 414 | U12: 1631.9422 | V12: =IF(AVERAGE(C12,D12,E12,F12,G12,H12,I12,J12,K12,L12,M12,N12)>=500,"Diamante","Estrela") -> Estrela
B13: REDE NILO GOEDERT | C13: =SUMIF('Top Contas 04.07'!$K:$K,Metas!$B13,'Top Contas 04.07'!M:M) -> 139.908 | D13: =SUMIF('Top Contas 04.07'!$K:$K,Metas!$B13,'Top Contas 04.07'!N:N) -> 1105 | E13: =SUMIF('Top Contas 04.07'!$K:$K,Metas!$B13,'Top Contas 04.07'!O:O) -> 355.167 | F13: =SUMIF('Top Contas 04.07'!$K:$K,Metas!$B13,'Top Contas 04.07'!P:P) -> 142 | G13: =SUMIF('Top Contas 04.07'!$K:$K,Metas!$B13,'Top Contas 04.07'!Q:Q) -> 493 | H13: =SUMIF('Top Contas 04.07'!$K:$K,Metas!$B13,'Top Contas 04.07'!R:R) -> 0 | I13: =SUMIF('Top Contas 04.07'!$K:$K,Metas!$B13,'Top Contas 04.07'!S:S) -> 63 | J13: =SUMIF('Top Contas 04.07'!$K:$K,Metas!$B13,'Top Contas 04.07'!T:T) -> 146 | K13: =SUMIF('Top Contas 04.07'!$K:$K,Metas!$B13,'Top Contas 04.07'!U:U) -> 432.583 | L13: =SUMIF('Top Contas 04.07'!$K:$K,Metas!$B13,'Top Contas 04.07'!V:V) -> 116.104 | M13: =SUMIF('Top Contas 04.07'!$K:$K,Metas!$B13,'Top Contas 04.07'!W:W) -> 75.667 | N13: =SUMIF('Top Contas 04.07'!$K:$K,Metas!$B13,'Top Contas 04.07'!X:X) -> 220 | O13: =SUM(C13:N13) -> 3288.429 | Q13: 985.46 | R13: 844.67923 | S13: 794.44218 | T13: 846 | U13: 3538.6745 | V13: =IF(AVERAGE(C13,D13,E13,F13,G13,H13,I13,J13,K13,L13,M13,N13)>=500,"Diamante","Estrela") -> Estrela
B14: REDE MESCHKE | C14: =SUMIF('Top Contas 04.07'!$K:$K,Metas!$B14,'Top Contas 04.07'!M:M) -> -0.667 | D14: =SUMIF('Top Contas 04.07'!$K:$K,Metas!$B14,'Top Contas 04.07'!N:N) -> 713.125 | E14: =SUMIF('Top Contas 04.07'!$K:$K,Metas!$B14,'Top Contas 04.07'!O:O) -> 552.75 | F14: =SUMIF('Top Contas 04.07'!$K:$K,Metas!$B14,'Top Contas 04.07'!P:P) -> 259.521 | G14: =SUMIF('Top Contas 04.07'!$K:$K,Metas!$B14,'Top Contas 04.07'!Q:Q) -> 12.458 | H14: =SUMIF('Top Contas 04.07'!$K:$K,Metas!$B14,'Top Contas 04.07'!R:R) -> 697.917 | I14: =SUMIF('Top Contas 04.07'!$K:$K,Metas!$B14,'Top Contas 04.07'!S:S) -> 60.167 | J14: =SUMIF('Top Contas 04.07'!$K:$K,Metas!$B14,'Top Contas 04.07'!T:T) -> 99.104 | K14: =SUMIF('Top Contas 04.07'!$K:$K,Metas!$B14,'Top Contas 04.07'!U:U) -> 532.125 | L14: =SUMIF('Top Contas 04.07'!$K:$K,Metas!$B14,'Top Contas 04.07'!V:V) -> 188 | M14: =SUMIF('Top Contas 04.07'!$K:$K,Metas!$B14,'Top Contas 04.07'!W:W) -> 40.083 | N14: =SUMIF('Top Contas 04.07'!$K:$K,Metas!$B14,'Top Contas 04.07'!X:X) -> 295 | O14: =SUM(C14:N14) -> 3449.583 | Q14: 1028.44 | R14: 881.52398 | S14: 829.09561 | T14: 882 | U14: 3760.0941 | V14: =IF(AVERAGE(C14,D14,E14,F14,G14,H14,I14,J14,K14,L14,M14,N14)>=500,"Diamante","Estrela") -> Estrela
... B16: REDE TOP | C16: =SUMIF('Top Contas 04.07'!$K:$K,Metas!$B16,'Top Contas 04.07'!M:M) -> 436.75 | D16: =SUMIF('Top Contas 04.07'!$K:$K,Metas!$B16,'Top Contas 04.07'!N:N) -> 239 | E16: =SUMIF('Top Contas 04.07'!$K:$K,Metas!$B16,'Top Contas 04.07'!O:O) -> 417 | F16: =SUMIF('Top Contas 04.07'!$K:$K,Metas!$B16,'Top Contas 04.07'!P:P) -> 2393.583 | G16: =SUMIF('Top Contas 04.07'!$K:$K,Metas!$B16,'Top Contas 04.07'!Q:Q) -> 1487.917 | H16: =SUMIF('Top Contas 04.07'!$K:$K,Metas!$B16,'Top Contas 04.07'!R:R) -> 1044.667 | I16: =SUMIF('Top Contas 04.07'!$K:$K,Metas!$B16,'Top Contas 04.07'!S:S) -> 339 | J16: =SUMIF('Top Contas 04.07'!$K:$K,Metas!$B16,'Top Contas 04.07'!T:T) -> 873.667 | K16: =SUMIF('Top Contas 04.07'!$K:$K,Metas!$B16,'Top Contas 04.07'!U:U) -> 198.583 | L16: =SUMIF('Top Contas 04.07'!$K:$K,Metas!$B16,'Top Contas 04.07'!V:V) -> 326.325 | M16: =SUMIF('Top Contas 04.07'!$K:$K,Metas!$B16,'Top Contas 04.07'!W:W) -> 606 | N16: =SUMIF('Top Contas 04.07'!$K:$K,Metas!$B16,'Top Contas 04.07'!X:X) -> 284.917 | O16: =SUM(C16:N16) -> 8647.409 | Q16: 2551.88 | R16: 2187.3287 | S16: 2057.2379 | T16: 2190 | U16: 8670.11 | V16: =IF(AVERAGE(C16,D16,E16,F16,G16,H16,I16,J16,K16,L16,M16,N16)>=500,"Diamante","Estrela") -> Diamante
C17: =SUM(C3:C16) -> 1856.139 | D17: =SUM(D3:D16) -> 4894.183 | E17: =SUM(E3:E16) -> 7589.477 | F17: =SUM(F3:F16) -> 6436.716 | G17: =SUM(G3:G16) -> 3615.471 | H17: =SUM(H3:H16) -> 4279.903 | I17: =SUM(I3:I16) -> 2064.847 | J17: =SUM(J3:J16) -> 2460.051 | ... O17: =SUM(O3:O16) -> 42134.62 | Q17: =SUM(Q3:Q16) -> 12641.68 | R17: =SUM(R3:R16) -> 10835.718 | S17: =SUM(S3:S16) -> 10191.267 | T17: =SUM(T3:T16) -> 10857 | U17: 45072.671

Sheet Top Contas 04.07
E1: d | K1: d | M1: JUL/2024 | N1: AGO/2024 | O1: SET/2024 | P1: OUT/2024 | Q1: NOV/2024 | R1: DEZ/2024 | S1: JAN/2025 | T1: FEV/2025 | U1: MAR/2025 | V1: ABR/2025 | W1: MAI/2025 | X1: JUN/2025
B2: FLP-SUL MC/KA D | C2: 771 | D2: MC-FLP D | E2: 142393 | F2: HIPER SELECT SUPERMERCADOS LTDA. | G2: FLORIANOPOLIS | H2: ROD SC 405 4400 | I2: CAMPECHE | J2: SM DE 05 A 09 CHECK-OUT | K2: REDE HIPER SELECT | L2: 040310260004-09 | M2: 270.844 | N2: 854.558 | O2: 525.542 | P2: 814.133 | Q2: 79.108 | R2: 100.167 | S2: 180.779 | T2: 47.792 | U2: 52.833 | V2: 14.333 | W2: 14.825 | X2: 15.238
B3: FLP-SUL MC/KA D | C3: 771 | D3: MC-FLP D | E3: 55070 | F3: HIPER SELECT SUPERMERCADOS LTDA | G3: FLORIANOPOLIS | H3: ROD DOUTOR ANTONIO LUIZ MOURA GONZA 2797 | I3: RIO TAVARES | J3: SM DE 10 A 19 CHECK-OUT | K3: REDE HIPER SELECT | L3: 036508310001-05 | M3: 0 | N3: 0 | O3: 0 | P3: 0 | Q3: 0 | R3: 0 | S3: 0 | T3: 0 | U3: 0 | V3: 0 | W3: 0 | X3: 0
B4: FLP-SUL MC/KA D | C4: 771 | D4: MC-FLP D | E4: 69413 | F4: SUPERMERCADO FELIPE ROYER LTDA | G4: FLORIANOPOLIS | H4: RUA FRANCISCO VIEIRA 465 | I4: MORRO DAS PEDRAS | J4: SM DE 02 A 04 CHECK-OUT | K4: REDE HIPER SELECT | L4: 040310260001-58 | M4: 0 | N4: 0 | O4: 0 | P4: 0 | Q4: 0 | R4: 0 | S4: 0 | T4: 0 | U4: 0 | V4: 0 | W4: 0 | X4: 0
B5: FLP-SUL MC/KA D | C5: 771 | D5: MC-FLP D | E5: 116011 | F5: SUPERMERCADO FELIPE ROYER LTDA | G5: FLORIANOPOLIS | H5: ROD ROD SC 406 4823 | I5: ARMACAO | J5: SM DE 02 A 04 CHECK-OUT | K5: REDE HIPER SELECT | L5: 040310260002-39 | M5: 0 | N5: 0 | O5: 0 | P5: 0 | Q5: 0 | R5: 0 | S5: 0 | T5: 0 | U5: 0 | V5: 0 | W5: 0 | X5: 0
B6: FLP-SUL MC/KA D | C6: 771 | D6: MC-FLP D | E6: 143128 | F6: HIPER SELECT SUPERMERCADOS LTDA. | G6: FLORIANOPOLIS | H6: AV PEQUENO PRINCIPE 1770 | I6: CAMPECHE | J6: SM DE 05 A 09 CHECK-OUT | K6: REDE HIPER SELECT | L6: 040310260003-10 | M6: 0 | N6: 0 | O6: 0 | P6: 0 | Q6: 0 | R6: 0 | S6: 0 | T6: 0 | U6: 0 | V6: 0 | W6: 0 | X6: 0
B7: FLP-SUL MC/KA D | C7: 771 | D7: MC-FLP D | E7: 171117 | F7: SUPERMERCADO FELIPE ROYER LTDA | G7: FLORIANOPOLIS | H7: RUA DEODORO 281 | I7: CENTRO | J7: SM DE 05 A 09 CHECK-OUT | K7: REDE HIPER SELECT | L7: 040310260006-62 | M7: 0 | N7: 0 | O7: 0 | P7: 0 | Q7: 0 | R7: 0 | S7: 0 | T7: 0 | U7: 0 | V7: 0 | W7: 0 | X7: 0
B8: FLP-SUL MC/KA D | C8: 771 | D8: MC-FLP D | E8: 184604 | F8: HIPER SELECT SUPERMERCADOS LTDA. | G8: FLORIANOPOLIS | H8: DOUTOR ANTONIO LUIZ MOURA GONZAGA 2797 | I8: RIO TAVARES | J8: CONVENIENCIA | K8: REDE HIPER SELECT | L8: 040310260009-05 | M8: 0 | N8: 0 | O8: 0 | P8: 0 | Q8: 0 | R8: 0 | S8: 0 | T8: 0 | U8: 0 | V8: 0 | W8: 0 | X8: 0
B9: FLP-SUL MC/KA D | C9: 771 | D9: MC-FLP D | E9: 185710 | F9: HIPER SELECT SUPERMERCADOS LTDA | G9: PALHOCA | H9: RUA ALCINO DOS NAVEGANTES MOREIRA 3010 | I9: BARRA DO ARIRIU | J9: SM DE 05 A 09 CHECK-OUT | K9: REDE HIPER SELECT | L9: 040310260008-24 | M9: 0 | N9: 0 | O9: 0 | P9: 0 | Q9: 0 | R9: 0 | S9: 0 | T9: 0 | U9: 0 | V9: 0 | W9: 0 | X9: 0
B10: FLP-SUL MC/KA D | C10: 771 | D10: MC-FLP D | E10: 185711 | F10: HIPER SELECT SUPERMERCADOS LTDA | G10: FLORIANOPOLIS | H10: RUA LAURINDO JANUARIO DA SILVEIRA 2308 | I10: LAGOA DA CONCEICAO | J10: SM DE 05 A 09 CHECK-OUT | K10: REDE HIPER SELECT | L10: 040310260010-49 | M10: 0 | N10: 0 | O10: 0 | P10: 0 | Q10: 0 | R10: 0 | S10: 0 | T10: 0 | U10: 0 | V10: 0 | W10: 0 | X10: 0
B11: FLP-SUL MC/KA D | C11: 771 | D11: MC-FLP D | E11: 185712 | F11: HIPER SELECT SUPERMERCADOS LTDA | G11: FLORIANOPOLIS | H11: AVENIDA CAMPECHE 2865 | I11: CAMPECHE | J11: SM DE 05 A 09 CHECK-OUT | K11: REDE HIPER SELECT | L11: 040310260011-20 | M11: 0 | N11: 0 | O11: 0 | P11: 0 | Q11: 0 | R11: 0 | S11: 0 | T11: 0 | U11: 0 | V11: 0 | W11: 0 | X11: 0
B12: FLP-SUL MC/KA D | C12: 771 | D12: MC-FLP D | E12: 185713 | F12: HIPER SELECT SUPERMERCADOS LTDA | G12: FLORIANOPOLIS | H12: RUA LAURINDO JANUARIO DA SILVEIRA 432 | I12: LAGOA DA CONCEICAO | J12: SM DE 05 A 09 CHECK-OUT | K12: REDE HIPER SELECT | L12: 040310260012-00 | M12: 0 | N12: 0 | O12: 0 | P12: 0 | Q12: 0 | R12: 0 | S12: 0 | T12: 0 | U12: 0 | V12: 0 | W12: 0 | X12: 0
B13: FLP-SUL MC/KA D | C13: 771 | D13: MC-FLP D | E13: 185714 | F13: HIPER SELECT SUPERMERCADOS LTDA | G13: FLORIANOPOLIS | H13: RUA JOAO PIO DUARTE SILVA 1630 | I13: CORREGO GRANDE | J13: SM DE 05 A 09 CHECK-OUT | K13: REDE HIPER SELECT | L13: 040310260013-91 | M13: 0 | N13: 0 | O13: 0 | P13: 0 | Q13: 0 | R13: 0 | S13: 0 | T13: 0 | U13: 0 | V13: 0 | W13: 0 | X13: 0
... B99: NORTE MC/KA M | C99: 3655 | D99: KA-BNU | E99: 189159 | F99: GTOP DISTRIBUICAO LTDA | G99: GASPAR | H99: ANFILOQUIO NUNES PIRES 4242 | I99: BELA VISTA | J99: SM DE 05 A 09 CHECK-OUT | K99: REDE TOP | L99: 188036540007-04 | M99: 0 | N99: 0 | O99: 0 | P99: 0 | Q99: 0 | R99: 0 | S99: 0 | T99: 0 | U99: 0 | V99: 0 | W99: 0 | X99: 0

Sheet Base
B1: HISTÓRICO JUL 2024 À JUN 2025 | G1: Relatório Pronto - 2824 - Top Contas - Cliente X MêsCompra x Ven. Liquida - JOHNSON - JULHO 25 A JUNHO 26 | M1: RELATÓRIO 2824 - CLIENTE X MÊS - COMPRA X V LIQUIDA - 525 | T1: PEDIDOS DE VENDA - NA MÁQUINA MÊS ATUAL
B2: Código Cliente | C2: Cliente | D2: Mês | E2: Quantidade | G2: VENDA DISTRIB | H2: Código Cliente | I2: Cliente | J2: Mês | K2: Quantidade | M2: BONIFICAÇÃO | N2: Código Cliente | O2: Cliente | P2: Mês | Q2: Quantidade | T2: CLIENTE X TOTAL - COMPRA X EX. FATURADO - JOHNSON | U2: Código Cliente | V2: Cliente | W2: Quantidade Atendida
C3: TOTAL | D3: 259 linhas | E3: 42134.62 | I3: TOTAL | J3: 319 linhas | K3: 41914.983 | O3: TOTAL | P3: 113 linhas | Q3: 866.415 | V3: TOTAL: 264 linhas | W3: 1005.657
A4: 158062 JUL/2024 | B4: 158062 | C4: ABIMAR SUPERMERCADOS LTDA | D4: JUL/2024 | E4: 118.792 | G4: =H4&J4 -> 158062 JUL/2025 | H4: 158062 | I4: ABIMAR SUPERMERCADOS LTDA | J4: JUL/2025 | K4: 166.813 | M4: =N4&P4 -> 158062 JUL/2025 | N4: 158062 | O4: ABIMAR SUPERMERCADOS LTDA | P4: JUL/2025 | Q4: 1 | U4: 189555 | V4: 58.911.277 GABRIEL JAQUES LUZ | W4: 0.167
A5: 158062 AGO/2024 | B5: 158062 | C5: ABIMAR SUPERMERCADOS LTDA | D5: AGO/2024 | E5: 4.542 | G5: =H5&J5 -> 158062 AGO/2025 | H5: 158062 | I5: ABIMAR SUPERMERCADOS LTDA | J5: AGO/2025 | K5: 682.542 | M5: =N5&P5 -> 158062 AGO/2025 | N5: 158062 | O5: ABIMAR SUPERMERCADOS LTDA | P5: AGO/2025 | Q5: 11 | U5: 67567 | V5: ABASTECEDORA AVENIDA DE COMBUSTIVEL LTDA | W5: 0.083
A6: 158062 SET/2024 | B6: 158062 | C6: ABIMAR SUPERMERCADOS LTDA | D6: SET/2024 | E6: 914.167 | G6: =H6&J6 -> 158062 SET/2025 | H6: 158062 | I6: ABIMAR SUPERMERCADOS LTDA | J6: SET/2025 | K6: 749.042 | M6: =N6&P6 -> 158062 SET/2025 | N6: 158062 | O6: ABIMAR SUPERMERCADOS LTDA | P6: SET/2025 | Q6: 3 | U6: 187623 | V6: ADRIANO FRANCISCO BARBOSA DA SILVA | W6: 0.25
A7: 158062 OUT/2024 | B7: 158062 | C7: ABIMAR SUPERMERCADOS LTDA | D7: OUT/2024 | E7: 102.583 | G7: =H7&J7 -> 158062 OUT/2025 | H7: 158062 | I7: ABIMAR SUPERMERCADOS LTDA | J7: OUT/2025 | K7: 98 | M7: =N7&P7 -> 158062 OUT/2025 | N7: 158062 | O7: ABIMAR SUPERMERCADOS LTDA | P7: OUT/2025 | Q7: 1 | U7: 187482 | V7: AGRO TROPICAL LTDA | W7: 0.146
A8: 158062 NOV/2024 | B8: 158062 | C8: ABIMAR SUPERMERCADOS LTDA | D8: NOV/2024 | E8: 127 | G8: =H8&J8 -> 158062 NOV/2025 | H8: 158062 | I8: ABIMAR SUPERMERCADOS LTDA | J8: NOV/2025 | K8: 237 | M8: =N8&P8 -> 158062 NOV/2025 | N8: 158062 | O8: ABIMAR SUPERMERCADOS LTDA | P8: NOV/2025 | Q8: 3 | U8: 62107 | V8: ALCIONE ZANOLLA ME | W8: 0.5
A9: 158062 DEZ/2024 | B9: 158062 | C9: ABIMAR SUPERMERCADOS LTDA | D9: DEZ/2024 | E9: 449.75 | G9: =H9&J9 -> 158062 DEZ/2025 | H9: 158062 | I9: ABIMAR SUPERMERCADOS LTDA | J9: DEZ/2025 | K9: 574.583 | M9: =N9&P9 -> 158062 DEZ/2025 | N9: 158062 | O9: ABIMAR SUPERMERCADOS LTDA | P9: DEZ/2025 | Q9: 16 | U9: 136970 | V9: ALESSANDRA SCARIOT CECHINEL | W9: 0.75
A10: 158062 JAN/2025 | B10: 158062 | C10: ABIMAR SUPERMERCADOS LTDA | D10: JAN/2025 | E10: -2.858 | G10: =H10&J10 -> 158062 JAN/2026 | H10: 158062 | I10: ABIMAR SUPERMERCADOS LTDA | J10: JAN/2026 | K10: 5.625 | M10: =N10&P10 -> 158062 JAN/2026 | N10: 158062 | O10: ABIMAR SUPERMERCADOS LTDA | P10: JAN/2026 | Q10: 1.5 | U10: 191283 | V10: ALEXANDRE DOS SANTOS DIATEL | W10: 0.167
A11: 158062 FEV/2025 | B11: 158062 | C11: ABIMAR SUPERMERCADOS LTDA | D11: FEV/2025 | E11: 67.667 | G11: =H11&J11 -> 158062 FEV/2026 | H11: 158062 | I11: ABIMAR SUPERMERCADOS LTDA | J11: FEV/2026 | K11: 56.833 | M11: =N11&P11 -> 158062 FEV/2026 | N11: 158062 | O11: ABIMAR SUPERMERCADOS LTDA | P11: FEV/2026 | Q11: 2 | U11: 126883 | V11: ALTAMIR SERRAO E CIA LTDA | W11: 0.375
A12: 158062 MAR/2025 | B12: 158062 | C12: ABIMAR SUPERMERCADOS LTDA | D12: MAR/2025 | E12: 193.854 | G12: =H12&J12 -> 158062 MAR/2026 | H12: 158062 | I12: ABIMAR SUPERMERCADOS LTDA | J12: MAR/2026 | K12: 239.333 | M12: =N12&P12 -> 158062 MAR/2026 | N12: 158062 | O12: ABIMAR SUPERMERCADOS LTDA | P12: MAR/2026 | Q12: 32 | U12: 68379 | V12: ALTHOFF SUPERMERCADOS LTDA | W12: 53
A13: 158062 ABR/2025 | B13: 158062 | C13: ABIMAR SUPERMERCADOS LTDA | D13: ABR/2025 | E13: 0.542 | G13: =H13&J13 -> 158062 ABR/2026 | H13: 158062 | I13: ABIMAR SUPERMERCADOS LTDA | J13: ABR/2026 | K13: 44.917 | M13: =N13&P13 -> 158062 ABR/2026 | N13: 158062 | O13: ABIMAR SUPERMERCADOS LTDA | P13: ABR/2026 | Q13: 4.083 | U13: 190591 | V13: AMANDA CARVALHO POLLHEIM | W13: 0.125
A14: 158062 MAI/2025 | B14: 158062 | C14: ABIMAR SUPERMERCADOS LTDA | D14: MAI/2025 | E14: 56.333 | G14: =H14&J14 -> 158062 MAI/2026 | H14: 158062 | I14: ABIMAR SUPERMERCADOS LTDA | J14: MAI/2026 | K14: 193.25 | M14: =N14&P14 -> 158062 MAI/2026 | N14: 158062 | O14: ABIMAR SUPERMERCADOS LTDA | P14: MAI/2026 | Q14: 18 | U14: 138135 | V14: ANDERSON PIMENTEL SUPERMERCADO LTDA | W14: 0.75
A15: 159620 AGO/2024 | B15: 159620 | C15: ABIMAR SUPERMERCADOS LTDA | D15: AGO/2024 | E15: 5.875 | G15: =H15&J15 -> 158062 JUN/2026 | H15: 158062 | I15: ABIMAR SUPERMERCADOS LTDA | J15: JUN/2026 | K15: 310.833 | M15: =N15&P15 -> 158062 JUN/2026 | N15: 158062 | O15: ABIMAR SUPERMERCADOS LTDA | P15: JUN/2026 | Q15: 9 | U15: 80160 | V15: ARCELINA MARIA ELIAS SEIDEL ME | W15: 1.438
... A116: 132039 SET/2024 | B116: 132039 | C116: NILSON ARNALDO DA SILVA E CIA LTDA | D116: SET/2024 | E116: 573.083 | G116: =H116&J116 -> 65205 FEV/2026 | H116: 65205 | I116: M M ROSSO SUPERMERCADO LTDA | J116: FEV/2026 | K116: 3 | M116: =N116&P116 -> 48374 DEZ/2025 | N116: 48374 | O116: VENCEDOR ATACADISTA LTDA | P116: DEZ/2025 | Q116: 2 | U116: 186304 | V116: MARIA TARCILA GESSELE | W116: 0.5
A117: 132039 OUT/2024 | B117: 132039 | C117: NILSON ARNALDO DA SILVA E CIA LTDA | D117: OUT/2024 | E117: 131 | G117: =H117&J117 -> 65205 MAR/2026 | H117: 65205 | I117: M M ROSSO SUPERMERCADO LTDA | J117: MAR/2026 | K117: 3 | U117: 179564 | V117: MARIZIE HELENA DA SILVA ANGELI | W117: 0.125
A118: 132039 NOV/2024 | B118: 132039 | C118: NILSON ARNALDO DA SILVA E CIA LTDA | D118: NOV/2024 | E118: 11 | G118: =H118&J118 -> 166720 FEV/2026 | H118: 166720 | I118: M M ROSSO SUPERMERCADO LTDA | J118: FEV/2026 | K118: 3 | U118: 168379 | V118: MAYARA TUANE MARTINS EPP | W118: 0.875
A119: 132039 JAN/2025 | B119: 132039 | C119: NILSON ARNALDO DA SILVA E CIA LTDA | D119: JAN/2025 | E119: 35 | G119: =H119&J119 -> 184214 FEV/2026 | H119: 184214 | I119: M M ROSSO SUPERMERCADO LTDA | J119: FEV/2026 | K119: 3 | U119: 58781 | V119: MERCADINHO IRMAOS SCHMITT LTDA | W119: 6
A120: 132039 FEV/2025 | B120: 132039 | C120: NILSON ARNALDO DA SILVA E CIA LTDA | D120: FEV/2025 | E120: 5 | G120: =H120&J120 -> 184221 OUT/2025 | H120: 184221 | I120: M M ROSSO SUPERMERCADO LTDA | J120: OUT/2025 | K120: 5.875 | U120: 171581 | V120: MERCADO C MAIS LTDA | W120: 2
A121: 132039 MAR/2025 | B121: 132039 | C121: NILSON ARNALDO DA SILVA E CIA LTDA | D121: MAR/2025 | E121: 221.25 | G121: =H121&J121 -> 184221 FEV/2026 | H121: 184221 | I121: M M ROSSO SUPERMERCADO LTDA | J121: FEV/2026 | K121: 3 | U121: 179244 | V121: MERCADO CAMELIA LTDA | W121: 0.292
A122: 132039 JUN/2025 | B122: 132039 | C122: NILSON ARNALDO DA SILVA E CIA LTDA | D122: JUN/2025 | E122: 195 | G122: =H122&J122 -> 131538 MAR/2026 | H122: 131538 | I122: M M ROSSO SUPERMERCADO LTDA FL 03 | J122: MAR/2026 | K122: 3 | U122: 49712 | V122: MERCADO CAMPOS SALLES LTDA | W122: 1.813
A123: 168551 JUL/2024 | B123: 168551 | C123: NILSON ARNALDO DA SILVA E CIA LTDA | D123: JUL/2024 | E123: 28 | G123: =H123&J123 -> 131539 FEV/2026 | H123: 131539 | I123: M M ROSSO SUPERMERCADO LTDA FL 04 | J123: FEV/2026 | K123: 3 | U123: 170658 | V123: MERCADO CARIJOS LTDA | W123: 0.25
